Workbook
Name \0: #REF!
Name \054: #N/A
Name \a: #REF!
Name \b: #REF!
Name \c: #REF!
Name \CARBU: #REF!
Name \DOLAR: #REF!
Name \e: #REF!
Name \f: #REF!
Name \FA: #REF!
Name \g: #REF!
Name \GSGRAL: #REF!
Name \h: #REF!
Name \HORAS: #REF!
Name \JORNAL: #REF!
Name \k: #REF!
Name \l: #REF!
Name \m: #REF!
Name \n: #REF!
Name \ñ: #REF!
Name \OBR: #REF!
Name \OWNER: #REF!
Name \p: #REF!
Name \R: #REF!
Name \REPREP: #REF!
Name \RUBROS: #REF!
Name \s: #REF!
Name \SUELDOS: #REF!
Name \t: #REF!
Name \TITULO: #REF!
Name \VIAJES: #REF!
Name \w: #REF!
Name \x: #REF!
Name \y: #REF!
Name \z: #REF!
Name _: #REF!
Name _______Rev1: #REF!
Name _______Rev2: #REF!
Name _______Rev3: #REF!
Name ______Rev1: #REF!
Name ______Rev2: #REF!
Name ______Rev3: #REF!
Name ______Rev4: #REF!
Name _____Rev1: #REF!
Name _____Rev2: #REF!
Name _____Rev3: #REF!
Name _____Rev4: #REF!
Name ____Rev1: #REF!
Name ____Rev2: #REF!
Name ____Rev3: #REF!
Name ____Rev4: #REF!
Name ___ACC53: #REF!
Name ___ACC54: #REF!
Name ___ACC56: #REF!
Name ___asp2: #REF!
Name ___BUT38: #REF!
Name ___BUT78: #REF!
Name ___F15p: #REF!
Name ___fc: #REF!
Name ___Ind1: #REF!

Sheet Preliminar
A1: SUMINISTROS PROYECTO XX | D1: TAG | E1: RI | J1: Emisión y liberación de Solped | R1: Recepción de ofertas | Y1: AT REV A | AC1: AT REV 0 | AJ1: Emisión OC | AV1: Fabricación | BC1: Transporte Internacional (incluida gestión comex+transporte) | BJ1: Nacionalización (tiempo Comex para nacionalizar) | BQ1: Transporte Local | BX1: Necesidad Construcciónes | BY1: Impacto Costrucciones | CB1: -30 | CC1: 0
CB2: 1 | CC2: 90
A3: ESP | B3: Requisición N° | C3: DESCRIPCION | D3: N° | E3: Final Prog | F3: Forecast | G3: Real | H3: Desvío | J3: Inicio Prog | K3: Final Prog | L3: Duración | M3: Forecast | N3: Real | O3: Desvío Acum | P3: N° Cesta/Solped | R3: Inicio Prog | S3: Final Prog | T3: Duración | U3: Forecast | V3: Real | W3: Desvío Acum | Y3: Final Prog | Z3: Real | AA3: Desvío Acum | AC3: Inicio Prog | AD3: Final Prog | AE3: Duración | AF3: Forecast | AG3: Real | AH3: Desvío Acum | AJ3: Inicio Prog | AK3: Final Prog | AL3: Duración | AM3: Forecast | AN3: Real | AO3: Desvío Acum | AP3: N° OC | AQ3: Pos | AR3: Proveedor | AS3: Fecha de Entrega | AT3: Lugar de entrega | AV3: Inicio Prog | AW3: Final Prog | AX3: Duración | AY3: Forecast | AZ3: Real | BA3: Desvío Acum | BC3: Inicio Prog | BD3: Final Prog | BE3: Duración | BF3: Forecast | BG3: Real | BH3: Desvío Acum | BJ3: Inicio Prog | BK3: Final Prog | BL3: Duración | BM3: Forecast | BN3: Real | BO3: Desvío Acum | BQ3: Inicio Prog | BR3: Final Prog | BS3: Duración | BT3: Forecast | BU3: Real | BV3: Desvío Acum
A4: CI-Civil | C4: RI Ignifugado | D4: - | E4: =+J4-1 -> 45389 | F4: 45371 | H4: =+F4-E4 -> -18 | J4: =+K4-L4 -> 45390 | K4: =+R4-1 -> 45397 | L4: 7 | M4: =+F4+L4 -> 45378 | O4: =+M4-K4 -> -19 | R4: =+S4-T4 -> 45398 | S4: =+AC4-1 -> 45419 | T4: 21 | U4: =+M4+T4 -> 45399 | W4: =+U4-S4 -> -20 | Y4: - | Z4: - | AA4: - | AC4: =+AD4-AE4 -> 45420 | AD4: =+AJ4-1 -> 45434 | AE4: 14 | AF4: =+IF(V4=0,U4,V4)+AE4 -> 45413 | AH4: =+AF4-AD4 -> -21 | AJ4: =+AK4-AL4 -> 45435 | AK4: =+AV4-1 -> 45449 | AL4: 14 | AM4: =+IF(AG4=0,AF4,AG4)+AL4 -> 45427 | AO4: =+AM4-AK4 -> -22 | AV4: =+AW4-AX4 -> 45450 | AW4: =+BQ4-1 -> 45540 | AX4: 90 | AY4: =+IF(AN4=0,AM4,AN4)+AX4 -> 45517 | BA4: =+AY4-AW4 -> -23 | BC4: =+BD4-BE4 -> 45541 | BD4: =+BJ4 -> 45541 | BE4: 0 | BF4: =+IF(AZ4=0,AY4,AZ4)+BE4 -> 45517 | BH4: =+BF4-BD4 -> -24 | BJ4: =+BK4-BL4 -> 45541 | BK4: =+BQ4 -> 45541 | BL4: 0 | BM4: =+IF(BG4=0,BF4,BG4)+BL4 -> 45517 | BO4: =+BM4-BK4 -> -24 | BQ4: =+BR4-BS4 -> 45541 | BR4: =+BX4 -> 45547 | BS4: 6 | BT4: =+IF(BN4=0,BM4,BN4)+BS4 -> 45523 | BV4: =+BT4-BR4 -> -24 | BX4: 45547 | BY4: =+BT4-BX4 -> -24
A5: CI-Civil | C5: RI Tinglado de compresores | E5: =+J5-1 -> 45359 | F5: 45371 | H5: =+F5-E5 -> 12 | J5: =+K5-L5 -> 45360 | K5: =+R5-1 -> 45367 | L5: 7 | M5: =+F5+L5 -> 45378 | O5: =+M5-K5 -> 11 | R5: =+S5-T5 -> 45368 | S5: =+AC5-1 -> 45389 | T5: 21 | U5: =+M5+T5 -> 45399 | W5: =+U5-S5 -> 10 | AC5: =+AD5-AE5 -> 45390 | AD5: =+AJ5-1 -> 45404 | AE5: 14 | AF5: =+IF(V5=0,U5,V5)+AE5 -> 45413 | AH5: =+AF5-AD5 -> 9 | AJ5: =+AK5-AL5 -> 45405 | AK5: =+AV5-1 -> 45419 | AL5: 14 | AM5: =+IF(AG5=0,AF5,AG5)+AL5 -> 45427 | AO5: =+AM5-AK5 -> 8 | AV5: =+AW5-AX5 -> 45420 | AW5: =+BQ5-1 -> 45540 | AX5: 120 | AY5: =+IF(AN5=0,AM5,AN5)+AX5 -> 45547 | BA5: =+AY5-AW5 -> 7 | BC5: =+BD5-BE5 -> 45541 | BD5: =+BJ5 -> 45541 | BE5: 0 | BF5: =+IF(AZ5=0,AY5,AZ5)+BE5 -> 45547 | BH5: =+BF5-BD5 -> 6 | BJ5: =+BK5-BL5 -> 45541 | BK5: =+BQ5 -> 45541 | BL5: 0 | BM5: =+IF(BG5=0,BF5,BG5)+BL5 -> 45547 | BO5: =+BM5-BK5 -> 6 | BQ5: =+BR5-BS5 -> 45541 | BR5: =+BX5 -> 45547 | BS5: 6 | BT5: =+IF(BN5=0,BM5,BN5)+BS5 -> 45553 | BV5: =+BT5-BR5 -> 6 | BX5: 45547 | BY5: =+BT5-BX5 -> 6
A6: CI-Civil | C6: RI Shelter remotas | E6: =+J6-1 -> 45329 | F6: 45371 | H6: =+F6-E6 -> 42 | J6: =+K6-L6 -> 45330 | K6: =+R6-1 -> 45337 | L6: 7 | M6: =+F6+L6 -> 45378 | O6: =+M6-K6 -> 41 | R6: =+S6-T6 -> 45338 | S6: =+AC6-1 -> 45359 | T6: 21 | U6: =+M6+T6 -> 45399 | W6: =+U6-S6 -> 40 | AC6: =+AD6-AE6 -> 45360 | AD6: =+AJ6-1 -> 45374 | AE6: 14 | AF6: =+IF(V6=0,U6,V6)+AE6 -> 45413 | AH6: =+AF6-AD6 -> 39 | AJ6: =+AK6-AL6 -> 45375 | AK6: =+AV6-1 -> 45389 | AL6: 14 | AM6: =+IF(AG6=0,AF6,AG6)+AL6 -> 45427 | AO6: =+AM6-AK6 -> 38 | AV6: =+AW6-AX6 -> 45390 | AW6: =+BQ6-1 -> 45540 | AX6: 150 | AY6: =+IF(AN6=0,AM6,AN6)+AX6 -> 45577 | BA6: =+AY6-AW6 -> 37 | BC6: =+BD6-BE6 -> 45541 | BD6: =+BJ6 -> 45541 | BE6: 0 | BF6: =+IF(AZ6=0,AY6,AZ6)+BE6 -> 45577 | BH6: =+BF6-BD6 -> 36 | BJ6: =+BK6-BL6 -> 45541 | BK6: =+BQ6 -> 45541 | BL6: 0 | BM6: =+IF(BG6=0,BF6,BG6)+BL6 -> 45577 | BO6: =+BM6-BK6 -> 36 | BQ6: =+BR6-BS6 -> 45541 | BR6: =+BX6 -> 45547 | BS6: 6 | BT6: =+IF(BN6=0,BM6,BN6)+BS6 -> 45583 | BV6: =+BT6-BR6 -> 36 | BX6: 45547 | BY6: =+BT6-BX6 -> 36
A7: CI-Civil | C7: RI Estructuras metalicas | E7: =+J7-1 -> 45359 | F7: 45371 | H7: =+F7-E7 -> 12 | J7: =+K7-L7 -> 45360 | K7: =+R7-1 -> 45367 | L7: 7 | M7: =+F7+L7 -> 45378 | O7: =+M7-K7 -> 11 | R7: =+S7-T7 -> 45368 | S7: =+AC7-1 -> 45389 | T7: 21 | U7: =+M7+T7 -> 45399 | W7: =+U7-S7 -> 10 | AC7: =+AD7-AE7 -> 45390 | AD7: =+AJ7-1 -> 45404 | AE7: 14 | AF7: =+IF(V7=0,U7,V7)+AE7 -> 45413 | AH7: =+AF7-AD7 -> 9 | AJ7: =+AK7-AL7 -> 45405 | AK7: =+AV7-1 -> 45419 | AL7: 14 | AM7: =+IF(AG7=0,AF7,AG7)+AL7 -> 45427 | AO7: =+AM7-AK7 -> 8 | AV7: =+AW7-AX7 -> 45420 | AW7: =+BQ7-1 -> 45540 | AX7: 120 | AY7: =+IF(AN7=0,AM7,AN7)+AX7 -> 45547 | BA7: =+AY7-AW7 -> 7 | BC7: =+BD7-BE7 -> 45541 | BD7: =+BJ7 -> 45541 | BE7: 0 | BF7: =+IF(AZ7=0,AY7,AZ7)+BE7 -> 45547 | BH7: =+BF7-BD7 -> 6 | BJ7: =+BK7-BL7 -> 45541 | BK7: =+BQ7 -> 45541 | BL7: 0 | BM7: =+IF(BG7=0,BF7,BG7)+BL7 -> 45547 | BO7: =+BM7-BK7 -> 6 | BQ7: =+BR7-BS7 -> 45541 | BR7: =+BX7 -> 45547 | BS7: 6 | BT7: =+IF(BN7=0,BM7,BN7)+BS7 -> 45553 | BV7: =+BT7-BR7 -> 6 | BX7: 45547 | BY7: =+BT7-BX7 -> 6
A8: CI-Civil | C8: RI Estructuras de hormigon premoldeado | E8: =+J8-1 -> 45359 | F8: 45371 | H8: =+F8-E8 -> 12 | J8: =+K8-L8 -> 45360 | K8: =+R8-1 -> 45367 | L8: 7 | M8: =+F8+L8 -> 45378 | O8: =+M8-K8 -> 11 | R8: =+S8-T8 -> 45368 | S8: =+AC8-1 -> 45389 | T8: 21 | U8: =+M8+T8 -> 45399 | W8: =+U8-S8 -> 10 | AC8: =+AD8-AE8 -> 45390 | AD8: =+AJ8-1 -> 45404 | AE8: 14 | AF8: =+IF(V8=0,U8,V8)+AE8 -> 45413 | AH8: =+AF8-AD8 -> 9 | AJ8: =+AK8-AL8 -> 45405 | AK8: =+AV8-1 -> 45419 | AL8: 14 | AM8: =+IF(AG8=0,AF8,AG8)+AL8 -> 45427 | AO8: =+AM8-AK8 -> 8 | AV8: =+AW8-AX8 -> 45420 | AW8: =+BQ8-1 -> 45540 | AX8: 120 | AY8: =+IF(AN8=0,AM8,AN8)+AX8 -> 45547 | BA8: =+AY8-AW8 -> 7 | BC8: =+BD8-BE8 -> 45541 | BD8: =+BJ8 -> 45541 | BE8: 0 | BF8: =+IF(AZ8=0,AY8,AZ8)+BE8 -> 45547 | BH8: =+BF8-BD8 -> 6 | BJ8: =+BK8-BL8 -> 45541 | BK8: =+BQ8 -> 45541 | BL8: 0 | BM8: =+IF(BG8=0,BF8,BG8)+BL8 -> 45547 | BO8: =+BM8-BK8 -> 6 | BQ8: =+BR8-BS8 -> 45541 | BR8: =+BX8 -> 45547 | BS8: 6 | BT8: =+IF(BN8=0,BM8,BN8)+BS8 -> 45553 | BV8: =+BT8-BR8 -> 6 | BX8: 45547 | BY8: =+BT8-BX8 -> 6
A9: CI-Civil | C9: RI Misceláneos (membranas, anclajes 2da etapa, etc) | E9: =+J9-1 -> 45389 | F9: 45371 | H9: =+F9-E9 -> -18 | J9: =+K9-L9 -> 45390 | K9: =+R9-1 -> 45397 | L9: 7 | M9: =+F9+L9 -> 45378 | O9: =+M9-K9 -> -19 | R9: =+S9-T9 -> 45398 | S9: =+AC9-1 -> 45419 | T9: 21 | U9: =+M9+T9 -> 45399 | W9: =+U9-S9 -> -20 | AC9: =+AD9-AE9 -> 45420 | AD9: =+AJ9-1 -> 45434 | AE9: 14 | AF9: =+IF(V9=0,U9,V9)+AE9 -> 45413 | AH9: =+AF9-AD9 -> -21 | AJ9: =+AK9-AL9 -> 45435 | AK9: =+AV9-1 -> 45449 | AL9: 14 | AM9: =+IF(AG9=0,AF9,AG9)+AL9 -> 45427 | AO9: =+AM9-AK9 -> -22 | AV9: =+AW9-AX9 -> 45450 | AW9: =+BQ9-1 -> 45540 | AX9: 90 | AY9: =+IF(AN9=0,AM9,AN9)+AX9 -> 45517 | BA9: =+AY9-AW9 -> -23 | BC9: =+BD9-BE9 -> 45541 | BD9: =+BJ9 -> 45541 | BE9: 0 | BF9: =+IF(AZ9=0,AY9,AZ9)+BE9 -> 45517 | BH9: =+BF9-BD9 -> -24 | BJ9: =+BK9-BL9 -> 45541 | BK9: =+BQ9 -> 45541 | BL9: 0 | BM9: =+IF(BG9=0,BF9,BG9)+BL9 -> 45517 | BO9: =+BM9-BK9 -> -24 | BQ9: =+BR9-BS9 -> 45541 | BR9: =+BX9 -> 45547 | BS9: 6 | BT9: =+IF(BN9=0,BM9,BN9)+BS9 -> 45523 | BV9: =+BT9-BR9 -> -24 | BX9: 45547 | BY9: =+BT9-BX9 -> -24
A10: CI-Civil | C10: RI Relevamiento topgorafico | E10: =+J10-1 -> 45329 | F10: 45350 | H10: =+F10-E10 -> 21 | J10: =+K10-L10 -> 45330 | K10: =+R10-1 -> 45337 | L10: 7 | M10: =+F10+L10 -> 45357 | O10: =+M10-K10 -> 20 | R10: =+S10-T10 -> 45338 | S10: =+AC10-1 -> 45359 | T10: 21 | U10: =+M10+T10 -> 45378 | W10: =+U10-S10 -> 19 | AC10: =+AD10-AE10 -> 45360 | AD10: =+AJ10-1 -> 45374 | AE10: 14 | AF10: =+IF(V10=0,U10,V10)+AE10 -> 45392 | AH10: =+AF10-AD10 -> 18 | AJ10: =+AK10-AL10 -> 45375 | AK10: =+AV10-1 -> 45389 | AL10: 14 | AM10: =+IF(AG10=0,AF10,AG10)+AL10 -> 45406 | AO10: =+AM10-AK10 -> 17 | AV10: =+AW10-AX10 -> 45390 | AW10: =+BQ10-1 -> 45435 | AX10: 45 | AY10: =+IF(AN10=0,AM10,AN10)+AX10 -> 45451 | BA10: =+AY10-AW10 -> 16 | BC10: =+BD10-BE10 -> 45436 | BD10: =+BJ10 -> 45436 | BE10: 0 | BF10: =+IF(AZ10=0,AY10,AZ10)+BE10 -> 45451 | BH10: =+BF10-BD10 -> 15 | BJ10: =+BK10-BL10 -> 45436 | BK10: =+BQ10 -> 45436 | BL10: 0 | BM10: =+IF(BG10=0,BF10,BG10)+BL10 -> 45451 | BO10: =+BM10-BK10 -> 15 | BQ10: =+BR10-BS10 -> 45436 | BR10: =+BX10 -> 45442 | BS10: 6 | BT10: =+IF(BN10=0,BM10,BN10)+BS10 -> 45457 | BV10: =+BT10-BR10 -> 15 | BX10: 45442 | BY10: =+BT10-BX10 -> 15
A11: CI-Civil | C11: RI Detección de Interferencias enterradas (georadar) | E11: =+J11-1 -> 45329 | F11: 45350 | H11: =+F11-E11 -> 21 | J11: =+K11-L11 -> 45330 | K11: =+R11-1 -> 45337 | L11: 7 | M11: =+F11+L11 -> 45357 | O11: =+M11-K11 -> 20 | R11: =+S11-T11 -> 45338 | S11: =+AC11-1 -> 45359 | T11: 21 | U11: =+M11+T11 -> 45378 | W11: =+U11-S11 -> 19 | AC11: =+AD11-AE11 -> 45360 | AD11: =+AJ11-1 -> 45374 | AE11: 14 | AF11: =+IF(V11=0,U11,V11)+AE11 -> 45392 | AH11: =+AF11-AD11 -> 18 | AJ11: =+AK11-AL11 -> 45375 | AK11: =+AV11-1 -> 45389 | AL11: 14 | AM11: =+IF(AG11=0,AF11,AG11)+AL11 -> 45406 | AO11: =+AM11-AK11 -> 17 | AV11: =+AW11-AX11 -> 45390 | AW11: =+BQ11-1 -> 45435 | AX11: 45 | AY11: =+IF(AN11=0,AM11,AN11)+AX11 -> 45451 | BA11: =+AY11-AW11 -> 16 | BC11: =+BD11-BE11 -> 45436 | BD11: =+BJ11 -> 45436 | BE11: 0 | BF11: =+IF(AZ11=0,AY11,AZ11)+BE11 -> 45451 | BH11: =+BF11-BD11 -> 15 | BJ11: =+BK11-BL11 -> 45436 | BK11: =+BQ11 -> 45436 | BL11: 0 | BM11: =+IF(BG11=0,BF11,BG11)+BL11 -> 45451 | BO11: =+BM11-BK11 -> 15 | BQ11: =+BR11-BS11 -> 45436 | BR11: =+BX11 -> 45442 | BS11: 6 | BT11: =+IF(BN11=0,BM11,BN11)+BS11 -> 45457 | BV11: =+BT11-BR11 -> 15 | BX11: 45442 | BY11: =+BT11-BX11 -> 15
A12: IN-Instrumentación y Control | C12: Requisición de Ingeniería Transmisor de Presión | E12: =+J12-1 -> 45407 | F12: 45397 | H12: =+F12-E12 -> -10 | J12: =+K12-L12 -> 45408 | K12: =+R12-1 -> 45415 | L12: 7 | M12: =+F12+L12 -> 45404 | O12: =+M12-K12 -> -11 | R12: =+S12-T12 -> 45416 | S12: =+AC12-1 -> 45437 | T12: 21 | U12: =+M12+T12 -> 45425 | W12: =+U12-S12 -> -12 | AC12: =+AD12-AE12 -> 45438 | AD12: =+AJ12-1 -> 45468 | AE12: 30 | AF12: =+IF(V12=0,U12,V12)+AE12 -> 45455 | AH12: =+AF12-AD12 -> -13 | AJ12: =+AK12-AL12 -> 45469 | AK12: =+AV12-1 -> 45483 | AL12: 14 | AM12: =+IF(AG12=0,AF12,AG12)+AL12 -> 45469 | AO12: =+AM12-AK12 -> -14 | AV12: =+AW12-AX12 -> 45484 | AW12: =+BQ12-1 -> 45634 | AX12: 150 | AY12: =+IF(AN12=0,AM12,AN12)+AX12 -> 45619 | BA12: =+AY12-AW12 -> -15 | BC12: =+BD12-BE12 -> 45635 | BD12: =+BJ12 -> 45635 | BE12: 0 | BF12: =+IF(AZ12=0,AY12,AZ12)+BE12 -> 45619 | BH12: =+BF12-BD12 -> -16 | BJ12: =+BK12-BL12 -> 45635 | BK12: =+BQ12 -> 45635 | BL12: 0 | BM12: =+IF(BG12=0,BF12,BG12)+BL12 -> 45619 | BO12: =+BM12-BK12 -> -16 | BQ12: =+BR12-BS12 -> 45635 | BR12: =+BX12 -> 45641 | BS12: 6 | BT12: =+IF(BN12=0,BM12,BN12)+BS12 -> 45625 | BV12: =+BT12-BR12 -> -16 | BX12: 45641 | BY12: =+BT12-BX12 -> -16
A13: IN-Instrumentación y Control | C13: Requisición de Ingeniería Transmisor de Presión Diferencial | E13: =+J13-1 -> 45407 | F13: 45397 | H13: =+F13-E13 -> -10 | J13: =+K13-L13 -> 45408 | K13: =+R13-1 -> 45415 | L13: 7 | M13: =+F13+L13 -> 45404 | O13: =+M13-K13 -> -11 | R13: =+S13-T13 -> 45416 | S13: =+AC13-1 -> 45437 | T13: 21 | U13: =+M13+T13 -> 45425 | W13: =+U13-S13 -> -12 | AC13: =+AD13-AE13 -> 45438 | AD13: =+AJ13-1 -> 45468 | AE13: 30 | AF13: =+IF(V13=0,U13,V13)+AE13 -> 45455 | AH13: =+AF13-AD13 -> -13 | AJ13: =+AK13-AL13 -> 45469 | AK13: =+AV13-1 -> 45483 | AL13: 14 | AM13: =+IF(AG13=0,AF13,AG13)+AL13 -> 45469 | AO13: =+AM13-AK13 -> -14 | AV13: =+AW13-AX13 -> 45484 | AW13: =+BQ13-1 -> 45634 | AX13: 150 | AY13: =+IF(AN13=0,AM13,AN13)+AX13 -> 45619 | BA13: =+AY13-AW13 -> -15 | BC13: =+BD13-BE13 -> 45635 | BD13: =+BJ13 -> 45635 | BE13: 0 | BF13: =+IF(AZ13=0,AY13,AZ13)+BE13 -> 45619 | BH13: =+BF13-BD13 -> -16 | BJ13: =+BK13-BL13 -> 45635 | BK13: =+BQ13 -> 45635 | BL13: 0 | BM13: =+IF(BG13=0,BF13,BG13)+BL13 -> 45619 | BO13: =+BM13-BK13 -> -16 | BQ13: =+BR13-BS13 -> 45635 | BR13: =+BX13 -> 45641 | BS13: 6 | BT13: =+IF(BN13=0,BM13,BN13)+BS13 -> 45625 | BV13: =+BT13-BR13 -> -16 | BX13: 45641 | BY13: =+BT13-BX13 -> -16
A14: IN-Instrumentación y Control | C14: Requisición de Ingeniería Transmisor de Caudal Multivariable | E14: =+J14-1 -> 45377 | F14: 45397 | H14: =+F14-E14 -> 20 | J14: =+K14-L14 -> 45378 | K14: =+R14-1 -> 45385 | L14: 7 | M14: =+F14+L14 -> 45404 | O14: =+M14-K14 -> 19 | R14: =+S14-T14 -> 45386 | S14: =+AC14-1 -> 45407 | T14: 21 | U14: =+M14+T14 -> 45425 | W14: =+U14-S14 -> 18 | AC14: =+AD14-AE14 -> 45408 | AD14: =+AJ14-1 -> 45438 | AE14: 30 | AF14: =+IF(V14=0,U14,V14)+AE14 -> 45455 | AH14: =+AF14-AD14 -> 17 | AJ14: =+AK14-AL14 -> 45439 | AK14: =+AV14-1 -> 45453 | AL14: 14 | AM14: =+IF(AG14=0,AF14,AG14)+AL14 -> 45469 | AO14: =+AM14-AK14 -> 16 | AV14: =+AW14-AX14 -> 45454 | AW14: =+BQ14-1 -> 45634 | AX14: 180 | AY14: =+IF(AN14=0,AM14,AN14)+AX14 -> 45649 | BA14: =+AY14-AW14 -> 15 | BC14: =+BD14-BE14 -> 45635 | BD14: =+BJ14 -> 45635 | BE14: 0 | BF14: =+IF(AZ14=0,AY14,AZ14)+BE14 -> 45649 | BH14: =+BF14-BD14 -> 14 | BJ14: =+BK14-BL14 -> 45635 | BK14: =+BQ14 -> 45635 | BL14: 0 | BM14: =+IF(BG14=0,BF14,BG14)+BL14 -> 45649 | BO14: =+BM14-BK14 -> 14 | BQ14: =+BR14-BS14 -> 45635 | BR14: =+BX14 -> 45641 | BS14: 6 | BT14: =+IF(BN14=0,BM14,BN14)+BS14 -> 45655 | BV14: =+BT14-BR14 -> 14 | BX14: 45641 | BY14: =+BT14-BX14 -> 14
A15: IN-Instrumentación y Control | C15: Requisición de Ingeniería Transmisor de Caudal Coriolis | E15: =+J15-1 -> 45377 | F15: 45397 | H15: =+F15-E15 -> 20 | J15: =+K15-L15 -> 45378 | K15: =+R15-1 -> 45385 | L15: 7 | M15: =+F15+L15 -> 45404 | O15: =+M15-K15 -> 19 | R15: =+S15-T15 -> 45386 | S15: =+AC15-1 -> 45407 | T15: 21 | U15: =+M15+T15 -> 45425 | W15: =+U15-S15 -> 18 | AC15: =+AD15-AE15 -> 45408 | AD15: =+AJ15-1 -> 45438 | AE15: 30 | AF15: =+IF(V15=0,U15,V15)+AE15 -> 45455 | AH15: =+AF15-AD15 -> 17 | AJ15: =+AK15-AL15 -> 45439 | AK15: =+AV15-1 -> 45453 | AL15: 14 | AM15: =+IF(AG15=0,AF15,AG15)+AL15 -> 45469 | AO15: =+AM15-AK15 -> 16 | AV15: =+AW15-AX15 -> 45454 | AW15: =+BQ15-1 -> 45634 | AX15: 180 | AY15: =+IF(AN15=0,AM15,AN15)+AX15 -> 45649 | BA15: =+AY15-AW15 -> 15 | BC15: =+BD15-BE15 -> 45635 | BD15: =+BJ15 -> 45635 | BE15: 0 | BF15: =+IF(AZ15=0,AY15,AZ15)+BE15 -> 45649 | BH15: =+BF15-BD15 -> 14 | BJ15: =+BK15-BL15 -> 45635 | BK15: =+BQ15 -> 45635 | BL15: 0 | BM15: =+IF(BG15=0,BF15,BG15)+BL15 -> 45649 | BO15: =+BM15-BK15 -> 14 | BQ15: =+BR15-BS15 -> 45635 | BR15: =+BX15 -> 45641 | BS15: 6 | BT15: =+IF(BN15=0,BM15,BN15)+BS15 -> 45655 | BV15: =+BT15-BR15 -> 14 | BX15: 45641 | BY15: =+BT15-BX15 -> 14
A16: IN-Instrumentación y Control | C16: Requisición de Ingeniería Transmisor de Caudal Presión Diferencial | E16: =+J16-1 -> 45377 | F16: 45397 | H16: =+F16-E16 -> 20 | J16: =+K16-L16 -> 45378 | K16: =+R16-1 -> 45385 | L16: 7 | M16: =+F16+L16 -> 45404 | O16: =+M16-K16 -> 19 | R16: =+S16-T16 -> 45386 | S16: =+AC16-1 -> 45407 | T16: 21 | U16: =+M16+T16 -> 45425 | W16: =+U16-S16 -> 18 | AC16: =+AD16-AE16 -> 45408 | AD16: =+AJ16-1 -> 45438 | AE16: 30 | AF16: =+IF(V16=0,U16,V16)+AE16 -> 45455 | AH16: =+AF16-AD16 -> 17 | AJ16: =+AK16-AL16 -> 45439 | AK16: =+AV16-1 -> 45453 | AL16: 14 | AM16: =+IF(AG16=0,AF16,AG16)+AL16 -> 45469 | AO16: =+AM16-AK16 -> 16 | AV16: =+AW16-AX16 -> 45454 | AW16: =+BQ16-1 -> 45634 | AX16: 180 | AY16: =+IF(AN16=0,AM16,AN16)+AX16 -> 45649 | BA16: =+AY16-AW16 -> 15 | BC16: =+BD16-BE16 -> 45635 | BD16: =+BJ16 -> 45635 | BE16: 0 | BF16: =+IF(AZ16=0,AY16,AZ16)+BE16 -> 45649 | BH16: =+BF16-BD16 -> 14 | BJ16: =+BK16-BL16 -> 45635 | BK16: =+BQ16 -> 45635 | BL16: 0 | BM16: =+IF(BG16=0,BF16,BG16)+BL16 -> 45649 | BO16: =+BM16-BK16 -> 14 | BQ16: =+BR16-BS16 -> 45635 | BR16: =+BX16 -> 45641 | BS16: 6 | BT16: =+IF(BN16=0,BM16,BN16)+BS16 -> 45655 | BV16: =+BT16-BR16 -> 14 | BX16: 45641 | BY16: =+BT16-BX16 -> 14
... A71: EL-Electricidad | C71: Materiales Misceláneos | E71: =+J71-1 -> 45435 | F71: 45397 | H71: =+F71-E71 -> -38 | J71: =+K71-L71 -> 45436 | K71: =+R71-1 -> 45443 | L71: 7 | M71: =+F71+L71 -> 45404 | O71: =+M71-K71 -> -39 | R71: =+S71-T71 -> 45444 | S71: =+AC71-1 -> 45465 | T71: 21 | U71: =+M71+T71 -> 45425 | W71: =+U71-S71 -> -40 | AC71: =+AD71-AE71 -> 45466 | AD71: =+AJ71-1 -> 45480 | AE71: 14 | AF71: =+IF(V71=0,U71,V71)+AE71 -> 45439 | AH71: =+AF71-AD71 -> -41 | AJ71: =+AK71-AL71 -> 45481 | AK71: =+AV71-1 -> 45495 | AL71: 14 | AM71: =+IF(AG71=0,AF71,AG71)+AL71 -> 45453 | AO71: =+AM71-AK71 -> -42 | AV71: =+AW71-AX71 -> 45496 | AW71: =+BQ71-1 -> 45586 | AX71: 90 | AY71: =+IF(AN71=0,AM71,AN71)+AX71 -> 45543 | BA71: =+AY71-AW71 -> -43 | BC71: =+BD71-BE71 -> 45587 | BD71: =+BJ71 -> 45587 | BE71: 0 | BF71: =+IF(AZ71=0,AY71,AZ71)+BE71 -> 45543 | BH71: =+BF71-BD71 -> -44 | BJ71: =+BK71-BL71 -> 45587 | BK71: =+BQ71 -> 45587 | BL71: 0 | BM71: =+IF(BG71=0,BF71,BG71)+BL71 -> 45543 | BO71: =+BM71-BK71 -> -44 | BQ71: =+BR71-BS71 -> 45587 | BR71: =+BX71 -> 45593 | BS71: 6 | BT71: =+IF(BN71=0,BM71,BN71)+BS71 -> 45549 | BV71: =+BT71-BR71 -> -44 | BX71: 45593 | BY71: =+BT71-BX71 -> -44
E73: LAS PLANIFICADAS P/ COMPRA EN FUNCIÓN DE ESTRATEGIA SUMINISTROS/PROYECTO | Y73: VA A DEPENDER DE CADA ESTRATEGIA DE PROYECTO | AV73: SE PUEDE ABRIR LOS TIEMPOS DE VENDORS/INSPECCIÓN, ETC | BC73: DEPENDE DE LA ESTRATEGIA DEL SUMINISTRO/PROYECTO | BQ73: SI HAY DESAGREACIÓN EN CANNING SE PUEDE PLANIFICAR TAMBIÉN | BX73: INTERNO SUMINISTROS PARA PREVEER IMPACTOS, ALERTAR Y ARTICULAR CON CONSTRUCCIONES
E77: TIEMPO PLANIFICADO DE INGENERIA | J77: TIEMPO PLANIFICADO PARA ADMINISTRACIÓN DE MATERIALES | R77: TIEMPO PLANIFICADO PARA COMPRAS | Y77: TIEMPO PLANIFICADO INGENIERÍA | AJ77: TIEMPO PLANIFICADO COMPRAS | AV77: TIEMPO PLANIFICADO INGENIERÍA/ACTIVACIÓN/INSPECCIÓN | BC77: TIEMPO PLANIFICADO COMEX | BJ77: TIEMPO PLANIFICADO COMEX | BQ77: TIEMPO PLANIFICADO LOGISTICA Y ALMACES

Sheet La Calera II - crono 4.11
A1: SUMINISTROS PROYECTO XX | D1: TAG | E1: RI | J1: Emisión y liberación de Solped | R1: Recepción de ofertas | Y1: AT REV A | AC1: AT REV 0 | AJ1: Emisión OC | AV1: Fabricación | BC1: Transporte Internacional (incluida gestión comex+transporte) | BJ1: Nacionalización (tiempo Comex para nacionalizar) | BQ1: Transporte Local | BX1: Necesidad Construcciónes | BY1: Impacto Costrucciones | CB1: -30 | CC1: 0
CB2: 1 | CC2: 90
A3: ESP | B3: Requisición N° | C3: DESCRIPCION | D3: N° | E3: Final Prog | F3: Forecast | G3: Real | H3: Desvío | J3: Inicio Prog | K3: Final Prog | L3: Duración | M3: Forecast | N3: Real | O3: Desvío Acum | P3: N° Cesta/Solped | R3: Inicio Prog | S3: Final Prog | T3: Duración | U3: Forecast | V3: Real | W3: Desvío Acum | Y3: Final Prog | Z3: Real | AA3: Desvío Acum | AC3: Inicio Prog | AD3: Final Prog | AE3: Duración | AF3: Forecast | AG3: Real | AH3: Desvío Acum | AJ3: Inicio Prog | AK3: Final Prog | AL3: Duración | AM3: Forecast | AN3: Real | AO3: Desvío Acum | AP3: N° OC | AQ3: Pos | AR3: Proveedor | AS3: Fecha de Entrega | AT3: Lugar de entrega | AV3: Inicio Prog | AW3: Final Prog | AX3: Duración | AY3: Forecast | AZ3: Real | BA3: Desvío Acum | BC3: Inicio Prog | BD3: Final Prog | BE3: Duración | BF3: Forecast | BG3: Real | BH3: Desvío Acum | BJ3: Inicio Prog | BK3: Final Prog | BL3: Duración | BM3: Forecast | BN3: Real | BO3: Desvío Acum | BQ3: Inicio Prog | BR3: Final Prog | BS3: Duración | BT3: Forecast | BU3: Real | BV3: Desvío Acum
A4: EM-Mecánica | C4: Calentador eléctrico | D4: - | E4: =+J4-1 -> 45744 | H4: =+F4-E4 -> -45744 | J4: =+K4-L4 -> 45745 | K4: =+R4-1 -> 45752 | L4: 7 | M4: =+F4+L4 -> 7 | O4: =+M4-K4 -> -45745 | R4: =+S4-T4 -> 45753 | S4: =+AC4-1 -> 45783 | T4: 30 | U4: =+M4+T4 -> 37 | W4: =+U4-S4 -> -45746 | Y4: - | Z4: - | AA4: - | AC4: =+AD4-AE4 -> 45784 | AD4: =+AJ4-1 -> 45829 | AE4: 45 | AF4: =+IF(V4=0,U4,V4)+AE4 -> 82 | AH4: =+AF4-AD4 -> -45747 | AJ4: =+AK4-AL4 -> 45830 | AK4: =+AV4-1 -> 45844 | AL4: 14 | AM4: =+IF(AG4=0,AF4,AG4)+AL4 -> 96 | AO4: =+AM4-AK4 -> -45748 | AV4: =+AW4-AX4 -> 45845 | AW4: =+BQ4-1 -> 46145 | AX4: 300 | AY4: =+IF(AN4=0,AM4,AN4)+AX4 -> 396 | BA4: =+AY4-AW4 -> -45749 | BC4: =+BD4-BE4 -> 46146 | BD4: =+BJ4 -> 46146 | BE4: 0 | BF4: =+IF(AZ4=0,AY4,AZ4)+BE4 -> 396 | BH4: =+BF4-BD4 -> -45750 | BJ4: =+BK4-BL4 -> 46146 | BK4: =+BQ4 -> 46146 | BL4: 0 | BM4: =+IF(BG4=0,BF4,BG4)+BL4 -> 396 | BO4: =+BM4-BK4 -> -45750 | BQ4: =+BR4-BS4 -> 46146 | BR4: =+BX4 -> 46153 | BS4: 7 | BT4: =+IF(BN4=0,BM4,BN4)+BS4 -> 403 | BV4: =+BT4-BR4 -> -45750 | BX4: 46153 | BY4: =+BT4-BX4 -> -45750 | CA4: Fecha de equipos estáticos y paquetes crono 4/11/24
A5: EM-Mecánica | C5: Intercambiador gas-gas | E5: =+J5-1 -> 45774 | H5: =+F5-E5 -> -45774 | J5: =+K5-L5 -> 45775 | K5: =+R5-1 -> 45782 | L5: 7 | M5: =+F5+L5 -> 7 | O5: =+M5-K5 -> -45775 | R5: =+S5-T5 -> 45783 | S5: =+AC5-1 -> 45813 | T5: 30 | U5: =+M5+T5 -> 37 | W5: =+U5-S5 -> -45776 | AC5: =+AD5-AE5 -> 45814 | AD5: =+AJ5-1 -> 45859 | AE5: 45 | AF5: =+IF(V5=0,U5,V5)+AE5 -> 82 | AH5: =+AF5-AD5 -> -45777 | AJ5: =+AK5-AL5 -> 45860 | AK5: =+AV5-1 -> 45874 | AL5: 14 | AM5: =+IF(AG5=0,AF5,AG5)+AL5 -> 96 | AO5: =+AM5-AK5 -> -45778 | AV5: =+AW5-AX5 -> 45875 | AW5: =+BQ5-1 -> 46145 | AX5: 270 | AY5: =+IF(AN5=0,AM5,AN5)+AX5 -> 366 | BA5: =+AY5-AW5 -> -45779 | BC5: =+BD5-BE5 -> 46146 | BD5: =+BJ5 -> 46146 | BE5: 0 | BF5: =+IF(AZ5=0,AY5,AZ5)+BE5 -> 366 | BH5: =+BF5-BD5 -> -45780 | BJ5: =+BK5-BL5 -> 46146 | BK5: =+BQ5 -> 46146 | BL5: 0 | BM5: =+IF(BG5=0,BF5,BG5)+BL5 -> 366 | BO5: =+BM5-BK5 -> -45780 | BQ5: =+BR5-BS5 -> 46146 | BR5: =+BX5 -> 46153 | BS5: 7 | BT5: =+IF(BN5=0,BM5,BN5)+BS5 -> 373 | BV5: =+BT5-BR5 -> -45780 | BX5: 46153 | BY5: =+BT5-BX5 -> -45780 | CA5: Fecha de equipos estáticos y paquetes crono 4/11/24
A6: EM-Mecánica | C6: Separador de gas combustible | E6: =+J6-1 -> 45744 | H6: =+F6-E6 -> -45744 | J6: =+K6-L6 -> 45745 | K6: =+R6-1 -> 45752 | L6: 7 | M6: =+F6+L6 -> 7 | O6: =+M6-K6 -> -45745 | R6: =+S6-T6 -> 45753 | S6: =+AC6-1 -> 45783 | T6: 30 | U6: =+M6+T6 -> 37 | W6: =+U6-S6 -> -45746 | AC6: =+AD6-AE6 -> 45784 | AD6: =+AJ6-1 -> 45829 | AE6: 45 | AF6: =+IF(V6=0,U6,V6)+AE6 -> 82 | AH6: =+AF6-AD6 -> -45747 | AJ6: =+AK6-AL6 -> 45830 | AK6: =+AV6-1 -> 45844 | AL6: 14 | AM6: =+IF(AG6=0,AF6,AG6)+AL6 -> 96 | AO6: =+AM6-AK6 -> -45748 | AV6: =+AW6-AX6 -> 45845 | AW6: =+BQ6-1 -> 46145 | AX6: 300 | AY6: =+IF(AN6=0,AM6,AN6)+AX6 -> 396 | BA6: =+AY6-AW6 -> -45749 | BC6: =+BD6-BE6 -> 46146 | BD6: =+BJ6 -> 46146 | BE6: 0 | BF6: =+IF(AZ6=0,AY6,AZ6)+BE6 -> 396 | BH6: =+BF6-BD6 -> -45750 | BJ6: =+BK6-BL6 -> 46146 | BK6: =+BQ6 -> 46146 | BL6: 0 | BM6: =+IF(BG6=0,BF6,BG6)+BL6 -> 396 | BO6: =+BM6-BK6 -> -45750 | BQ6: =+BR6-BS6 -> 46146 | BR6: =+BX6 -> 46153 | BS6: 7 | BT6: =+IF(BN6=0,BM6,BN6)+BS6 -> 403 | BV6: =+BT6-BR6 -> -45750 | BX6: 46153 | BY6: =+BT6-BX6 -> -45750 | CA6: Fecha de equipos estáticos y paquetes crono 4/11/24
A7: EM-Mecánica | C7: Filtro de gas combustible | E7: =+J7-1 -> 45794 | H7: =+F7-E7 -> -45794 | J7: =+K7-L7 -> 45795 | K7: =+R7-1 -> 45802 | L7: 7 | M7: =+F7+L7 -> 7 | O7: =+M7-K7 -> -45795 | R7: =+S7-T7 -> 45803 | S7: =+AC7-1 -> 45833 | T7: 30 | U7: =+M7+T7 -> 37 | W7: =+U7-S7 -> -45796 | AC7: =+AD7-AE7 -> 45834 | AD7: =+AJ7-1 -> 45879 | AE7: 45 | AF7: =+IF(V7=0,U7,V7)+AE7 -> 82 | AH7: =+AF7-AD7 -> -45797 | AJ7: =+AK7-AL7 -> 45880 | AK7: =+AV7-1 -> 45894 | AL7: 14 | AM7: =+IF(AG7=0,AF7,AG7)+AL7 -> 96 | AO7: =+AM7-AK7 -> -45798 | AV7: =+AW7-AX7 -> 45895 | AW7: =+BQ7-1 -> 46145 | AX7: 250 | AY7: =+IF(AN7=0,AM7,AN7)+AX7 -> 346 | BA7: =+AY7-AW7 -> -45799 | BC7: =+BD7-BE7 -> 46146 | BD7: =+BJ7 -> 46146 | BE7: 0 | BF7: =+IF(AZ7=0,AY7,AZ7)+BE7 -> 346 | BH7: =+BF7-BD7 -> -45800 | BJ7: =+BK7-BL7 -> 46146 | BK7: =+BQ7 -> 46146 | BL7: 0 | BM7: =+IF(BG7=0,BF7,BG7)+BL7 -> 346 | BO7: =+BM7-BK7 -> -45800 | BQ7: =+BR7-BS7 -> 46146 | BR7: =+BX7 -> 46153 | BS7: 7 | BT7: =+IF(BN7=0,BM7,BN7)+BS7 -> 353 | BV7: =+BT7-BR7 -> -45800 | BX7: 46153 | BY7: =+BT7-BX7 -> -45800 | CA7: Fecha de equipos estáticos y paquetes crono 4/11/24
A8: EM-Mecánica | C8: Compresor/Secador de aire | E8: =+J8-1 -> 45794 | H8: =+F8-E8 -> -45794 | J8: =+K8-L8 -> 45795 | K8: =+R8-1 -> 45802 | L8: 7 | M8: =+F8+L8 -> 7 | O8: =+M8-K8 -> -45795 | R8: =+S8-T8 -> 45803 | S8: =+AC8-1 -> 45833 | T8: 30 | U8: =+M8+T8 -> 37 | W8: =+U8-S8 -> -45796 | AC8: =+AD8-AE8 -> 45834 | AD8: =+AJ8-1 -> 45879 | AE8: 45 | AF8: =+IF(V8=0,U8,V8)+AE8 -> 82 | AH8: =+AF8-AD8 -> -45797 | AJ8: =+AK8-AL8 -> 45880 | AK8: =+AV8-1 -> 45894 | AL8: 14 | AM8: =+IF(AG8=0,AF8,AG8)+AL8 -> 96 | AO8: =+AM8-AK8 -> -45798 | AV8: =+AW8-AX8 -> 45895 | AW8: =+BQ8-1 -> 46145 | AX8: 250 | AY8: =+IF(AN8=0,AM8,AN8)+AX8 -> 346 | BA8: =+AY8-AW8 -> -45799 | BC8: =+BD8-BE8 -> 46146 | BD8: =+BJ8 -> 46146 | BE8: 0 | BF8: =+IF(AZ8=0,AY8,AZ8)+BE8 -> 346 | BH8: =+BF8-BD8 -> -45800 | BJ8: =+BK8-BL8 -> 46146 | BK8: =+BQ8 -> 46146 | BL8: 0 | BM8: =+IF(BG8=0,BF8,BG8)+BL8 -> 346 | BO8: =+BM8-BK8 -> -45800 | BQ8: =+BR8-BS8 -> 46146 | BR8: =+BX8 -> 46153 | BS8: 7 | BT8: =+IF(BN8=0,BM8,BN8)+BS8 -> 353 | BV8: =+BT8-BR8 -> -45800 | BX8: 46153 | BY8: =+BT8-BX8 -> -45800 | CA8: Fecha de equipos estáticos y paquetes crono 4/11/24
A9: EM-Mecánica | C9: Filtro de aire | E9: =+J9-1 -> 45804 | H9: =+F9-E9 -> -45804 | J9: =+K9-L9 -> 45805 | K9: =+R9-1 -> 45812 | L9: 7 | M9: =+F9+L9 -> 7 | O9: =+M9-K9 -> -45805 | R9: =+S9-T9 -> 45813 | S9: =+AC9-1 -> 45843 | T9: 30 | U9: =+M9+T9 -> 37 | W9: =+U9-S9 -> -45806 | AC9: =+AD9-AE9 -> 45844 | AD9: =+AJ9-1 -> 45889 | AE9: 45 | AF9: =+IF(V9=0,U9,V9)+AE9 -> 82 | AH9: =+AF9-AD9 -> -45807 | AJ9: =+AK9-AL9 -> 45890 | AK9: =+AV9-1 -> 45904 | AL9: 14 | AM9: =+IF(AG9=0,AF9,AG9)+AL9 -> 96 | AO9: =+AM9-AK9 -> -45808 | AV9: =+AW9-AX9 -> 45905 | AW9: =+BQ9-1 -> 46145 | AX9: 240 | AY9: =+IF(AN9=0,AM9,AN9)+AX9 -> 336 | BA9: =+AY9-AW9 -> -45809 | BC9: =+BD9-BE9 -> 46146 | BD9: =+BJ9 -> 46146 | BE9: 0 | BF9: =+IF(AZ9=0,AY9,AZ9)+BE9 -> 336 | BH9: =+BF9-BD9 -> -45810 | BJ9: =+BK9-BL9 -> 46146 | BK9: =+BQ9 -> 46146 | BL9: 0 | BM9: =+IF(BG9=0,BF9,BG9)+BL9 -> 336 | BO9: =+BM9-BK9 -> -45810 | BQ9: =+BR9-BS9 -> 46146 | BR9: =+BX9 -> 46153 | BS9: 7 | BT9: =+IF(BN9=0,BM9,BN9)+BS9 -> 343 | BV9: =+BT9-BR9 -> -45810 | BX9: 46153 | BY9: =+BT9-BX9 -> -45810 | CA9: Fecha de equipos estáticos y paquetes crono 4/11/24
A10: EM-Mecánica | C10: Enfriador de aire | E10: =+J10-1 -> 45774 | H10: =+F10-E10 -> -45774 | J10: =+K10-L10 -> 45775 | K10: =+R10-1 -> 45782 | L10: 7 | M10: =+F10+L10 -> 7 | O10: =+M10-K10 -> -45775 | R10: =+S10-T10 -> 45783 | S10: =+AC10-1 -> 45813 | T10: 30 | U10: =+M10+T10 -> 37 | W10: =+U10-S10 -> -45776 | AC10: =+AD10-AE10 -> 45814 | AD10: =+AJ10-1 -> 45859 | AE10: 45 | AF10: =+IF(V10=0,U10,V10)+AE10 -> 82 | AH10: =+AF10-AD10 -> -45777 | AJ10: =+AK10-AL10 -> 45860 | AK10: =+AV10-1 -> 45874 | AL10: 14 | AM10: =+IF(AG10=0,AF10,AG10)+AL10 -> 96 | AO10: =+AM10-AK10 -> -45778 | AV10: =+AW10-AX10 -> 45875 | AW10: =+BQ10-1 -> 46145 | AX10: 270 | AY10: =+IF(AN10=0,AM10,AN10)+AX10 -> 366 | BA10: =+AY10-AW10 -> -45779 | BC10: =+BD10-BE10 -> 46146 | BD10: =+BJ10 -> 46146 | BE10: 0 | BF10: =+IF(AZ10=0,AY10,AZ10)+BE10 -> 366 | BH10: =+BF10-BD10 -> -45780 | BJ10: =+BK10-BL10 -> 46146 | BK10: =+BQ10 -> 46146 | BL10: 0 | BM10: =+IF(BG10=0,BF10,BG10)+BL10 -> 366 | BO10: =+BM10-BK10 -> -45780 | BQ10: =+BR10-BS10 -> 46146 | BR10: =+BX10 -> 46153 | BS10: 7 | BT10: =+IF(BN10=0,BM10,BN10)+BS10 -> 373 | BV10: =+BT10-BR10 -> -45780 | BX10: 46153 | BY10: =+BT10-BX10 -> -45780 | CA10: Fecha de equipos estáticos y paquetes crono 4/11/24
A11: EM-Mecánica | C11: Skid generación de nitrógeno | E11: =+J11-1 -> 45714 | H11: =+F11-E11 -> -45714 | J11: =+K11-L11 -> 45715 | K11: =+R11-1 -> 45722 | L11: 7 | M11: =+F11+L11 -> 7 | O11: =+M11-K11 -> -45715 | R11: =+S11-T11 -> 45723 | S11: =+AC11-1 -> 45753 | T11: 30 | U11: =+M11+T11 -> 37 | W11: =+U11-S11 -> -45716 | AC11: =+AD11-AE11 -> 45754 | AD11: =+AJ11-1 -> 45799 | AE11: 45 | AF11: =+IF(V11=0,U11,V11)+AE11 -> 82 | AH11: =+AF11-AD11 -> -45717 | AJ11: =+AK11-AL11 -> 45800 | AK11: =+AV11-1 -> 45814 | AL11: 14 | AM11: =+IF(AG11=0,AF11,AG11)+AL11 -> 96 | AO11: =+AM11-AK11 -> -45718 | AV11: =+AW11-AX11 -> 45815 | AW11: =+BQ11-1 -> 46145 | AX11: 330 | AY11: =+IF(AN11=0,AM11,AN11)+AX11 -> 426 | BA11: =+AY11-AW11 -> -45719 | BC11: =+BD11-BE11 -> 46146 | BD11: =+BJ11 -> 46146 | BE11: 0 | BF11: =+IF(AZ11=0,AY11,AZ11)+BE11 -> 426 | BH11: =+BF11-BD11 -> -45720 | BJ11: =+BK11-BL11 -> 46146 | BK11: =+BQ11 -> 46146 | BL11: 0 | BM11: =+IF(BG11=0,BF11,BG11)+BL11 -> 426 | BO11: =+BM11-BK11 -> -45720 | BQ11: =+BR11-BS11 -> 46146 | BR11: =+BX11 -> 46153 | BS11: 7 | BT11: =+IF(BN11=0,BM11,BN11)+BS11 -> 433 | BV11: =+BT11-BR11 -> -45720 | BX11: 46153 | BY11: =+BT11-BX11 -> -45720 | CA11: Fecha de equipos estáticos y paquetes crono 4/11/24
A12: EM-Mecánica | C12: Calentador de gas combustible AP | E12: =+J12-1 -> 45714 | H12: =+F12-E12 -> -45714 | J12: =+K12-L12 -> 45715 | K12: =+R12-1 -> 45722 | L12: 7 | M12: =+F12+L12 -> 7 | O12: =+M12-K12 -> -45715 | R12: =+S12-T12 -> 45723 | S12: =+AC12-1 -> 45753 | T12: 30 | U12: =+M12+T12 -> 37 | W12: =+U12-S12 -> -45716 | AC12: =+AD12-AE12 -> 45754 | AD12: =+AJ12-1 -> 45799 | AE12: 45 | AF12: =+IF(V12=0,U12,V12)+AE12 -> 82 | AH12: =+AF12-AD12 -> -45717 | AJ12: =+AK12-AL12 -> 45800 | AK12: =+AV12-1 -> 45814 | AL12: 14 | AM12: =+IF(AG12=0,AF12,AG12)+AL12 -> 96 | AO12: =+AM12-AK12 -> -45718 | AV12: =+AW12-AX12 -> 45815 | AW12: =+BQ12-1 -> 46145 | AX12: 330 | AY12: =+IF(AN12=0,AM12,AN12)+AX12 -> 426 | BA12: =+AY12-AW12 -> -45719 | BC12: =+BD12-BE12 -> 46146 | BD12: =+BJ12 -> 46146 | BE12: 0 | BF12: =+IF(AZ12=0,AY12,AZ12)+BE12 -> 426 | BH12: =+BF12-BD12 -> -45720 | BJ12: =+BK12-BL12 -> 46146 | BK12: =+BQ12 -> 46146 | BL12: 0 | BM12: =+IF(BG12=0,BF12,BG12)+BL12 -> 426 | BO12: =+BM12-BK12 -> -45720 | BQ12: =+BR12-BS12 -> 46146 | BR12: =+BX12 -> 46153 | BS12: 7 | BT12: =+IF(BN12=0,BM12,BN12)+BS12 -> 433 | BV12: =+BT12-BR12 -> -45720 | BX12: 46153 | BY12: =+BT12-BX12 -> -45720 | CA12: Fecha de equipos estáticos y paquetes crono 4/11/24
A13: EM-Mecánica | C13: Skid de inyección de químicos (tanque + bombas) | E13: =+J13-1 -> 45834 | H13: =+F13-E13 -> -45834 | J13: =+K13-L13 -> 45835 | K13: =+R13-1 -> 45842 | L13: 7 | M13: =+F13+L13 -> 7 | O13: =+M13-K13 -> -45835 | R13: =+S13-T13 -> 45843 | S13: =+AC13-1 -> 45873 | T13: 30 | U13: =+M13+T13 -> 37 | W13: =+U13-S13 -> -45836 | AC13: =+AD13-AE13 -> 45874 | AD13: =+AJ13-1 -> 45919 | AE13: 45 | AF13: =+IF(V13=0,U13,V13)+AE13 -> 82 | AH13: =+AF13-AD13 -> -45837 | AJ13: =+AK13-AL13 -> 45920 | AK13: =+AV13-1 -> 45934 | AL13: 14 | AM13: =+IF(AG13=0,AF13,AG13)+AL13 -> 96 | AO13: =+AM13-AK13 -> -45838 | AV13: =+AW13-AX13 -> 45935 | AW13: =+BQ13-1 -> 46145 | AX13: 210 | AY13: =+IF(AN13=0,AM13,AN13)+AX13 -> 306 | BA13: =+AY13-AW13 -> -45839 | BC13: =+BD13-BE13 -> 46146 | BD13: =+BJ13 -> 46146 | BE13: 0 | BF13: =+IF(AZ13=0,AY13,AZ13)+BE13 -> 306 | BH13: =+BF13-BD13 -> -45840 | BJ13: =+BK13-BL13 -> 46146 | BK13: =+BQ13 -> 46146 | BL13: 0 | BM13: =+IF(BG13=0,BF13,BG13)+BL13 -> 306 | BO13: =+BM13-BK13 -> -45840 | BQ13: =+BR13-BS13 -> 46146 | BR13: =+BX13 -> 46153 | BS13: 7 | BT13: =+IF(BN13=0,BM13,BN13)+BS13 -> 313 | BV13: =+BT13-BR13 -> -45840 | BX13: 46153 | BY13: =+BT13-BX13 -> -45840 | CA13: Fecha de equipos estáticos y paquetes crono 4/11/24
A14: EM-Mecánica | C14: Separador de condensados de EPF | E14: =+J14-1 -> 45714 | H14: =+F14-E14 -> -45714 | J14: =+K14-L14 -> 45715 | K14: =+R14-1 -> 45722 | L14: 7 | M14: =+F14+L14 -> 7 | O14: =+M14-K14 -> -45715 | R14: =+S14-T14 -> 45723 | S14: =+AC14-1 -> 45753 | T14: 30 | U14: =+M14+T14 -> 37 | W14: =+U14-S14 -> -45716 | AC14: =+AD14-AE14 -> 45754 | AD14: =+AJ14-1 -> 45799 | AE14: 45 | AF14: =+IF(V14=0,U14,V14)+AE14 -> 82 | AH14: =+AF14-AD14 -> -45717 | AJ14: =+AK14-AL14 -> 45800 | AK14: =+AV14-1 -> 45814 | AL14: 14 | AM14: =+IF(AG14=0,AF14,AG14)+AL14 -> 96 | AO14: =+AM14-AK14 -> -45718 | AV14: =+AW14-AX14 -> 45815 | AW14: =+BQ14-1 -> 46145 | AX14: 330 | AY14: =+IF(AN14=0,AM14,AN14)+AX14 -> 426 | BA14: =+AY14-AW14 -> -45719 | BC14: =+BD14-BE14 -> 46146 | BD14: =+BJ14 -> 46146 | BE14: 0 | BF14: =+IF(AZ14=0,AY14,AZ14)+BE14 -> 426 | BH14: =+BF14-BD14 -> -45720 | BJ14: =+BK14-BL14 -> 46146 | BK14: =+BQ14 -> 46146 | BL14: 0 | BM14: =+IF(BG14=0,BF14,BG14)+BL14 -> 426 | BO14: =+BM14-BK14 -> -45720 | BQ14: =+BR14-BS14 -> 46146 | BR14: =+BX14 -> 46153 | BS14: 7 | BT14: =+IF(BN14=0,BM14,BN14)+BS14 -> 433 | BV14: =+BT14-BR14 -> -45720 | BX14: 46153 | BY14: =+BT14-BX14 -> -45720 | CA14: Fecha de equipos estáticos y paquetes crono 4/11/24
A15: EM-Mecánica | C15: Tanque de almacenamiento de agua de inyección | E15: =+J15-1 -> 45764 | H15: =+F15-E15 -> -45764 | J15: =+K15-L15 -> 45765 | K15: =+R15-1 -> 45772 | L15: 7 | M15: =+F15+L15 -> 7 | O15: =+M15-K15 -> -45765 | R15: =+S15-T15 -> 45773 | S15: =+AC15-1 -> 45803 | T15: 30 | U15: =+M15+T15 -> 37 | W15: =+U15-S15 -> -45766 | AC15: =+AD15-AE15 -> 45804 | AD15: =+AJ15-1 -> 45849 | AE15: 45 | AF15: =+IF(V15=0,U15,V15)+AE15 -> 82 | AH15: =+AF15-AD15 -> -45767 | AJ15: =+AK15-AL15 -> 45850 | AK15: =+AV15-1 -> 45864 | AL15: 14 | AM15: =+IF(AG15=0,AF15,AG15)+AL15 -> 96 | AO15: =+AM15-AK15 -> -45768 | AV15: =+AW15-AX15 -> 45865 | AW15: =+BQ15-1 -> 46145 | AX15: 280 | AY15: =+IF(AN15=0,AM15,AN15)+AX15 -> 376 | BA15: =+AY15-AW15 -> -45769 | BC15: =+BD15-BE15 -> 46146 | BD15: =+BJ15 -> 46146 | BE15: 0 | BF15: =+IF(AZ15=0,AY15,AZ15)+BE15 -> 376 | BH15: =+BF15-BD15 -> -45770 | BJ15: =+BK15-BL15 -> 46146 | BK15: =+BQ15 -> 46146 | BL15: 0 | BM15: =+IF(BG15=0,BF15,BG15)+BL15 -> 376 | BO15: =+BM15-BK15 -> -45770 | BQ15: =+BR15-BS15 -> 46146 | BR15: =+BX15 -> 46153 | BS15: 7 | BT15: =+IF(BN15=0,BM15,BN15)+BS15 -> 383 | BV15: =+BT15-BR15 -> -45770 | BX15: 46153 | BY15: =+BT15-BX15 -> -45770 | CA15: Fecha de equipos estáticos y paquetes crono 4/11/24
A16: EM-Mecánica | C16: Filtro para bombas | E16: =+J16-1 -> 45804 | H16: =+F16-E16 -> -45804 | J16: =+K16-L16 -> 45805 | K16: =+R16-1 -> 45812 | L16: 7 | M16: =+F16+L16 -> 7 | O16: =+M16-K16 -> -45805 | R16: =+S16-T16 -> 45813 | S16: =+AC16-1 -> 45843 | T16: 30 | U16: =+M16+T16 -> 37 | W16: =+U16-S16 -> -45806 | AC16: =+AD16-AE16 -> 45844 | AD16: =+AJ16-1 -> 45889 | AE16: 45 | AF16: =+IF(V16=0,U16,V16)+AE16 -> 82 | AH16: =+AF16-AD16 -> -45807 | AJ16: =+AK16-AL16 -> 45890 | AK16: =+AV16-1 -> 45904 | AL16: 14 | AM16: =+IF(AG16=0,AF16,AG16)+AL16 -> 96 | AO16: =+AM16-AK16 -> -45808 | AV16: =+AW16-AX16 -> 45905 | AW16: =+BQ16-1 -> 46145 | AX16: 240 | AY16: =+IF(AN16=0,AM16,AN16)+AX16 -> 336 | BA16: =+AY16-AW16 -> -45809 | BC16: =+BD16-BE16 -> 46146 | BD16: =+BJ16 -> 46146 | BE16: 0 | BF16: =+IF(AZ16=0,AY16,AZ16)+BE16 -> 336 | BH16: =+BF16-BD16 -> -45810 | BJ16: =+BK16-BL16 -> 46146 | BK16: =+BQ16 -> 46146 | BL16: 0 | BM16: =+IF(BG16=0,BF16,BG16)+BL16 -> 336 | BO16: =+BM16-BK16 -> -45810 | BQ16: =+BR16-BS16 -> 46146 | BR16: =+BX16 -> 46153 | BS16: 7 | BT16: =+IF(BN16=0,BM16,BN16)+BS16 -> 343 | BV16: =+BT16-BR16 -> -45810 | BX16: 46153 | BY16: =+BT16-BX16 -> -45810 | CA16: Fecha de equipos estáticos y paquetes crono 4/11/24
... A62: IN-Instrumentación | C62: Cables de instrumentación Rev. 0 - Ingeniería inicial | E62: =+J62-1 -> 45900 | H62: =+F62-E62 -> -45900 | J62: =+K62-L62 -> 45901 | K62: =+R62-1 -> 45908 | L62: 7 | M62: =+F62+L62 -> 7 | O62: =+M62-K62 -> -45901 | R62: =+S62-T62 -> 45909 | S62: =+AC62-1 -> 45934 | T62: 25 | U62: =+M62+T62 -> 32 | W62: =+U62-S62 -> -45902 | AC62: =+AD62-AE62 -> 45935 | AD62: =+AJ62-1 -> 45980 | AE62: 45 | AF62: =+IF(V62=0,U62,V62)+AE62 -> 77 | AH62: =+AF62-AD62 -> -45903 | AJ62: =+AK62-AL62 -> 45981 | AK62: =+AV62-1 -> 45995 | AL62: 14 | AM62: =+IF(AG62=0,AF62,AG62)+AL62 -> 91 | AO62: =+AM62-AK62 -> -45904 | AV62: =+AW62-AX62 -> 45996 | AW62: =+BQ62-1 -> 46176 | AX62: 180 | AY62: =+IF(AN62=0,AM62,AN62)+AX62 -> 271 | BA62: =+AY62-AW62 -> -45905 | BC62: =+BD62-BE62 -> 46177 | BD62: =+BJ62 -> 46177 | BE62: 0 | BF62: =+IF(AZ62=0,AY62,AZ62)+BE62 -> 271 | BH62: =+BF62-BD62 -> -45906 | BJ62: =+BK62-BL62 -> 46177 | BK62: =+BQ62 -> 46177 | BL62: 0 | BM62: =+IF(BG62=0,BF62,BG62)+BL62 -> 271 | BO62: =+BM62-BK62 -> -45906 | BQ62: =+BR62-BS62 -> 46177 | BR62: =+BX62 -> 46184 | BS62: 7 | BT62: =+IF(BN62=0,BM62,BN62)+BS62 -> 278 | BV62: =+BT62-BR62 -> -45906 | BX62: 46184 | BY62: =+BT62-BX62 -> -45906 | CA62: Considero fecha inicio tendido de cables instrumentación
A63: IN-Instrumentación | C63: Cables de instrumentación Rev. 1 - Ingeniería 80% | E63: =+J63-1 -> 46041 | F63: =+C85 -> 46168 | H63: =+F63-E63 -> 127 | J63: =+K63-L63 -> 46042 | K63: =+R63-1 -> 46049 | L63: 7 | M63: =+F63+L63 -> 46175 | O63: =+M63-K63 -> 126 | R63: =+S63-T63 -> 46050 | S63: =+AC63-1 -> 46075 | T63: 25 | U63: =+M63+T63 -> 46200 | W63: =+U63-S63 -> 125 | AC63: =+AD63-AE63 -> 46076 | AD63: =+AJ63-1 -> 46121 | AE63: 45 | AF63: =+IF(V63=0,U63,V63)+AE63 -> 46245 | AH63: =+AF63-AD63 -> 124 | AJ63: =+AK63-AL63 -> 46122 | AK63: =+AV63-1 -> 46136 | AL63: 14 | AM63: =+IF(AG63=0,AF63,AG63)+AL63 -> 46259 | AO63: =+AM63-AK63 -> 123 | AV63: =+AW63-AX63 -> 46137 | AW63: =+BQ63-1 -> 46257 | AX63: 120 | AY63: =+IF(AN63=0,AM63,AN63)+AX63 -> 46379 | BA63: =+AY63-AW63 -> 122 | BC63: =+BD63-BE63 -> 46258 | BD63: =+BJ63 -> 46258 | BE63: 0 | BF63: =+IF(AZ63=0,AY63,AZ63)+BE63 -> 46379 | BH63: =+BF63-BD63 -> 121 | BJ63: =+BK63-BL63 -> 46258 | BK63: =+BQ63 -> 46258 | BL63: 0 | BM63: =+IF(BG63=0,BF63,BG63)+BL63 -> 46379 | BO63: =+BM63-BK63 -> 121 | BQ63: =+BR63-BS63 -> 46258 | BR63: =+BX63 -> 46265 | BS63: 7 | BT63: =+IF(BN63=0,BM63,BN63)+BS63 -> 46386 | BV63: =+BT63-BR63 -> 121 | BX63: 46265 | BY63: =+BT63-BX63 -> 121 | CA63: Considero fin de entrega de cables de acuerdo a crono 4.11
A64: IN-Instrumentación | C64: Sistema de control, hardware y software | E64: =+J64-1 -> 45967 | H64: =+F64-E64 -> -45967 | J64: =+K64-L64 -> 45968 | K64: =+R64-1 -> 45975 | L64: 7 | M64: =+F64+L64 -> 7 | O64: =+M64-K64 -> -45968 | R64: =+S64-T64 -> 45976 | S64: =+AC64-1 -> 46001 | T64: 25 | U64: =+M64+T64 -> 32 | W64: =+U64-S64 -> -45969 | AC64: =+AD64-AE64 -> 46002 | AD64: =+AJ64-1 -> 46047 | AE64: 45 | AF64: =+IF(V64=0,U64,V64)+AE64 -> 77 | AH64: =+AF64-AD64 -> -45970 | AJ64: =+AK64-AL64 -> 46048 | AK64: =+AV64-1 -> 46062 | AL64: 14 | AM64: =+IF(AG64=0,AF64,AG64)+AL64 -> 91 | AO64: =+AM64-AK64 -> -45971 | AV64: =+AW64-AX64 -> 46063 | AW64: =+BQ64-1 -> 46363 | AX64: 300 | AY64: =+IF(AN64=0,AM64,AN64)+AX64 -> 391 | BA64: =+AY64-AW64 -> -45972 | BC64: =+BD64-BE64 -> 46364 | BD64: =+BJ64 -> 46364 | BE64: 0 | BF64: =+IF(AZ64=0,AY64,AZ64)+BE64 -> 391 | BH64: =+BF64-BD64 -> -45973 | BJ64: =+BK64-BL64 -> 46364 | BK64: =+BQ64 -> 46364 | BL64: 0 | BM64: =+IF(BG64=0,BF64,BG64)+BL64 -> 391 | BO64: =+BM64-BK64 -> -45973 | BQ64: =+BR64-BS64 -> 46364 | BR64: =+BX64 -> 46371 | BS64: 7 | BT64: =+IF(BN64=0,BM64,BN64)+BS64 -> 398 | BV64: =+BT64-BR64 -> -45973 | BX64: 46371 | BY64: =+BT64-BX64 -> -45973 | CA64: Considero FE transmisores crono 4.11
A65: IN-Instrumentación | C65: Sistema fire & gas | E65: =+J65-1 -> 46027 | H65: =+F65-E65 -> -46027 | J65: =+K65-L65 -> 46028 | K65: =+R65-1 -> 46035 | L65: 7 | M65: =+F65+L65 -> 7 | O65: =+M65-K65 -> -46028 | R65: =+S65-T65 -> 46036 | S65: =+AC65-1 -> 46061 | T65: 25 | U65: =+M65+T65 -> 32 | W65: =+U65-S65 -> -46029 | AC65: =+AD65-AE65 -> 46062 | AD65: =+AJ65-1 -> 46107 | AE65: 45 | AF65: =+IF(V65=0,U65,V65)+AE65 -> 77 | AH65: =+AF65-AD65 -> -46030 | AJ65: =+AK65-AL65 -> 46108 | AK65: =+AV65-1 -> 46122 | AL65: 14 | AM65: =+IF(AG65=0,AF65,AG65)+AL65 -> 91 | AO65: =+AM65-AK65 -> -46031 | AV65: =+AW65-AX65 -> 46123 | AW65: =+BQ65-1 -> 46363 | AX65: 240 | AY65: =+IF(AN65=0,AM65,AN65)+AX65 -> 331 | BA65: =+AY65-AW65 -> -46032 | BC65: =+BD65-BE65 -> 46364 | BD65: =+BJ65 -> 46364 | BE65: 0 | BF65: =+IF(AZ65=0,AY65,AZ65)+BE65 -> 331 | BH65: =+BF65-BD65 -> -46033 | BJ65: =+BK65-BL65 -> 46364 | BK65: =+BQ65 -> 46364 | BL65: 0 | BM65: =+IF(BG65=0,BF65,BG65)+BL65 -> 331 | BO65: =+BM65-BK65 -> -46033 | BQ65: =+BR65-BS65 -> 46364 | BR65: =+BX65 -> 46371 | BS65: 7 | BT65: =+IF(BN65=0,BM65,BN65)+BS65 -> 338 | BV65: =+BT65-BR65 -> -46033 | BX65: 46371 | BY65: =+BT65-BX65 -> -46033 | CA65: Considero FE transmisores crono 4.11
A66: IN-Instrumentación | C66: Sistema contra incendio | E66: =+J66-1 -> 46027 | H66: =+F66-E66 -> -46027 | J66: =+K66-L66 -> 46028 | K66: =+R66-1 -> 46035 | L66: 7 | M66: =+F66+L66 -> 7 | O66: =+M66-K66 -> -46028 | R66: =+S66-T66 -> 46036 | S66: =+AC66-1 -> 46061 | T66: 25 | U66: =+M66+T66 -> 32 | W66: =+U66-S66 -> -46029 | AC66: =+AD66-AE66 -> 46062 | AD66: =+AJ66-1 -> 46107 | AE66: 45 | AF66: =+IF(V66=0,U66,V66)+AE66 -> 77 | AH66: =+AF66-AD66 -> -46030 | AJ66: =+AK66-AL66 -> 46108 | AK66: =+AV66-1 -> 46122 | AL66: 14 | AM66: =+IF(AG66=0,AF66,AG66)+AL66 -> 91 | AO66: =+AM66-AK66 -> -46031 | AV66: =+AW66-AX66 -> 46123 | AW66: =+BQ66-1 -> 46363 | AX66: 240 | AY66: =+IF(AN66=0,AM66,AN66)+AX66 -> 331 | BA66: =+AY66-AW66 -> -46032 | BC66: =+BD66-BE66 -> 46364 | BD66: =+BJ66 -> 46364 | BE66: 0 | BF66: =+IF(AZ66=0,AY66,AZ66)+BE66 -> 331 | BH66: =+BF66-BD66 -> -46033 | BJ66: =+BK66-BL66 -> 46364 | BK66: =+BQ66 -> 46364 | BL66: 0 | BM66: =+IF(BG66=0,BF66,BG66)+BL66 -> 331 | BO66: =+BM66-BK66 -> -46033 | BQ66: =+BR66-BS66 -> 46364 | BR66: =+BX66 -> 46371 | BS66: 7 | BT66: =+IF(BN66=0,BM66,BN66)+BS66 -> 338 | BV66: =+BT66-BR66 -> -46033 | BX66: 46371 | BY66: =+BT66-BX66 -> -46033 | CA66: Considero FE transmisores crono 4.11
A67: EL-Electricidad | C67: Shelter y banco de carga | E67: =+J67-1 -> 45948 | H67: =+F67-E67 -> -45948 | J67: =+K67-L67 -> 45949 | K67: =+R67-1 -> 45956 | L67: 7 | M67: =+F67+L67 -> 7 | O67: =+M67-K67 -> -45949 | R67: =+S67-T67 -> 45957 | S67: =+AC67-1 -> 45982 | T67: 25 | U67: =+M67+T67 -> 32 | W67: =+U67-S67 -> -45950 | AC67: =+AD67-AE67 -> 45983 | AD67: =+AJ67-1 -> 46028 | AE67: 45 | AF67: =+IF(V67=0,U67,V67)+AE67 -> 77 | AH67: =+AF67-AD67 -> -45951 | AJ67: =+AK67-AL67 -> 46029 | AK67: =+AV67-1 -> 46043 | AL67: 14 | AM67: =+IF(AG67=0,AF67,AG67)+AL67 -> 91 | AO67: =+AM67-AK67 -> -45952 | AV67: =+AW67-AX67 -> 46044 | AW67: =+BQ67-1 -> 46344 | AX67: 300 | AY67: =+IF(AN67=0,AM67,AN67)+AX67 -> 391 | BA67: =+AY67-AW67 -> -45953 | BC67: =+BD67-BE67 -> 46345 | BD67: =+BJ67 -> 46345 | BE67: 0 | BF67: =+IF(AZ67=0,AY67,AZ67)+BE67 -> 391 | BH67: =+BF67-BD67 -> -45954 | BJ67: =+BK67-BL67 -> 46345 | BK67: =+BQ67 -> 46345 | BL67: 0 | BM67: =+IF(BG67=0,BF67,BG67)+BL67 -> 391 | BO67: =+BM67-BK67 -> -45954 | BQ67: =+BR67-BS67 -> 46345 | BR67: =+BX67 -> 46352 | BS67: 7 | BT67: =+IF(BN67=0,BM67,BN67)+BS67 -> 398 | BV67: =+BT67-BR67 -> -45954 | BX67: 46352 | BY67: =+BT67-BX67 -> -45954 | CA67: Considero fecha de entrega de acuerdo a crono 4.11
A68: EL-Electricidad | C68: Tableros y celdas MT | E68: =+J68-1 -> 45895 | H68: =+F68-E68 -> -45895 | J68: =+K68-L68 -> 45896 | K68: =+R68-1 -> 45903 | L68: 7 | M68: =+F68+L68 -> 7 | O68: =+M68-K68 -> -45896 | R68: =+S68-T68 -> 45904 | S68: =+AC68-1 -> 45929 | T68: 25 | U68: =+M68+T68 -> 32 | W68: =+U68-S68 -> -45897 | AC68: =+AD68-AE68 -> 45930 | AD68: =+AJ68-1 -> 45975 | AE68: 45 | AF68: =+IF(V68=0,U68,V68)+AE68 -> 77 | AH68: =+AF68-AD68 -> -45898 | AJ68: =+AK68-AL68 -> 45976 | AK68: =+AV68-1 -> 45990 | AL68: 14 | AM68: =+IF(AG68=0,AF68,AG68)+AL68 -> 91 | AO68: =+AM68-AK68 -> -45899 | AV68: =+AW68-AX68 -> 45991 | AW68: =+BQ68-1 -> 46351 | AX68: 360 | AY68: =+IF(AN68=0,AM68,AN68)+AX68 -> 451 | BA68: =+AY68-AW68 -> -45900 | BC68: =+BD68-BE68 -> 46352 | BD68: =+BJ68 -> 46352 | BE68: 0 | BF68: =+IF(AZ68=0,AY68,AZ68)+BE68 -> 451 | BH68: =+BF68-BD68 -> -45901 | BJ68: =+BK68-BL68 -> 46352 | BK68: =+BQ68 -> 46352 | BL68: 0 | BM68: =+IF(BG68=0,BF68,BG68)+BL68 -> 451 | BO68: =+BM68-BK68 -> -45901 | BQ68: =+BR68-BS68 -> 46352 | BR68: =+BX68 -> 46359 | BS68: 7 | BT68: =+IF(BN68=0,BM68,BN68)+BS68 -> 458 | BV68: =+BT68-BR68 -> -45901 | BX68: 46359 | BY68: =+BT68-BX68 -> -45901 | CA68: Considero fecha de entrega de acuerdo a crono 4.11
A69: EL-Electricidad | C69: Tableros BT y CCM | E69: =+J69-1 -> 45852 | H69: =+F69-E69 -> -45852 | J69: =+K69-L69 -> 45853 | K69: =+R69-1 -> 45860 | L69: 7 | M69: =+F69+L69 -> 7 | O69: =+M69-K69 -> -45853 | R69: =+S69-T69 -> 45861 | S69: =+AC69-1 -> 45886 | T69: 25 | U69: =+M69+T69 -> 32 | W69: =+U69-S69 -> -45854 | AC69: =+AD69-AE69 -> 45887 | AD69: =+AJ69-1 -> 45932 | AE69: 45 | AF69: =+IF(V69=0,U69,V69)+AE69 -> 77 | AH69: =+AF69-AD69 -> -45855 | AJ69: =+AK69-AL69 -> 45933 | AK69: =+AV69-1 -> 45947 | AL69: 14 | AM69: =+IF(AG69=0,AF69,AG69)+AL69 -> 91 | AO69: =+AM69-AK69 -> -45856 | AV69: =+AW69-AX69 -> 45948 | AW69: =+BQ69-1 -> 46308 | AX69: 360 | AY69: =+IF(AN69=0,AM69,AN69)+AX69 -> 451 | BA69: =+AY69-AW69 -> -45857 | BC69: =+BD69-BE69 -> 46309 | BD69: =+BJ69 -> 46309 | BE69: 0 | BF69: =+IF(AZ69=0,AY69,AZ69)+BE69 -> 451 | BH69: =+BF69-BD69 -> -45858 | BJ69: =+BK69-BL69 -> 46309 | BK69: =+BQ69 -> 46309 | BL69: 0 | BM69: =+IF(BG69=0,BF69,BG69)+BL69 -> 451 | BO69: =+BM69-BK69 -> -45858 | BQ69: =+BR69-BS69 -> 46309 | BR69: =+BX69 -> 46316 | BS69: 7 | BT69: =+IF(BN69=0,BM69,BN69)+BS69 -> 458 | BV69: =+BT69-BR69 -> -45858 | BX69: 46316 | BY69: =+BT69-BX69 -> -45858 | CA69: Considero fecha de entrega de acuerdo a crono 4.11
A70: EL-Electricidad | C70: Canalizaciones eléctricas | E70: =+J70-1 -> 45842 | H70: =+F70-E70 -> -45842 | J70: =+K70-L70 -> 45843 | K70: =+R70-1 -> 45850 | L70: 7 | M70: =+F70+L70 -> 7 | O70: =+M70-K70 -> -45843 | R70: =+S70-T70 -> 45851 | S70: =+AC70-1 -> 45876 | T70: 25 | U70: =+M70+T70 -> 32 | W70: =+U70-S70 -> -45844 | AC70: =+AD70-AE70 -> 45877 | AD70: =+AJ70-1 -> 45907 | AE70: 30 | AF70: =+IF(V70=0,U70,V70)+AE70 -> 62 | AH70: =+AF70-AD70 -> -45845 | AJ70: =+AK70-AL70 -> 45908 | AK70: =+AV70-1 -> 45922 | AL70: 14 | AM70: =+IF(AG70=0,AF70,AG70)+AL70 -> 76 | AO70: =+AM70-AK70 -> -45846 | AV70: =+AW70-AX70 -> 45923 | AW70: =+BQ70-1 -> 46043 | AX70: 120 | AY70: =+IF(AN70=0,AM70,AN70)+AX70 -> 196 | BA70: =+AY70-AW70 -> -45847 | BC70: =+BD70-BE70 -> 46044 | BD70: =+BJ70 -> 46044 | BE70: 0 | BF70: =+IF(AZ70=0,AY70,AZ70)+BE70 -> 196 | BH70: =+BF70-BD70 -> -45848 | BJ70: =+BK70-BL70 -> 46044 | BK70: =+BQ70 -> 46044 | BL70: 0 | BM70: =+IF(BG70=0,BF70,BG70)+BL70 -> 196 | BO70: =+BM70-BK70 -> -45848 | BQ70: =+BR70-BS70 -> 46044 | BR70: =+BX70 -> 46051 | BS70: 7 | BT70: =+IF(BN70=0,BM70,BN70)+BS70 -> 203 | BV70: =+BT70-BR70 -> -45848 | BX70: 46051 | BY70: =+BT70-BX70 -> -45848 | CA70: Considero fecha de entrega de acuerdo a crono 4.11
A71: EL-Electricidad | C71: Cables Rev. 0 - Ingeniería inicial | E71: =+J71-1 -> 45892 | H71: =+F71-E71 -> -45892 | J71: =+K71-L71 -> 45893 | K71: =+R71-1 -> 45900 | L71: 7 | M71: =+F71+L71 -> 7 | O71: =+M71-K71 -> -45893 | R71: =+S71-T71 -> 45901 | S71: =+AC71-1 -> 45926 | T71: 25 | U71: =+M71+T71 -> 32 | W71: =+U71-S71 -> -45894 | AC71: =+AD71-AE71 -> 45927 | AD71: =+AJ71-1 -> 45972 | AE71: 45 | AF71: =+IF(V71=0,U71,V71)+AE71 -> 77 | AH71: =+AF71-AD71 -> -45895 | AJ71: =+AK71-AL71 -> 45973 | AK71: =+AV71-1 -> 45987 | AL71: 14 | AM71: =+IF(AG71=0,AF71,AG71)+AL71 -> 91 | AO71: =+AM71-AK71 -> -45896 | AV71: =+AW71-AX71 -> 45988 | AW71: =+BQ71-1 -> 46168 | AX71: 180 | AY71: =+IF(AN71=0,AM71,AN71)+AX71 -> 271 | BA71: =+AY71-AW71 -> -45897 | BC71: =+BD71-BE71 -> 46169 | BD71: =+BJ71 -> 46169 | BE71: 0 | BF71: =+IF(AZ71=0,AY71,AZ71)+BE71 -> 271 | BH71: =+BF71-BD71 -> -45898 | BJ71: =+BK71-BL71 -> 46169 | BK71: =+BQ71 -> 46169 | BL71: 0 | BM71: =+IF(BG71=0,BF71,BG71)+BL71 -> 271 | BO71: =+BM71-BK71 -> -45898 | BQ71: =+BR71-BS71 -> 46169 | BR71: =+BX71 -> 46176 | BS71: 7 | BT71: =+IF(BN71=0,BM71,BN71)+BS71 -> 278 | BV71: =+BT71-BR71 -> -45898 | BX71: 46176 | BY71: =+BT71-BX71 -> -45898 | CA71: Considero fecha de entrega de acuerdo a crono 4.11
A72: EL-Electricidad | C72: Cables Rev. 1 - Ingeniería 80% | E72: =+J72-1 -> 46016 | F72: =+F63 -> 46168 | H72: =+F72-E72 -> 152 | J72: =+K72-L72 -> 46017 | K72: =+R72-1 -> 46024 | L72: 7 | M72: =+F72+L72 -> 46175 | O72: =+M72-K72 -> 151 | R72: =+S72-T72 -> 46025 | S72: =+AC72-1 -> 46050 | T72: 25 | U72: =+M72+T72 -> 46200 | W72: =+U72-S72 -> 150 | AC72: =+AD72-AE72 -> 46051 | AD72: =+AJ72-1 -> 46096 | AE72: 45 | AF72: =+IF(V72=0,U72,V72)+AE72 -> 46245 | AH72: =+AF72-AD72 -> 149 | AJ72: =+AK72-AL72 -> 46097 | AK72: =+AV72-1 -> 46111 | AL72: 14 | AM72: =+IF(AG72=0,AF72,AG72)+AL72 -> 46259 | AO72: =+AM72-AK72 -> 148 | AV72: =+AW72-AX72 -> 46112 | AW72: =+BQ72-1 -> 46232 | AX72: 120 | AY72: =+IF(AN72=0,AM72,AN72)+AX72 -> 46379 | BA72: =+AY72-AW72 -> 147 | BC72: =+BD72-BE72 -> 46233 | BD72: =+BJ72 -> 46233 | BE72: 0 | BF72: =+IF(AZ72=0,AY72,AZ72)+BE72 -> 46379 | BH72: =+BF72-BD72 -> 146 | BJ72: =+BK72-BL72 -> 46233 | BK72: =+BQ72 -> 46233 | BL72: 0 | BM72: =+IF(BG72=0,BF72,BG72)+BL72 -> 46379 | BO72: =+BM72-BK72 -> 146 | BQ72: =+BR72-BS72 -> 46233 | BR72: =+BX72 -> 46240 | BS72: 7 | BT72: =+IF(BN72=0,BM72,BN72)+BS72 -> 46386 | BV72: =+BT72-BR72 -> 146 | BX72: 46240 | BY72: =+BT72-BX72 -> 146 | CA72: Considero fecha de inicio de tendido de cables crono 4.11
A73: EL-Electricidad | C73: Materiales para PAT | E73: =+J73-1 -> 46130 | F73: =+F77 -> 45748 | H73: =+F73-E73 -> -382 | J73: =+K73-L73 -> 46131 | K73: =+R73-1 -> 46138 | L73: 7 | M73: =+F73+L73 -> 45755 | O73: =+M73-K73 -> -383 | R73: =+S73-T73 -> 46139 | S73: =+AC73-1 -> 46164 | T73: 25 | U73: =+M73+T73 -> 45780 | W73: =+U73-S73 -> -384 | AC73: =+AD73-AE73 -> 46165 | AD73: =+AJ73-1 -> 46195 | AE73: 30 | AF73: =+IF(V73=0,U73,V73)+AE73 -> 45810 | AH73: =+AF73-AD73 -> -385 | AJ73: =+AK73-AL73 -> 46196 | AK73: =+AV73-1 -> 46210 | AL73: 14 | AM73: =+IF(AG73=0,AF73,AG73)+AL73 -> 45824 | AO73: =+AM73-AK73 -> -386 | AV73: =+AW73-AX73 -> 46211 | AW73: =+BQ73-1 -> 46331 | AX73: 120 | AY73: =+IF(AN73=0,AM73,AN73)+AX73 -> 45944 | BA73: =+AY73-AW73 -> -387 | BC73: =+BD73-BE73 -> 46332 | BD73: =+BJ73 -> 46332 | BE73: 0 | BF73: =+IF(AZ73=0,AY73,AZ73)+BE73 -> 45944 | BH73: =+BF73-BD73 -> -388 | BJ73: =+BK73-BL73 -> 46332 | BK73: =+BQ73 -> 46332 | BL73: 0 | BM73: =+IF(BG73=0,BF73,BG73)+BL73 -> 45944 | BO73: =+BM73-BK73 -> -388 | BQ73: =+BR73-BS73 -> 46332 | BR73: =+BX73 -> 46339 | BS73: 7 | BT73: =+IF(BN73=0,BM73,BN73)+BS73 -> 45951 | BV73: =+BT73-BR73 -> -388 | BX73: 46339 | BY73: =+BT73-BX73 -> -388 | CA73: Considero fecha de entrega de acuerdo a crono 4.11
A74: EL-Electricidad | C74: Sistema UPS y rectificadores | E74: =+J74-1 -> 45962 | H74: =+F74-E74 -> -45962 | J74: =+K74-L74 -> 45963 | K74: =+R74-1 -> 45970 | L74: 7 | M74: =+F74+L74 -> 7 | O74: =+M74-K74 -> -45963 | R74: =+S74-T74 -> 45971 | S74: =+AC74-1 -> 45996 | T74: 25 | U74: =+M74+T74 -> 32 | W74: =+U74-S74 -> -45964 | AC74: =+AD74-AE74 -> 45997 | AD74: =+AJ74-1 -> 46042 | AE74: 45 | AF74: =+IF(V74=0,U74,V74)+AE74 -> 77 | AH74: =+AF74-AD74 -> -45965 | AJ74: =+AK74-AL74 -> 46043 | AK74: =+AV74-1 -> 46057 | AL74: 14 | AM74: =+IF(AG74=0,AF74,AG74)+AL74 -> 91 | AO74: =+AM74-AK74 -> -45966 | AV74: =+AW74-AX74 -> 46058 | AW74: =+BQ74-1 -> 46358 | AX74: 300 | AY74: =+IF(AN74=0,AM74,AN74)+AX74 -> 391 | BA74: =+AY74-AW74 -> -45967 | BC74: =+BD74-BE74 -> 46359 | BD74: =+BJ74 -> 46359 | BE74: 0 | BF74: =+IF(AZ74=0,AY74,AZ74)+BE74 -> 391 | BH74: =+BF74-BD74 -> -45968 | BJ74: =+BK74-BL74 -> 46359 | BK74: =+BQ74 -> 46359 | BL74: 0 | BM74: =+IF(BG74=0,BF74,BG74)+BL74 -> 391 | BO74: =+BM74-BK74 -> -45968 | BQ74: =+BR74-BS74 -> 46359 | BR74: =+BX74 -> 46366 | BS74: 7 | BT74: =+IF(BN74=0,BM74,BN74)+BS74 -> 398 | BV74: =+BT74-BR74 -> -45968 | BX74: 46366 | BY74: =+BT74-BX74 -> -45968 | CA74: Considero fecha de entrega de acuerdo a crono 4.11
A75: EL-Electricidad | C75: Tracing | E75: =+J75-1 -> 46138 | H75: =+F75-E75 -> -46138 | J75: =+K75-L75 -> 46139 | K75: =+R75-1 -> 46146 | L75: 7 | M75: =+F75+L75 -> 7 | O75: =+M75-K75 -> -46139 | R75: =+S75-T75 -> 46147 | S75: =+AC75-1 -> 46172 | T75: 25 | U75: =+M75+T75 -> 32 | W75: =+U75-S75 -> -46140 | AC75: =+AD75-AE75 -> 46173 | AD75: =+AJ75-1 -> 46203 | AE75: 30 | AF75: =+IF(V75=0,U75,V75)+AE75 -> 62 | AH75: =+AF75-AD75 -> -46141 | AJ75: =+AK75-AL75 -> 46204 | AK75: =+AV75-1 -> 46218 | AL75: 14 | AM75: =+IF(AG75=0,AF75,AG75)+AL75 -> 76 | AO75: =+AM75-AK75 -> -46142 | AV75: =+AW75-AX75 -> 46219 | AW75: =+BQ75-1 -> 46369 | AX75: 150 | AY75: =+IF(AN75=0,AM75,AN75)+AX75 -> 226 | BA75: =+AY75-AW75 -> -46143 | BC75: =+BD75-BE75 -> 46370 | BD75: =+BJ75 -> 46370 | BE75: 0 | BF75: =+IF(AZ75=0,AY75,AZ75)+BE75 -> 226 | BH75: =+BF75-BD75 -> -46144 | BJ75: =+BK75-BL75 -> 46370 | BK75: =+BQ75 -> 46370 | BL75: 0 | BM75: =+IF(BG75=0,BF75,BG75)+BL75 -> 226 | BO75: =+BM75-BK75 -> -46144 | BQ75: =+BR75-BS75 -> 46370 | BR75: =+BX75 -> 46377 | BS75: 7 | BT75: =+IF(BN75=0,BM75,BN75)+BS75 -> 233 | BV75: =+BT75-BR75 -> -46144 | BX75: 46377 | BY75: =+BT75-BX75 -> -46144 | CA75: Considero fecha de entrega de acuerdo a crono 4.11
A76: EL-Electricidad | C76: Ducto de barras | E76: =+J76-1 -> 45912 | H76: =+F76-E76 -> -45912 | J76: =+K76-L76 -> 45913 | K76: =+R76-1 -> 45920 | L76: 7 | M76: =+F76+L76 -> 7 | O76: =+M76-K76 -> -45913 | R76: =+S76-T76 -> 45921 | S76: =+AC76-1 -> 45946 | T76: 25 | U76: =+M76+T76 -> 32 | W76: =+U76-S76 -> -45914 | AC76: =+AD76-AE76 -> 45947 | AD76: =+AJ76-1 -> 45992 | AE76: 45 | AF76: =+IF(V76=0,U76,V76)+AE76 -> 77 | AH76: =+AF76-AD76 -> -45915 | AJ76: =+AK76-AL76 -> 45993 | AK76: =+AV76-1 -> 46007 | AL76: 14 | AM76: =+IF(AG76=0,AF76,AG76)+AL76 -> 91 | AO76: =+AM76-AK76 -> -45916 | AV76: =+AW76-AX76 -> 46008 | AW76: =+BQ76-1 -> 46308 | AX76: 300 | AY76: =+IF(AN76=0,AM76,AN76)+AX76 -> 391 | BA76: =+AY76-AW76 -> -45917 | BC76: =+BD76-BE76 -> 46309 | BD76: =+BJ76 -> 46309 | BE76: 0 | BF76: =+IF(AZ76=0,AY76,AZ76)+BE76 -> 391 | BH76: =+BF76-BD76 -> -45918 | BJ76: =+BK76-BL76 -> 46309 | BK76: =+BQ76 -> 46309 | BL76: 0 | BM76: =+IF(BG76=0,BF76,BG76)+BL76 -> 391 | BO76: =+BM76-BK76 -> -45918 | BQ76: =+BR76-BS76 -> 46309 | BR76: =+BX76 -> 46316 | BS76: 7 | BT76: =+IF(BN76=0,BM76,BN76)+BS76 -> 398 | BV76: =+BT76-BR76 -> -45918 | BX76: 46316 | BY76: =+BT76-BX76 -> -45918 | CA76: Considero fecha de entrega de CCM y Tablero BT de acuerdo a crono 4.11
A77: PI-Piping | C77: Cañerías y accesorios - Rev. 0 - OC a 150 días Hito 2 | E77: =+J77-1 -> 45739 | F77: =+C82+60 -> 45748 | H77: =+F77-E77 -> 9 | J77: =+K77-L77 -> 45740 | K77: =+R77-1 -> 45747 | L77: 7 | M77: =+F77+L77 -> 45755 | O77: =+M77-K77 -> 8 | R77: =+S77-T77 -> 45748 | S77: =+AC77-1 -> 45773 | T77: 25 | U77: =+M77+T77 -> 45780 | W77: =+U77-S77 -> 7 | AC77: =+AD77-AE77 -> 45774 | AD77: =+AJ77-1 -> 45774 | AF77: =+IF(V77=0,U77,V77)+AE77 -> 45780 | AH77: =+AF77-AD77 -> 6 | AJ77: =+AK77-AL77 -> 45775 | AK77: =+AV77-1 -> 45789 | AL77: 14 | AM77: =+IF(AG77=0,AF77,AG77)+AL77 -> 45794 | AO77: =+AM77-AK77 -> 5 | AV77: =+AW77-AX77 -> 45790 | AW77: =+BC77 -> 45865 | AX77: 75 | AY77: =+IF(AN77=0,AM77,AN77)+AX77 -> 45869 | BA77: =+AY77-AW77 -> 4 | BC77: =+BD77-BE77 -> 45865 | BD77: =+BJ77 -> 45955 | BE77: 90 | BF77: =+IF(AZ77=0,AY77,AZ77)+BE77 -> 45959 | BH77: =+BF77-BD77 -> 4 | BJ77: =+BK77-BL77 -> 45955 | BK77: =+BQ77 -> 45965 | BL77: 10 | BM77: =+IF(BG77=0,BF77,BG77)+BL77 -> 45969 | BO77: =+BM77-BK77 -> 4 | BQ77: =+BR77-BS77 -> 45965 | BR77: =+BX77 -> 45972 | BS77: 7 | BT77: =+IF(BN77=0,BM77,BN77)+BS77 -> 45976 | BV77: =+BT77-BR77 -> 4 | BX77: 45972 | BY77: =+BT77-BX77 -> 4 | CA77: Considero fecha de entrega de suministro temprano de piping de crono A8910
A78: PI-Piping | C78: Cañerías y accesorios - Rev. 1 - Ingeniería 80% | E78: =+J78-1 -> 45875 | F78: =+F72 -> 46168 | H78: =+F78-E78 -> 293 | J78: =+K78-L78 -> 45876 | K78: =+R78-1 -> 45883 | L78: 7 | M78: =+F78+L78 -> 46175 | O78: =+M78-K78 -> 292 | R78: =+S78-T78 -> 45884 | S78: =+AC78-1 -> 45909 | T78: 25 | U78: =+M78+T78 -> 46200 | W78: =+U78-S78 -> 291 | AC78: =+AD78-AE78 -> 45910 | AD78: =+AJ78-1 -> 45910 | AF78: =+IF(V78=0,U78,V78)+AE78 -> 46200 | AH78: =+AF78-AD78 -> 290 | AJ78: =+AK78-AL78 -> 45911 | AK78: =+AV78-1 -> 45925 | AL78: 14 | AM78: =+IF(AG78=0,AF78,AG78)+AL78 -> 46214 | AO78: =+AM78-AK78 -> 289 | AV78: =+AW78-AX78 -> 45926 | AW78: =+BQ78-1 -> 46001 | AX78: 75 | AY78: =+IF(AN78=0,AM78,AN78)+AX78 -> 46289 | BA78: =+AY78-AW78 -> 288 | BC78: =+BD78-BE78 -> 45962 | BD78: =+BJ78 -> 45992 | BE78: 30 | BF78: =+IF(AZ78=0,AY78,AZ78)+BE78 -> 46319 | BH78: =+BF78-BD78 -> 327 | BJ78: =+BK78-BL78 -> 45992 | BK78: =+BQ78 -> 46002 | BL78: 10 | BM78: =+IF(BG78=0,BF78,BG78)+BL78 -> 46329 | BO78: =+BM78-BK78 -> 327 | BQ78: =+BR78-BS78 -> 46002 | BR78: =+BX78 -> 46009 | BS78: 7 | BT78: =+IF(BN78=0,BM78,BN78)+BS78 -> 46336 | BV78: =+BT78-BR78 -> 327 | BX78: 46009 | BY78: =+BT78-BX78 -> 327 | CA78: Considero fecha de fin de entrega piping de crono 4.11 - Coincide con inicio de prefa
A79: PI-Piping | C79: Válvulas manuales - Rev. 0 - Ingeniería inicial | E79: =+J79-1 -> 46140 | H79: =+F79-E79 -> -46140 | J79: =+K79-L79 -> 46141 | K79: =+R79-1 -> 46148 | L79: 7 | M79: =+F79+L79 -> 7 | O79: =+M79-K79 -> -46141 | R79: =+S79-T79 -> 46149 | S79: =+AC79-1 -> 46174 | T79: 25 | U79: =+M79+T79 -> 32 | W79: =+U79-S79 -> -46142 | AC79: =+AD79-AE79 -> 46175 | AD79: =+AJ79-1 -> 46220 | AE79: 45 | AF79: =+IF(V79=0,U79,V79)+AE79 -> 77 | AH79: =+AF79-AD79 -> -46143 | AJ79: =+AK79-AL79 -> 46221 | AK79: =+AV79-1 -> 46235 | AL79: 14 | AM79: =+IF(AG79=0,AF79,AG79)+AL79 -> 91 | AO79: =+AM79-AK79 -> -46144 | AV79: =+AW79-AX79 -> 46236 | AW79: =+BQ79-1 -> 46386 | AX79: 150 | AY79: =+IF(AN79=0,AM79,AN79)+AX79 -> 241 | BA79: =+AY79-AW79 -> -46145 | BC79: =+BD79-BE79 -> 46287 | BD79: =+BJ79 -> 46377 | BE79: 90 | BF79: =+IF(AZ79=0,AY79,AZ79)+BE79 -> 331 | BH79: =+BF79-BD79 -> -46046 | BJ79: =+BK79-BL79 -> 46377 | BK79: =+BQ79 -> 46387 | BL79: 10 | BM79: =+IF(BG79=0,BF79,BG79)+BL79 -> 341 | BO79: =+BM79-BK79 -> -46046 | BQ79: =+BR79-BS79 -> 46387 | BR79: =+BX79 -> 46394 | BS79: 7 | BT79: =+IF(BN79=0,BM79,BN79)+BS79 -> 348 | BV79: =+BT79-BR79 -> -46046 | BX79: 46394 | BY79: =+BT79-BX79 -> -46046 | CA79: Considero fecha de fin de entrega piping de crono 4.11
A80: PI-Piping | C80: Válvulas manuales - Rev. 1 - Ingeniería 80% | E80: =+J80-1 -> 46140 | F80: =+F78 -> 46168 | H80: =+F80-E80 -> 28 | J80: =+K80-L80 -> 46141 | K80: =+R80-1 -> 46148 | L80: 7 | M80: =+F80+L80 -> 46175 | O80: =+M80-K80 -> 27 | R80: =+S80-T80 -> 46149 | S80: =+AC80-1 -> 46174 | T80: 25 | U80: =+M80+T80 -> 46200 | W80: =+U80-S80 -> 26 | AC80: =+AD80-AE80 -> 46175 | AD80: =+AJ80-1 -> 46220 | AE80: 45 | AF80: =+IF(V80=0,U80,V80)+AE80 -> 46245 | AH80: =+AF80-AD80 -> 25 | AJ80: =+AK80-AL80 -> 46221 | AK80: =+AV80-1 -> 46235 | AL80: 14 | AM80: =+IF(AG80=0,AF80,AG80)+AL80 -> 46259 | AO80: =+AM80-AK80 -> 24 | AV80: =+AW80-AX80 -> 46236 | AW80: =+BQ80-1 -> 46386 | AX80: 150 | AY80: =+IF(AN80=0,AM80,AN80)+AX80 -> 46409 | BA80: =+AY80-AW80 -> 23 | BC80: =+BD80-BE80 -> 46347 | BD80: =+BJ80 -> 46377 | BE80: 30 | BF80: =+IF(AZ80=0,AY80,AZ80)+BE80 -> 46439 | BH80: =+BF80-BD80 -> 62 | BJ80: =+BK80-BL80 -> 46377 | BK80: =+BQ80 -> 46387 | BL80: 10 | BM80: =+IF(BG80=0,BF80,BG80)+BL80 -> 46449 | BO80: =+BM80-BK80 -> 62 | BQ80: =+BR80-BS80 -> 46387 | BR80: =+BX80 -> 46394 | BS80: 7 | BT80: =+IF(BN80=0,BM80,BN80)+BS80 -> 46456 | BV80: =+BT80-BR80 -> 62 | BX80: 46394 | BY80: =+BT80-BX80 -> 62 | CA80: Considero fecha de fin de entrega piping de crono 4.11
A82: Fecha asumida inicio | B82: 45688 | C82: =+B82 -> 45688 | E82: LAS PLANIFICADAS P/ COMPRA EN FUNCIÓN DE ESTRATEGIA SUMINISTROS/PROYECTO | Y82: VA A DEPENDER DE CADA ESTRATEGIA DE PROYECTO | AV82: SE PUEDE ABRIR LOS TIEMPOS DE VENDORS/INSPECCIÓN, ETC | BC82: DEPENDE DE LA ESTRATEGIA DEL SUMINISTRO/PROYECTO | BQ82: SI HAY DESAGREACIÓN EN CANNING SE PUEDE PLANIFICAR TAMBIÉN | BX82: INTERNO SUMINISTROS PARA PREVEER IMPACTOS, ALERTAR Y ARTICULAR CON CONSTRUCCIONES
A83: Fecha RFSU | B83: =+B82+740 -> 46428 | C83: =+B83 -> 46428
A85: Hito ingeniería 80% | C85: =+C82+480 -> 46168
E86: TIEMPO PLANIFICADO DE INGENERIA | J86: TIEMPO PLANIFICADO PARA ADMINISTRACIÓN DE MATERIALES | R86: TIEMPO PLANIFICADO PARA COMPRAS | Y86: TIEMPO PLANIFICADO INGENIERÍA | AJ86: TIEMPO PLANIFICADO COMPRAS | AV86: TIEMPO PLANIFICADO INGENIERÍA/ACTIVACIÓN/INSPECCIÓN | BC86: TIEMPO PLANIFICADO COMEX | BJ86: TIEMPO PLANIFICADO COMEX | BQ86: TIEMPO PLANIFICADO LOGISTICA Y ALMACES

Sheet LD Ingeniería de detalle
E1: TITULO: | G1: DOCUMENTO Nº:
E2: =+[70]Carátula!K59 -> LISTADO DE DOCUMENTOS - EPC CPF2 LA CALERA | G2: =+[70]Carátula!K62 -> XXX-ACAL-102-LD-X-300
E3: =+[70]Carátula!K60 -> GENERAL | G3: REVISION: | H3: 0
G4: Pag:
B6: DISC | C6: CÓDIGO PLUSPETROL | D6: CÓDIGO AESA | E6: DESCRIPCION | F6: APR | G6: DISEÑO | H6: REQ APR CLIENTE? | I6: CAO | J6: COMENTARIOS
A8: 1 | B8: GENERAL | C8: XXX-ACAL-102-LD-X-300 | D8: 5155-00-0000-IG-CO-LD-001 | E8: LISTADO DE DOCUMENTOS | H8: SI | I8: NO
A9: 1 | B9: GENERAL | C9: XXX-ACAL-102-ET-X-300 | D9: 5155-00-0000-IG-CO-BD-001 | E9: BASES DE DISEÑO | H9: SI | I9: NO
A10: 1 | B10: GENERAL | C10: XXX-ACAL-102-SC-X-300 | D10: 5155-00-0000-IG-CO-PG-001 | E10: CRONOGRAMA DE INGENIERÍA | H10: NO | I10: NO
B11: GENERAL | E11: PLAN DE RELEVAMIENTO | H11: NO | I11: NO
B12: GENERAL | E12: INFORME DE RELEVAMIENTO | H12: NO | I12: NO
B13: GENERAL | E13: INFORME DE ANÁLISIS DE CONSISTENCIA | H13: NO | I13: NO
B14: ELECTRICIDAD | D14: 5155-00-2300-IG-EL-EE-XXX | E14: DIAGRAMA UNIFILAR ELÉCTRICO GENERAL | H14: SI | I14: NO
A15: 2 | B15: ELECTRICIDAD | D15: 5155-00-2000-IG-EL-EE-XXX | E15: DIAGRAMA UNIFILAR - AMPLIACIÓN AREA ANTENA | H15: SI | I15: NO
A16: 3 | B16: ELECTRICIDAD | D16: 5155-00-2300-IG-EL-EE-XXX | E16: DIAGRAMA UNIFILAR - TABLERO 13,2 kV 102-TGMT-001 - SALA ELÉCTRICA 3 | H16: SI | I16: NO
A17: 1 | B17: ELECTRICIDAD | D17: 5155-00-2300-IG-EL-EE-XXX | E17: DIAGRAMA UNIFILAR - TABLERO 6,6 kV 102-TGMT-003 - SALA ELÉCTRICA 4 | H17: SI | I17: NO
A18: 1 | B18: ELECTRICIDAD | D18: 5155-00-2300-IG-EL-EE-XXX | E18: DIAGRAMA UNIFILAR - 102-CCM-001 - SALA ELÉCTRICA 4 | H18: SI | I18: NO
A19: 1 | B19: ELECTRICIDAD | D19: 5155-00-2300-IG-EL-EE-XXX | E19: DIAGRAMA UNIFILAR - 102-CCM-002 - SALA ELÉCTRICA 3 | H19: SI | I19: NO
A20: 1 | B20: ELECTRICIDAD | D20: 5155-00-2300-IG-EL-EE-XXX | E20: DIAGRAMA UNIFILAR - 102-CCM-003 - SALA ELÉCTRICA 3 | H20: SI | I20: NO
A21: 1 | B21: ELECTRICIDAD | D21: 5155-00-2300-IG-EL-EE-XXX | E21: DIAGRAMA UNIFILAR - TABLERO DE UPS - SALA ELÉCTRICA 3 | H21: SI | I21: NO
A22: 1 | B22: ELECTRICIDAD | D22: 5155-00-2300-IG-EL-EE-XXX | E22: DIAGRAMA UNIFILAR - TABLERO DE UPS - SALA ELÉCTRICA 4 | H22: SI | I22: NO
A23: 1 | B23: ELECTRICIDAD | D23: 5155-00-2300-IG-EL-EE-XXX | E23: DIAGRAMA UNIFILAR - TABLERO DE CORRIENTE DIRECTA 110 VCC - SALA ELÉCTRICA 3 | H23: SI | I23: NO
A24: 1 | B24: ELECTRICIDAD | D24: 5155-00-2300-IG-EL-EE-XXX | E24: DIAGRAMA UNIFILAR - TABLERO DE CORRIENTE DIRECTA 110 VCC - SALA ELÉCTRICA 4 | H24: SI | I24: NO
A25: 1 | B25: ELECTRICIDAD | D25: 5155-00-2400-IG-EL-EE-XXX | E25: DIAGRAMA UNIFILAR - TABLERO DE CORRIENTE DIRECTA 110 VCC - SALAS REMOTAS INS007/INS008 | H25: SI | I25: NO
A26: 1 | B26: ELECTRICIDAD | D26: 5155-00-2300-IG-EL-EE-XXX | E26: DIAGRAMA UNIFILAR - TABLERO SERVICIOS AUXILIARES - SALA ELECTRICA 3 | H26: SI | I26: NO
... A59: 1 | B59: ELECTRICIDAD | D59: 5155-00-0000-IG-EL-MC-XXX | E59: MEMORIA DE CÁLCULO - SPCDA | H59: SI | I59: NO
B60: ELECTRICIDAD | D60: 5155-00-0000-IG-EL-MC-XXX | E60: MEMORIA DE CÁLCULO - OCUPACIÓN DE CANALIZACIONES ELÉCTRICAS | H60: SI | I60: NO
B61: ELECTRICIDAD | D61: 5155-00-0000-IG-EL-MC-XXX | E61: MEMORIA DE CÁLCULO - PUESTA A TIERRA | H61: SI | I61: NO
B62: ELECTRICIDAD | D62: 5155-00-0000-IG-EL-ES-XXX | E62: ESTUDIO DE CORTOCIRCUITO Y FLUJO DE CARGAS | H62: SI | I62: NO
B63: ELECTRICIDAD | D63: 5155-00-0000-IG-EL-ES-XXX | E63: ESTUDIO DE SELECTIVIDAD DE PROTECCIONES | H63: SI | I63: SI
B64: ELECTRICIDAD | D64: 5155-00-0000-IG-EL-ES-XXX | E64: ESTUDIO DE ARRANQUE DE MOTORES | H64: SI | I64: NO
B65: ELECTRICIDAD | D65: 5155-00-0000-IG-EL-ES-XXX | E65: ESTUDIO DE COMPONENTES ARMÓNICAS | H65: SI | I65: NO
B66: ELECTRICIDAD | D66: 5155-00-0000-IG-EL-MD-XXX | E66: MEMORIA DESCRIPTIVA DE LA INSTALACIÓN ELÉCTRICA/ SCADA Y PMS | H66: SI | I66: NO
B67: ELECTRICIDAD | D67: 5155-00-2300-IG-EL-ET-XXX | E67: ESPECIFICACIÓN TÉCNICA SALAS ELÉCTRICAS | H67: SI | I67: NO
B68: ELECTRICIDAD | D68: 5155-00-2300-IG-EL-ET-XXX | E68: ESPECIFICACIÓN TÉCNICA - SISTEMA DE TRANSFERENCIA AUTOMÁTICA | H68: SI | I68: NO
B69: ELECTRICIDAD | D69: 5155-00-2300-IG-EL-HD-XXX | E69: HOJA DE DATOS CCM | H69: SI | I69: NO
B70: ELECTRICIDAD | D70: 5155-00-2300-IG-EL-HD-XXX | E70: HOJA DE DATOS VFD BT | H70: SI | I70: NO
B71: ELECTRICIDAD | D71: 5155-00-2300-IG-EL-HD-XXX | E71: HOJA DE DATOS VFD MT | H71: SI | I71: NO
... B108: ELECTRICIDAD | D108: 5155-00-2000-IG-EL-LM-XXX | E108: LISTADO DE MATERIALES - PUESTA A TIERRA Y SPCDA - GENERACIÓN | H108: NO | I108: NO
A109: 1 | B109: ELECTRICIDAD | D109: 5155-00-2100-IG-EL-LM-XXX | E109: LISTADO DE MATERIALES - PUESTA A TIERRA Y SPCDA - HOT OIL | H109: NO | I109: NO
B110: ELECTRICIDAD | D110: 5155-00-2200-IG-EL-LM-XXX | E110: LISTADO DE MATERIALES - PUESTA A TIERRA Y SPCDA - SUMIDERO | H110: NO | I110: NO
A111: 2 | B111: ELECTRICIDAD | D111: 5155-00-2300-IG-EL-LM-XXX | E111: LISTADO DE MATERIALES - PUESTA A TIERRA Y SPCDA - SALA ELECTRICA | H111: NO | I111: NO
A112: 2 | B112: ELECTRICIDAD | D112: 5155-00-2400-IG-EL-LM-XXX | E112: LISTADO DE MATERIALES - PUESTA A TIERRA Y SPCDA - SHELTERS DE INSTRUMENTOS | H112: NO | I112: NO
A113: 2 | B113: ELECTRICIDAD | D113: 5155-00-0090-IG-EL-LM-XXX | E113: LISTADO DE MATERIALES - CANALIZACIONES - UNDERGROUND | H113: NO | I113: NO
A114: 2 | B114: ELECTRICIDAD | D114: 5155-00-0100-IG-EL-LM-XXX | E114: LISTADO DE MATERIALES - CANALIZACIONES - PARRAL E-O | H114: NO | I114: NO
A115: 2 | B115: ELECTRICIDAD | D115: 5155-00-0200-IG-EL-LM-XXX | E115: LISTADO DE MATERIALES - CANALIZACIONES - PARRAL N-S 1 | H115: NO | I115: NO
A116: 2 | B116: ELECTRICIDAD | D116: 5155-00-0300-IG-EL-LM-XXX | E116: LISTADO DE MATERIALES - CANALIZACIONES - PARRAL N-S 2 | H116: NO | I116: NO
A117: 2 | B117: ELECTRICIDAD | D117: 5155-00-0400-IG-EL-LM-XXX | E117: LISTADO DE MATERIALES - CANALIZACIONES - PARRAL ZONA HOT OIL | H117: NO | I117: NO
A118: 3 | B118: ELECTRICIDAD | D118: 5155-00-0500-IG-EL-LM-XXX | E118: LISTADO DE MATERIALES - CANALIZACIONES - SENDA NORTE | H118: NO | I118: NO
A119: 3 | B119: ELECTRICIDAD | D119: 5155-00-0600-IG-EL-LM-XXX | E119: LISTADO DE MATERIALES - CANALIZACIONES - PARRAL NORTE (ALIVIO) | H119: NO | I119: NO
A120: 3 | B120: ELECTRICIDAD | D120: 5155-00-0700-IG-EL-LM-XXX | E120: LISTADO DE MATERIALES - CANALIZACIONES - ZONA SLUG CATCHER | H120: NO | I120: NO
A121: 3 | B121: ELECTRICIDAD | D121: 5155-00-0800-IG-EL-LM-XXX | E121: LISTADO DE MATERIALES - CANALIZACIONES - SERVICIOS | H121: NO | I121: NO
A122: 2 | B122: ELECTRICIDAD | D122: 5155-00-0900-IG-EL-LM-XXX | E122: LISTADO DE MATERIALES - CANALIZACIONES - INTERCONEXIONES | H122: NO | I122: NO
... A175: 2 | B175: ELECTRICIDAD | D175: 5155-00-1700-IG-EL-LM-XXX | E175: LISTADO DE MATERIALES - MISCELANEOS - ALMACENAMIENTO DE CONDENSADO CPF2 | H175: NO | I175: NO
B176: ELECTRICIDAD | D176: 5155-00-1800-IG-EL-LM-XXX | E176: LISTADO DE MATERIALES - MISCELANEOS - PLANTA DE TRATAMIENTO DE AGUA | H176: NO | I176: NO
B177: ELECTRICIDAD | D177: 5155-00-2000-IG-EL-LM-XXX | E177: LISTADO DE MATERIALES - MISCELANEOS - GENERACIÓN | H177: NO | I177: NO
B178: ELECTRICIDAD | D178: 5155-00-2100-IG-EL-LM-XXX | E178: LISTADO DE MATERIALES - MISCELANEOS - HOT OIL | H178: NO | I178: NO
B179: ELECTRICIDAD | D179: 5155-00-2200-IG-EL-LM-XXX | E179: LISTADO DE MATERIALES - MISCELANEOS - SUMIDERO | H179: NO | I179: NO
B180: ELECTRICIDAD | D180: 5155-00-2300-IG-EL-LM-XXX | E180: LISTADO DE MATERIALES - MISCELANEOS - SALA ELECTRICA | H180: NO | I180: NO
B181: ELECTRICIDAD | D181: 5155-00-2400-IG-EL-LM-XXX | E181: LISTADO DE MATERIALES - MISCELANEOS - SHELTERS DE INSTRUMENTOS | H181: NO | I181: NO
B182: ELECTRICIDAD | D182: 5155-00-0090-IG-EL-PL-XXX | E182: PLANO DE CANALIZACIONES ELÉCTRICAS - UNDERGROUND | H182: SI | I182: SI
B183: ELECTRICIDAD | D183: 5155-00-0100-IG-EL-PL-XXX | E183: PLANO DE CANALIZACIONES ELÉCTRICAS - PARRAL E-O | H183: SI | I183: SI
B184: ELECTRICIDAD | D184: 5155-00-0200-IG-EL-PL-XXX | E184: PLANO DE CANALIZACIONES ELÉCTRICAS - PARRAL N-S 1 | H184: SI | I184: SI
B185: ELECTRICIDAD | D185: 5155-00-0300-IG-EL-PL-XXX | E185: PLANO DE CANALIZACIONES ELÉCTRICAS - PARRAL N-S 2 | H185: SI | I185: SI
B186: ELECTRICIDAD | D186: 5155-00-0400-IG-EL-PL-XXX | E186: PLANO DE CANALIZACIONES ELÉCTRICAS - PARRAL ZONA HOT OIL | H186: SI | I186: SI
B187: ELECTRICIDAD | D187: 5155-00-0500-IG-EL-PL-XXX | E187: PLANO DE CANALIZACIONES ELÉCTRICAS - SENDA NORTE | H187: SI | I187: SI
... B340: INSTRUMENTOS | D340: 5155-00-2200-IG-IN-DC-XXX | E340: DIAGRAMA DE CONEXIONADO DE CAMPO | H340: NO | I340: SI
B341: INSTRUMENTOS | D341: 5155-00-0000-IG-IN-DF-XXX | E341: DIAGRAMA EN BLOQUES COMUNICACIONES | H341: SI | I341: NO | J341: Actualización de documento existente 226-ACAL-100-PL-K-305
B342: INSTRUMENTOS | D342: 5155-00-0000-IG-IN-DL-XXX | E342: DIAGRAMA DE LAZOS | H342: NO | I342: SI
B343: INSTRUMENTOS | D343: 5155-00-2200-IG-IN-DL-XXX | E343: DIAGRAMA DE LAZOS | H343: NO | I343: SI
B344: INSTRUMENTOS | D344: 5155-00-0000-IG-IN-HD-XXX | E344: HOJA DE DATOS VÁLVULAS DE CONTROL Y AUTORREGULADORAS | H344: SI | I344: NO
B345: INSTRUMENTOS | D345: 5155-00-0000-IG-IN-HD-XXX | E345: HOJA DE DATOS VÁLVULAS DE SEGURIDAD | H345: SI | I345: NO
B346: INSTRUMENTOS | D346: 5155-00-0000-IG-IN-HD-XXX | E346: HOJA DE DATOS INSTRUMENTOS F&G (DETECTORES GAS/FUEGO) | H346: SI | I346: NO
B347: INSTRUMENTOS | D347: 5155-00-0000-IG-IN-HD-XXX | E347: HOJA DE DATOS VÁLVULAS BLOWDOWN Y SHUTDOWN | H347: SI | I347: NO
B348: INSTRUMENTOS | D348: 5155-00-0000-IG-IN-HD-XXX | E348: HOJA DE DATOS PLACA ORIFICIO Y ORIFICIO DE RESTRICCIÓN | H348: SI | I348: NO
B349: INSTRUMENTOS | D349: 5155-00-0000-IG-IN-HD-XXX | E349: HOJA DE DATOS TRANSMISOR DE PRESIÓN | H349: SI | I349: NO
B350: INSTRUMENTOS | D350: 5155-00-0000-IG-IN-HD-XXX | E350: HOJA DE DATOS TRANSMISOR DE PRESIÓN DIFERENCIAL | H350: SI | I350: NO
B351: INSTRUMENTOS | D351: 5155-00-0000-IG-IN-HD-XXX | E351: HOJA DE DATOS CAUDALÍMETROS ROTÁMETROS | H351: SI | I351: NO
B352: INSTRUMENTOS | D352: 5155-00-0000-IG-IN-HD-XXX | E352: HOJA DE DATOS TRANSMISOR DE NIVEL DP CELL | H352: SI | I352: NO
B353: INSTRUMENTOS | D353: 5155-00-0000-IG-IN-HD-XXX | E353: HOJA DE DATOS TRANSMISOR DE NIVEL RADAR | H353: SI | I353: NO
... B885: CIVIL | D885: 5155-00-1500-IG-CI-DH-xxx | E885: SLEEPERS SENDA PARRAL 1 - Planos Encofrado y Armadura con DH | H885: SI | I885: SI
B886: PROCESOS | C886: XXX-ACAL-102-MD-Y-XXX | D886: 5155-00-0000-IG-PR-MD-001 | E886: MEMORIA DESCRIPTIVA | H886: NO | I886: NO
B887: PROCESOS | C887: XXX-ACAL-100-PL-Y-312 | D887: 5155-00-0000-IG-PR-PI-001 | E887: P&ID. CPF. SLUG CATCHER ALTA PRESIÓN | H887: SI | I887: SI
B888: PROCESOS | C888: XXX-ACAL-102-PL-Y-302 | D888: 5155-00-0000-IG-PR-PI-003 | E888: P&ID CPF2 INTERCONEXIONES ZONA PROCESOS | H888: SI | I888: SI
B889: PROCESOS | C889: XXX-ACAL-100-PL-Y-314 | D889: 5155-00-0000-IG-PR-PI-004 | E889: P&ID. CPF. MANIFOLD DE ENTRADA | H889: SI | I889: SI
B890: PROCESOS | C890: XXX-ACAL-100-PL-Y-316 | D890: 5155-00-0000-IG-PR-PI-006 | E890: P&ID. CPF. DESARENADOR DE ENTRADA CPF | H890: SI | I890: SI
B891: PROCESOS | C891: XXX-ACAL-102-PL-Y-305 | D891: 5155-00-0000-IG-PR-PI-007 | E891: P&ID. CPF2. DESARENADOR DE ENTRADA | H891: SI | I891: SI
B892: PROCESOS | C892: XXX-ACAL-190-PL-Y-614 | D892: 5155-00-0000-IG-PR-PI-010 | E892: P&ID CPF2 PUENTE DE MEDICIÓN Y SALIDA DE PLANTA (NUEVO) | H892: SI | I892: SI
B893: PROCESOS | C893: XXX-ACAL-300-PL-Y-050 | D893: 5155-00-0000-IG-PR-PI-011 | E893: P&ID CPF SALIDA DE PLANTA - TRAMPAS LANZADORAS | H893: SI | I893: SI
B894: PROCESOS | C894: XXX-ACAL-230-PL-Y-301 | D894: 5155-00-0000-IG-PR-PI-012 | E894: P&ID. CPF ALMACENAMIENTO Y DESPACHO DE CONDENSADO | H894: SI | I894: SI
B895: PROCESOS | C895: XXX-ACAL-231-PL-Y-301 | D895: 5155-00-0000-IG-PR-PI-013 | E895: P&ID. CPF2. ALMACENAMIENTO Y DESPACHO DE CONDENSADO | H895: SI | I895: SI
B896: PROCESOS | C896: XXX-ACAL-243-PL-Y-301 | D896: 5155-00-0000-IG-PR-PI-014 | E896: P&ID. CPF2. SISTEMA DE TRATAMIENTO DE AGUA | H896: SI | I896: SI
B897: PROCESOS | C897: XXX-ACAL-242-PL-Y-302 | D897: 5155-00-0000-IG-PR-PI-015 | E897: P&ID. CPF2. DESPACHO DE AGUA | H897: SI | I897: SI
... B1015: SED | C1015: XXX-ACAL-102-HD-Y-300 | D1015: 5155-00-0000-IG-SD-HD-001 | E1015: HOJA DE DATOS - ELEMENTOS SISTEMA CONTRA INCENDIO | H1015: SI | I1015: NO
B1016: MECANICA | D1016: 5155-00-1500-IG-EM-HD-001 | E1016: HOJA DE DATOS- VBD-10240 - SEPARADOR GAS EPF | H1016: SI | I1016: NO
B1017: MECANICA | D1017: 5155-00-1800-IG-EM-HD-001 | E1017: HOJA DE DATOS- DBM-24310-DESGASIFICADOR PRESURIZADO | H1017: SI | I1017: NO
B1018: MECANICA | D1018: 5155-00-1800-IG-EM-HD-002 | E1018: HOJA DE DATOS- DBM-24320-DESGASIFICADOR ATMOSFÉRICO | H1018: SI | I1018: NO
B1019: MECANICA | D1019: 5155-00-0600-IG-EM-HD-001 | E1019: HOJA DE DATOS- VBE-95120 -KNOCK OUT DRUM | H1019: SI | I1019: NO
B1020: MECANICA | D1020: 5155-00-0800-IG-EM-HD-001 | E1020: HOJA DE DATOS- VBE-91020 -PULMÓN DE AIRE DE INSTRUMENTOS | H1020: SI | I1020: NO
B1021: MECANICA | D1021: 5155-00-1500-IG-EM-HD-002 | E1021: HOJA DE DATOS- VBE-91030 -PULMÓN DE AIRE DE ARRANQUE | H1021: SI | I1021: NO
B1022: MECANICA | D1022: 5155-00-0800-IG-EM-HD-002 | E1022: HOJA DE DATOS- VBE-92010 - PULMÓN DE NITRÓGENO | H1022: SI | I1022: NO
...

Sheet OC Exterior
B3: Legajo Comex | C3: Pedido | D3: Proveedor | E3: Cant. | F3: UM | G3: Monto (USD) | H3: FE origen | I3: Estado | J3: Comentarios | K3: N° BL | L3: Nombre buque | M3: Transbordo | N3: Contenedores
B4: 4591 | C4: 4508882882 | D4: Trustworthy | E4: 35364 | F4: m | G4: 662090.45 | H4: 46129 | I4: Liberada completa | J4: Caños Rev. 0 y 1. Inspección el 27/4 y 28/4. ETA estimada obra 20/8. Forwarder adjudicado. ETD 25/5 y ETA puerto 11/8. 33 contenedores | K4: SZES26050418 | L4: MSC Susanna | N4: 33 | O4: Leo | P4: Cyn
B5: 4590 | C5: 4508889420 | D5: Trustworthy | E5: 5357 | F5: u | G5: 141909.26 | H5: 46132 | I5: Liberada completa | J5: Bridas Rev. 0 y 1. Inspección el 27/4 y 28/4. ETA estimada obra 15/8. ETD 20/5-Arribando solución del paro nacional de prácticos, se espera que ingrese el 6/8 (a confirmar). | K5: SZ26050396 | L5: Ever Fame | N5: 5x20pies | O5: Leo | P5: Cyn
B6: 4589 | C6: 4508890700 | D6: HCI | E6: 276 | F6: u | G6: 26539.03 | H6: 46110 | I6: Entregado completo | J6: Entregado completo | O6: Juli | P6: Cyn
B7: 4593 | C7: 4508890749 | D7: Trustworthy | E7: 7674 | F7: u | G7: 42419.15 | H7: 46135 | I7: Liberada completa | J7: Entregado en Canning | L7: MSC SHUBA B | N7: 1 | O7: Leo | P7: Guille
B8: 4594 | C8: 4508892757 | D8: Trustworthy | E8: 2713 | F8: u | G8: 28140.62 | H8: 46136 | I8: Liberada completa | J8: Accesorios Rev. 0 y 1. ETA estimada obra 20/8. Forwarder adjudicado. ETD 23/5 y ETA puerto 14/8. | L8: Ever Faith | N8: 1x40. 13tn. | O8: Leo | P8: Guille | Q8: EVER FAITH
B9: 4601 | C9: 4508891322 | D9: Suternational | E9: 925 | F9: u | G9: 15434.63 | H9: 46140 | I9: Liberada completa | J9: Accesorios Rev. 0 y 1. ETA estimada obra 25/8. Material liberado, booking para ETD el 8/6 y ETA puerto 18/8. | L9: Kota Elok | N9: 1x40. 15,5tn | O9: Juli | P9: Muzzu
B10: 4601 | C10: 4508893258 | D10: Suternational | E10: 2918 | F10: u | G10: 33828.18 | H10: 46140 | I10: Liberada completa | J10: Accesorios Rev. 0 y 1. ETA estimada obra 25/8. Material liberado, booking para ETD el 8/6 y ETA puerto 18/8. | K10: GZ26050473 | L10: Kota Elok | N10: 1x40. 17,3tn | O10: Juli | P10: Muzzu
B11: 4629 | C11: 4508953544 | D11: Trustworthy | H11: 46213 | I11: Liberada completa | J11: Caños, 193tn - ETA estimada Canning 5/10/26. Pick Up coordinado. ETD 5/8/26 (el 14/8 saldría de Shangai) - ETA 22/9/26 | K11: OSEX2639446 | M11: Sí, feeder a Shangai | N11: 8x40 | O11: Leo | P11: Nicole
B12: 4650 | C12: 4508972604 | D12: Trustworthy | H12: 46242 | I12: En liberación | J12: Juntas, OC modificada. FE en origen. ETA obra 7/11/26. En liberación. | O12: Leo | P12: Guille
B13: 4636 | C13: 4508954248 | D13: Maron Steel | E13: 23618 | F13: u | G13: 32413.38 | H13: 46203 | I13: Liberada completa | J13: Espárragos, maritimo . ETA obra 30/10. Forwarder asignado, se aguarda confirmación de booking. | O13: Leo | P13: Nicole
B14: 4634 | C14: 4508977163 | D14: Elite Piping | H14: 46218 | I14: Liberada por calidad | J14: Bridas - ETA obra 10/10. ETD 28/7 desde Tianjin, de Ningbo sale el 11/8 - ETA 30/9 | O14: Leo | P14: Cyn
B15: 4640 | C15: 4508984427 | D15: FBV | H15: 46305 | I15: En fabricación | J15: Válvulas manuales - LD codificado - ETA estimada OBRA 20/1/27. Planos ACO. AESA inspeccionará junto con FBV a fin de septiembre. Planos comentados por ING, se aguarda re-emisión de parte de FBV. | O15: Juan | P15: Cyn
B16: 4641 | C16: 4508984403 | D16: FBV | H16: 46305 | I16: En fabricación | J16: Válvulas manuales - LD codificado - ETA estimada OBRA 20/1/27. Documentación presentada, en proceso de aprobación. AESA inspeccionará junto con FBV a fin de septiembre. Planos comentados por ING, se aguarda re-emisión de parte de FBV. | O16: Juan | P16: Cyn
B17: 4639 | C17: 4509030990 - Ex 4508984389 | D17: Valvitalia | H17: 46332 | I17: En fabricación | J17: Válvulas manuales - Pendiente subir planos de válvulas - ETA estimada OBRA 20/1/27. Planos aprobados con observaciones, el 5/8 se vuelve a emitir el plano. | O17: Ale | P17: Guille
B18: 4643 | C18: 4508984387 | D18: Grupo Cuñado | H18: 46311 | I18: En fabricación | J18: Válvulas manuales - ETA estimada OBRA 20/1/27. KOM 2/7. Plano ACO. | O18: Ale | P18: Cyn
B19: 4654 | C19: 4509002007 | D19: Trustworthy | H19: 46258 | I19: En fabricación | J19: Accesorios. ETA Canning 24/11/26. Se espera inspección 20/8 | O19: Leo | P19: Guille
B20: 4653 | C20: 4509001668 | D20: Elite Piping | H20: 46254 | I20: En fabricación | J20: Se inspeccionará 20/8. ETA Canning 20/11/26. Inspección 14/8. | O20: Leo | P20: Cyn
B21: 4669 | C21: 4509030959 | D21: Maron Steel | H21: 46254 | I21: En fabricación | J21: ETA Obra 20/11/26. Se inspeccionará 20/8. | O21: Leo | P21: Cyn
B22: 4677 | C22: 4509033161 | D22: Trustworthy | H22: 31/8 10/9 20/9 | I22: En fabricación | J22: Caños, bridas y accesorios. ETA Canning 20/12/26. Se solicitarán packings anticipados para definir estrategia de contratación de forwarder. | O22: Leo | P22: Cyn
B23: 4688 | C23: 4509012742 | D23: FBV | H23: 46357 | I23: OC enviada | J23: Válvulas ETA obra 15/03/26 | O23: Juan | P23: Cyn
B24: 4687 | C24: 4509031935 | D24: Valvitalia | H24: 46382 | I24: OC enviada | J24: Válvulas ETA obra 15/03/26 | O24: Ale | P24: Guille

Sheet RI y OC x mes
A1: RI emitidas por mes
B2: 2025 | C2: 46023 | D2: 46054 | E2: 46082 | F2: 46113 | G2: 46143 | H2: 46174 | I2: 46204 | J2: 46235 | K2: 46266 | L2: 46296 | M2: 46327 | N2: 46357 | O2: 46388 | P2: Total
A3: ELECTRICIDAD | C3: 5 | F3: 1 | G3: 4 | H3: 5 | J3: 2 | M3: 1 | P3: =+SUM(B3:N3) -> 18
A4: INSTRUMENTACIÓN | D4: 2 | E4: 15 | F4: 12 | G4: 16 | I4: 2 | L4: 3 | N4: 1 | P4: =+SUM(B4:N4) -> 51
A5: MECÁNICA | B5: 1 | C5: 3 | D5: 2 | E5: 2 | F5: 4 | G5: 2 | H5: 3 | I5: 1 | P5: =+SUM(B5:N5) -> 18
A8: RI adjudicadas por mes
B9: 2025 | C9: 46023 | D9: 46054 | E9: 46082 | F9: 46113 | G9: 46143 | H9: 46174 | I9: 46204 | J9: 46235 | K9: 46266 | L9: 46296 | M9: 46327 | N9: 46357 | O9: 46388 | P9: Total
A10: ELECTRICIDAD | D10: 1 | E10: 1 | F10: 3 | I10: 1 | J10: 4 | K10: 5 | L10: 2 | O10: 1 | P10: =+SUM(B10:O10) -> 18
A11: INSTRUMENTACIÓN | H11: 11 | I11: 15 | J11: 18 | K11: 1 | L11: 2 | O11: 4 | P11: =+SUM(B11:O11) -> 51
A12: MECÁNICA | D12: 1 | G12: 3 | H12: 3 | I12: 1 | J12: 4 | K12: 2 | L12: 4 | P12: =+SUM(B12:N12) -> 18
A14: Recursos compras por mes
B15: 2025 | C15: 46023 | D15: 46054 | E15: 46082 | F15: 46113 | G15: 46143 | H15: 46174 | I15: 46204 | J15: 46235 | K15: 46266 | L15: 46296 | M15: 46327 | N15: 46357 | O15: 46388 | P15: 46419 | Q15: 46447 | R15: 46478 | S15: 46508 | T15: 46539 | U15: 46569 | V15: 46600 | W15: 46631 | X15: 46661 | Y15: 46692 | Z15: 46722 | AA15: 46753 | AB15: Total
A16: Jefe de compras | B16: 1 | C16: 1 | D16: 1 | E16: 1 | F16: 1 | G16: 1 | H16: 1 | I16: 1 | J16: 1 | K16: 1 | L16: 1 | M16: 1 | N16: 1 | O16: 1 | P16: 1 | Q16: 1 | R16: 1 | S16: 1 | T16: 1 | U16: 0.5 | V16: 0.5 | W16: 0.5 | X16: 0.5 | Y16: 0.5 | Z16: 0.5 | AA16: 0.5 | AB16: =SUM(B16:AA16) -> 22.5
A17: Comprador | B17: 3 | C17: 3 | D17: 3 | E17: 5 | F17: 5 | G17: 5 | H17: 5 | I17: 5 | J17: 5 | K17: 4 | L17: 3 | M17: 2 | N17: 2 | O17: 2 | P17: 2 | Q17: 2 | R17: 2 | S17: 2 | T17: 1 | U17: 1 | V17: 1 | W17: 1 | X17: 1 | Y17: 1 | Z17: 1 | AA17: 1 | AB17: =SUM(B17:AA17) -> 68
AB18: =SUM(AB16:AB17) -> 90.5
A19: Las 3 RI a adjudicar en abril-26 corresponden a la provisión completa de ABB. Estamos intentando colocar la OC en marzo, pero difícilmente se llegue.
A20: En junio-26, dos de las Ris de instrumentación corresponden a equipos
A21: Para referencia, LAS tiene 40 RIs de equipos mecánicas y más de 100 equipos. Lo asociado a material bulk estimo que tendrá una carga de trabajo similar (quizás un poco menor al tratarse LCII de una única planta y pueden haber menos revisiones).
A23: Cantidad equipos de envergadura LCII
A24: Electricidad | B24: 3
A25: Instrumentación | B25: 2
A26: Mecánicos | B26: 42 | C26: (no incluye skids de químicos)
A28: Fecha de necesidad de acuerdo a cronogra
A29: Instrumentos | B29: mayoritariamente abril-27 y algunos mayo-junio-27
A30: Electricidad | B30: ABB en mayo-27, resto de materiales hasta mayo-27 (excepto ajustes finales de cables o materiales menores que pueden llegar hasta fin de 2027 por nuevas revisiones de Ris)
A31: Mecánica | B31: Entre mayo y junio-27

Sheet La Calera II - crono Rev. 0
A1: SUMINISTROS LA CALERA II | D1: TAG | E1: RI | J1: Emisión y liberación de Solped | R1: Recepción de ofertas | Y1: AT REV A | AC1: AT REV 0 | AJ1: Emisión OC | AV1: Fabricación | BC1: Transporte Internacional (incluida gestión comex+transporte) | BJ1: Nacionalización (tiempo Comex para nacionalizar) | BQ1: Transporte Local | BX1: Necesidad Construcciones | BY1: Impacto Costrucciones | CB1: -30 | CC1: 0
CB2: 1 | CC2: 90
A3: ESP | B3: Requisición N° | C3: DESCRIPCION | D3: N° | E3: Necesidad RI/Pliego | F3: Forecast | G3: Real | H3: Desvío | J3: Inicio Prog | K3: Final Prog | L3: Duración | M3: Forecast | N3: Real | O3: Desvío Acum | P3: N° Cesta/Solped | R3: Inicio Prog | S3: Final Prog | T3: Duración | U3: Forecast | V3: Real | W3: Desvío Acum | Y3: Final Prog | Z3: Real | AA3: Desvío Acum | AC3: Inicio Prog | AD3: Final Prog | AE3: Duración | AF3: Forecast | AG3: Real | AH3: Desvío Acum | AJ3: Inicio Prog | AK3: Final Prog | AL3: Duración | AM3: Forecast | AN3: Real | AO3: Desvío Acum | AP3: N° OC | AQ3: Pos | AR3: Proveedor | AS3: Fecha de Entrega | AT3: Lugar de entrega | AV3: Inicio Prog | AW3: Final Prog | AX3: Duración | AY3: Forecast | AZ3: Real | BA3: Desvío Acum | BC3: Inicio Prog | BD3: Final Prog | BE3: Duración | BF3: Forecast | BG3: Real | BH3: Desvío Acum | BJ3: Inicio Prog | BK3: Final Prog | BL3: Duración | BM3: Forecast | BN3: Real | BO3: Desvío Acum | BQ3: Inicio Prog | BR3: Final Prog | BS3: Duración | BT3: Forecast | BU3: Real | BV3: Desvío Acum | BW3: Tarea de cronograma para referencia | BX3: Fecha de necesidad de construcciones | BY3: Impacto | CA3: Comentarios
A4: SERVICIOS | C4: CONTRATACIÓN OBRA CIVIL | D4: - | E4: =+J4-1 -> 45841 | F4: 45883 | H4: =+F4-E4 -> 42 | J4: =+K4-L4 -> 45842 | K4: =+R4-1 -> 45849 | L4: 7 | M4: =+F4+L4 -> 45890 | O4: =+M4-K4 -> 41 | R4: =+S4-T4 -> 45850 | S4: =+AC4-1 -> 45880 | T4: 30 | U4: =+M4+T4 -> 45920 | W4: =+U4-S4 -> 40 | Y4: - | Z4: - | AA4: - | AC4: =+AD4-AE4 -> 45881 | AD4: =+AJ4-1 -> 45911 | AE4: 30 | AF4: =+IF(V4=0,U4,V4)+AE4 -> 45950 | AH4: =+AF4-AD4 -> 39 | AJ4: =+AK4-AL4 -> 45912 | AK4: =+AV4-1 -> 45952 | AL4: 40 | AM4: =+IF(AG4=0,AF4,AG4)+AL4 -> 45990 | AO4: =+AM4-AK4 -> 38 | AV4: =+AW4-AX4 -> 45953 | AW4: =+BC4-1 -> 45953 | AY4: =+IF(AN4=0,AM4,AN4)+AX4 -> 45990 | BA4: =+AY4-AW4 -> 37 | BC4: =+BD4-BE4 -> 45954 | BD4: =+BJ4 -> 45954 | BE4: 0 | BF4: =+IF(AZ4=0,AY4,AZ4)+BE4 -> 45990 | BH4: =+BF4-BD4 -> 36 | BJ4: =+BK4-BL4 -> 45954 | BK4: =+BQ4 -> 45954 | BL4: 0 | BM4: =+IF(BG4=0,BF4,BG4)+BL4 -> 45990 | BO4: =+BM4-BK4 -> 36 | BQ4: =+BR4-BS4 -> 45954 | BR4: =+BX4 -> 45954 | BT4: =+IF(BN4=0,BM4,BN4)+BS4 -> 45990 | BV4: =+BT4-BR4 -> 36 | BW4: GCC1000 | BX4: 45954 | BY4: =+BT4-BX4 -> 36 | CA4: Fecha de necesidad de contratación de Obra Civil
A5: SERVICIOS | C5: CONTRATACIÓN MOVIMIENTO DE SUELOS | D5: - | E5: =+J5-1 -> 45866 | F5: 45883 | H5: =+F5-E5 -> 17 | J5: =+K5-L5 -> 45867 | K5: =+R5-1 -> 45874 | L5: 7 | M5: =+F5+L5 -> 45890 | O5: =+M5-K5 -> 16 | R5: =+S5-T5 -> 45875 | S5: =+AC5-1 -> 45905 | T5: 30 | U5: =+M5+T5 -> 45920 | W5: =+U5-S5 -> 15 | Y5: - | Z5: - | AA5: - | AC5: =+AD5-AE5 -> 45906 | AD5: =+AJ5-1 -> 45936 | AE5: 30 | AF5: =+IF(V5=0,U5,V5)+AE5 -> 45950 | AH5: =+AF5-AD5 -> 14 | AJ5: =+AK5-AL5 -> 45937 | AK5: =+AV5-1 -> 45952 | AL5: 15 | AM5: =+IF(AG5=0,AF5,AG5)+AL5 -> 45965 | AO5: =+AM5-AK5 -> 13 | AV5: =+AW5-AX5 -> 45953 | AW5: =+BC5-1 -> 45953 | AY5: =+IF(AN5=0,AM5,AN5)+AX5 -> 45965 | BA5: =+AY5-AW5 -> 12 | BC5: =+BD5-BE5 -> 45954 | BD5: =+BJ5 -> 45954 | BE5: 0 | BF5: =+IF(AZ5=0,AY5,AZ5)+BE5 -> 45965 | BH5: =+BF5-BD5 -> 11 | BJ5: =+BK5-BL5 -> 45954 | BK5: =+BQ5 -> 45954 | BL5: 0 | BM5: =+IF(BG5=0,BF5,BG5)+BL5 -> 45965 | BO5: =+BM5-BK5 -> 11 | BQ5: =+BR5-BS5 -> 45954 | BR5: =+BX5 -> 45954 | BT5: =+IF(BN5=0,BM5,BN5)+BS5 -> 45965 | BV5: =+BT5-BR5 -> 11 | BW5: GCC1000 | BX5: 45954 | BY5: =+BT5-BX5 -> 11 | CA5: Fecha de necesidad de contratación de Obra Civil
A6: SERVICIOS | C6: CONTRATACIÓN TRANSPORTES | D6: - | E6: =+J6-1 -> 45841 | F6: 45890 | H6: =+F6-E6 -> 49 | J6: =+K6-L6 -> 45842 | K6: =+R6-1 -> 45849 | L6: 7 | M6: =+F6+L6 -> 45897 | O6: =+M6-K6 -> 48 | R6: =+S6-T6 -> 45850 | S6: =+AC6-1 -> 45880 | T6: 30 | U6: =+M6+T6 -> 45927 | W6: =+U6-S6 -> 47 | Y6: - | Z6: - | AA6: - | AC6: =+AD6-AE6 -> 45881 | AD6: =+AJ6-1 -> 45911 | AE6: 30 | AF6: =+IF(V6=0,U6,V6)+AE6 -> 45957 | AH6: =+AF6-AD6 -> 46 | AJ6: =+AK6-AL6 -> 45912 | AK6: =+AV6-1 -> 45952 | AL6: 40 | AM6: =+IF(AG6=0,AF6,AG6)+AL6 -> 45997 | AO6: =+AM6-AK6 -> 45 | AV6: =+AW6-AX6 -> 45953 | AW6: =+BC6-1 -> 45953 | AY6: =+IF(AN6=0,AM6,AN6)+AX6 -> 45997 | BA6: =+AY6-AW6 -> 44 | BC6: =+BD6-BE6 -> 45954 | BD6: =+BJ6 -> 45954 | BE6: 0 | BF6: =+IF(AZ6=0,AY6,AZ6)+BE6 -> 45997 | BH6: =+BF6-BD6 -> 43 | BJ6: =+BK6-BL6 -> 45954 | BK6: =+BQ6 -> 45954 | BL6: 0 | BM6: =+IF(BG6=0,BF6,BG6)+BL6 -> 45997 | BO6: =+BM6-BK6 -> 43 | BQ6: =+BR6-BS6 -> 45954 | BR6: =+BX6 -> 45954 | BT6: =+IF(BN6=0,BM6,BN6)+BS6 -> 45997 | BV6: =+BT6-BR6 -> 43 | BW6: GCC1000 | BX6: 45954 | BY6: =+BT6-BX6 -> 43 | CA6: Fecha de necesidad de contratación de Obra Civil
A7: SERVICIOS | C7: CONTRATACIÓN CAMPAMENTO | D7: - | E7: =+J7-1 -> 45841 | F7: 45889 | H7: =+F7-E7 -> 48 | J7: =+K7-L7 -> 45842 | K7: =+R7-1 -> 45849 | L7: 7 | M7: =+F7+L7 -> 45896 | O7: =+M7-K7 -> 47 | R7: =+S7-T7 -> 45850 | S7: =+AC7-1 -> 45880 | T7: 30 | U7: =+M7+T7 -> 45926 | W7: =+U7-S7 -> 46 | Y7: - | Z7: - | AA7: - | AC7: =+AD7-AE7 -> 45881 | AD7: =+AJ7-1 -> 45911 | AE7: 30 | AF7: =+IF(V7=0,U7,V7)+AE7 -> 45956 | AH7: =+AF7-AD7 -> 45 | AJ7: =+AK7-AL7 -> 45912 | AK7: =+AV7-1 -> 45952 | AL7: 40 | AM7: =+IF(AG7=0,AF7,AG7)+AL7 -> 45996 | AO7: =+AM7-AK7 -> 44 | AV7: =+AW7-AX7 -> 45953 | AW7: =+BC7-1 -> 45953 | AY7: =+IF(AN7=0,AM7,AN7)+AX7 -> 45996 | BA7: =+AY7-AW7 -> 43 | BC7: =+BD7-BE7 -> 45954 | BD7: =+BJ7 -> 45954 | BE7: 0 | BF7: =+IF(AZ7=0,AY7,AZ7)+BE7 -> 45996 | BH7: =+BF7-BD7 -> 42 | BJ7: =+BK7-BL7 -> 45954 | BK7: =+BQ7 -> 45954 | BL7: 0 | BM7: =+IF(BG7=0,BF7,BG7)+BL7 -> 45996 | BO7: =+BM7-BK7 -> 42 | BQ7: =+BR7-BS7 -> 45954 | BR7: =+BX7 -> 45954 | BT7: =+IF(BN7=0,BM7,BN7)+BS7 -> 45996 | BV7: =+BT7-BR7 -> 42 | BW7: GCC1000 | BX7: 45954 | BY7: =+BT7-BX7 -> 42 | CA7: Fecha de necesidad de contratación de Obra Civil
A8: SERVICIOS | C8: CONTRATACIÓN VIANDAS | D8: - | E8: =+J8-1 -> 45841 | F8: 45890 | H8: =+F8-E8 -> 49 | J8: =+K8-L8 -> 45842 | K8: =+R8-1 -> 45849 | L8: 7 | M8: =+F8+L8 -> 45897 | O8: =+M8-K8 -> 48 | R8: =+S8-T8 -> 45850 | S8: =+AC8-1 -> 45880 | T8: 30 | U8: =+M8+T8 -> 45927 | W8: =+U8-S8 -> 47 | Y8: - | Z8: - | AA8: - | AC8: =+AD8-AE8 -> 45881 | AD8: =+AJ8-1 -> 45911 | AE8: 30 | AF8: =+IF(V8=0,U8,V8)+AE8 -> 45957 | AH8: =+AF8-AD8 -> 46 | AJ8: =+AK8-AL8 -> 45912 | AK8: =+AV8-1 -> 45952 | AL8: 40 | AM8: =+IF(AG8=0,AF8,AG8)+AL8 -> 45997 | AO8: =+AM8-AK8 -> 45 | AV8: =+AW8-AX8 -> 45953 | AW8: =+BC8-1 -> 45953 | AY8: =+IF(AN8=0,AM8,AN8)+AX8 -> 45997 | BA8: =+AY8-AW8 -> 44 | BC8: =+BD8-BE8 -> 45954 | BD8: =+BJ8 -> 45954 | BE8: 0 | BF8: =+IF(AZ8=0,AY8,AZ8)+BE8 -> 45997 | BH8: =+BF8-BD8 -> 43 | BJ8: =+BK8-BL8 -> 45954 | BK8: =+BQ8 -> 45954 | BL8: 0 | BM8: =+IF(BG8=0,BF8,BG8)+BL8 -> 45997 | BO8: =+BM8-BK8 -> 43 | BQ8: =+BR8-BS8 -> 45954 | BR8: =+BX8 -> 45954 | BT8: =+IF(BN8=0,BM8,BN8)+BS8 -> 45997 | BV8: =+BT8-BR8 -> 43 | BW8: GCC1000 | BX8: 45954 | BY8: =+BT8-BX8 -> 43 | CA8: Fecha de necesidad de contratación de Obra Civil
A9: SERVICIOS | C9: CONTRATACIÓN PREFABRICADOS | D9: - | E9: =+J9-1 -> 45894 | F9: 45899 | H9: =+F9-E9 -> 5 | J9: =+K9-L9 -> 45895 | K9: =+R9-1 -> 45902 | L9: 7 | M9: =+F9+L9 -> 45906 | O9: =+M9-K9 -> 4 | R9: =+S9-T9 -> 45903 | S9: =+AC9-1 -> 45933 | T9: 30 | U9: =+M9+T9 -> 45936 | W9: =+U9-S9 -> 3 | Y9: - | Z9: - | AA9: - | AC9: =+AD9-AE9 -> 45934 | AD9: =+AJ9-1 -> 45964 | AE9: 30 | AF9: =+IF(V9=0,U9,V9)+AE9 -> 45966 | AH9: =+AF9-AD9 -> 2 | AJ9: =+AK9-AL9 -> 45965 | AK9: =+AV9-1 -> 46005 | AL9: 40 | AM9: =+IF(AG9=0,AF9,AG9)+AL9 -> 46006 | AO9: =+AM9-AK9 -> 1 | AV9: =+AW9-AX9 -> 46006 | AW9: =+BC9-1 -> 46036 | AX9: 30 | AY9: =+IF(AN9=0,AM9,AN9)+AX9 -> 46036 | BA9: =+AY9-AW9 -> 0 | BC9: =+BD9-BE9 -> 46037 | BD9: =+BJ9 -> 46037 | BE9: 0 | BF9: =+IF(AZ9=0,AY9,AZ9)+BE9 -> 46036 | BH9: =+BF9-BD9 -> -1 | BJ9: =+BK9-BL9 -> 46037 | BK9: =+BQ9 -> 46037 | BL9: 0 | BM9: =+IF(BG9=0,BF9,BG9)+BL9 -> 46036 | BO9: =+BM9-BK9 -> -1 | BQ9: =+BR9-BS9 -> 46037 | BR9: =+BX9 -> 46037 | BT9: =+IF(BN9=0,BM9,BN9)+BS9 -> 46036 | BV9: =+BT9-BR9 -> -1 | BW9: FDP1040 | BX9: 46037 | BY9: =+BT9-BX9 -> -1 | CA9: Fecha de necesidad de inicio de prefa
A10: SERVICIOS | C10: CONTRATACIÓN PINTURA | D10: - | E10: =+J10-1 -> 45919 | F10: 45899 | H10: =+F10-E10 -> -20 | J10: =+K10-L10 -> 45920 | K10: =+R10-1 -> 45927 | L10: 7 | M10: =+F10+L10 -> 45906 | O10: =+M10-K10 -> -21 | R10: =+S10-T10 -> 45928 | S10: =+AC10-1 -> 45958 | T10: 30 | U10: =+M10+T10 -> 45936 | W10: =+U10-S10 -> -22 | Y10: - | Z10: - | AA10: - | AC10: =+AD10-AE10 -> 45959 | AD10: =+AJ10-1 -> 45989 | AE10: 30 | AF10: =+IF(V10=0,U10,V10)+AE10 -> 45966 | AH10: =+AF10-AD10 -> -23 | AJ10: =+AK10-AL10 -> 45990 | AK10: =+AV10-1 -> 46005 | AL10: 15 | AM10: =+IF(AG10=0,AF10,AG10)+AL10 -> 45981 | AO10: =+AM10-AK10 -> -24 | AV10: =+AW10-AX10 -> 46006 | AW10: =+BC10-1 -> 46036 | AX10: 30 | AY10: =+IF(AN10=0,AM10,AN10)+AX10 -> 46011 | BA10: =+AY10-AW10 -> -25 | BC10: =+BD10-BE10 -> 46037 | BD10: =+BJ10 -> 46037 | BE10: 0 | BF10: =+IF(AZ10=0,AY10,AZ10)+BE10 -> 46011 | BH10: =+BF10-BD10 -> -26 | BJ10: =+BK10-BL10 -> 46037 | BK10: =+BQ10 -> 46037 | BL10: 0 | BM10: =+IF(BG10=0,BF10,BG10)+BL10 -> 46011 | BO10: =+BM10-BK10 -> -26 | BQ10: =+BR10-BS10 -> 46037 | BR10: =+BX10 -> 46037 | BT10: =+IF(BN10=0,BM10,BN10)+BS10 -> 46011 | BV10: =+BT10-BR10 -> -26 | BW10: FDP1040 | BX10: 46037 | BY10: =+BT10-BX10 -> -26 | CA10: Fecha de necesidad de inicio de prefa
A11: SERVICIOS | C11: CONTRATACIÓN ESTRUCTURA LIVIANA-SOPORTES | D11: - | E11: =+J11-1 -> 45971 | H11: =+F11-E11 -> -45971 | J11: =+K11-L11 -> 45972 | K11: =+R11-1 -> 45979 | L11: 7 | M11: =+F11+L11 -> 7 | O11: =+M11-K11 -> -45972 | R11: =+S11-T11 -> 45980 | S11: =+AC11-1 -> 46010 | T11: 30 | U11: =+M11+T11 -> 37 | W11: =+U11-S11 -> -45973 | Y11: - | Z11: - | AA11: - | AC11: =+AD11-AE11 -> 46011 | AD11: =+AJ11-1 -> 46041 | AE11: 30 | AF11: =+IF(V11=0,U11,V11)+AE11 -> 67 | AH11: =+AF11-AD11 -> -45974 | AJ11: =+AK11-AL11 -> 46042 | AK11: =+AV11-1 -> 46057 | AL11: 15 | AM11: =+IF(AG11=0,AF11,AG11)+AL11 -> 82 | AO11: =+AM11-AK11 -> -45975 | AV11: =+AW11-AX11 -> 46058 | AW11: =+BC11-1 -> 46058 | AY11: =+IF(AN11=0,AM11,AN11)+AX11 -> 82 | BA11: =+AY11-AW11 -> -45976 | BC11: =+BD11-BE11 -> 46059 | BD11: =+BJ11 -> 46059 | BE11: 0 | BF11: =+IF(AZ11=0,AY11,AZ11)+BE11 -> 82 | BH11: =+BF11-BD11 -> -45977 | BJ11: =+BK11-BL11 -> 46059 | BK11: =+BQ11 -> 46059 | BL11: 0 | BM11: =+IF(BG11=0,BF11,BG11)+BL11 -> 82 | BO11: =+BM11-BK11 -> -45977 | BQ11: =+BR11-BS11 -> 46059 | BR11: =+BX11 -> 46059 | BT11: =+IF(BN11=0,BM11,BN11)+BS11 -> 82 | BV11: =+BT11-BR11 -> -45977 | BW11: GCS1000 | BX11: 46059 | BY11: =+BT11-BX11 -> -45977 | CA11: Contratación de EEMM de acuerdo a Crono
A12: SERVICIOS | C12: CONTRATACIÓN AISLACIÓN (a confirmar) | D12: - | E12: =+J12-1 -> 46076 | H12: =+F12-E12 -> -46076 | J12: =+K12-L12 -> 46077 | K12: =+R12-1 -> 46084 | L12: 7 | M12: =+F12+L12 -> 7 | O12: =+M12-K12 -> -46077 | R12: =+S12-T12 -> 46085 | S12: =+AC12-1 -> 46115 | T12: 30 | U12: =+M12+T12 -> 37 | W12: =+U12-S12 -> -46078 | Y12: - | Z12: - | AA12: - | AC12: =+AD12-AE12 -> 46116 | AD12: =+AJ12-1 -> 46146 | AE12: 30 | AF12: =+IF(V12=0,U12,V12)+AE12 -> 67 | AH12: =+AF12-AD12 -> -46079 | AJ12: =+AK12-AL12 -> 46147 | AK12: =+AV12-1 -> 46162 | AL12: 15 | AM12: =+IF(AG12=0,AF12,AG12)+AL12 -> 82 | AO12: =+AM12-AK12 -> -46080 | AV12: =+AW12-AX12 -> 46163 | AW12: =+BC12-1 -> 46163 | AY12: =+IF(AN12=0,AM12,AN12)+AX12 -> 82 | BA12: =+AY12-AW12 -> -46081 | BC12: =+BD12-BE12 -> 46164 | BD12: =+BJ12 -> 46164 | BE12: 0 | BF12: =+IF(AZ12=0,AY12,AZ12)+BE12 -> 82 | BH12: =+BF12-BD12 -> -46082 | BJ12: =+BK12-BL12 -> 46164 | BK12: =+BQ12 -> 46164 | BL12: 0 | BM12: =+IF(BG12=0,BF12,BG12)+BL12 -> 82 | BO12: =+BM12-BK12 -> -46082 | BQ12: =+BR12-BS12 -> 46164 | BR12: =+BX12 -> 46164 | BT12: =+IF(BN12=0,BM12,BN12)+BS12 -> 82 | BV12: =+BT12-BR12 -> -46082 | BW12: FDP1040 | BX12: 46164 | BY12: =+BT12-BX12 -> -46082
A13: SERVICIOS | C13: CONTRATACIÓN ANDAMIOS (a confirmar) | D13: - | E13: =+J13-1 -> 46051 | H13: =+F13-E13 -> -46051 | J13: =+K13-L13 -> 46052 | K13: =+R13-1 -> 46059 | L13: 7 | M13: =+F13+L13 -> 7 | O13: =+M13-K13 -> -46052 | R13: =+S13-T13 -> 46060 | S13: =+AC13-1 -> 46090 | T13: 30 | U13: =+M13+T13 -> 37 | W13: =+U13-S13 -> -46053 | Y13: - | Z13: - | AA13: - | AC13: =+AD13-AE13 -> 46091 | AD13: =+AJ13-1 -> 46121 | AE13: 30 | AF13: =+IF(V13=0,U13,V13)+AE13 -> 67 | AH13: =+AF13-AD13 -> -46054 | AJ13: =+AK13-AL13 -> 46122 | AK13: =+AV13-1 -> 46162 | AL13: 40 | AM13: =+IF(AG13=0,AF13,AG13)+AL13 -> 107 | AO13: =+AM13-AK13 -> -46055 | AV13: =+AW13-AX13 -> 46163 | AW13: =+BC13-1 -> 46163 | AY13: =+IF(AN13=0,AM13,AN13)+AX13 -> 107 | BA13: =+AY13-AW13 -> -46056 | BC13: =+BD13-BE13 -> 46164 | BD13: =+BJ13 -> 46164 | BE13: 0 | BF13: =+IF(AZ13=0,AY13,AZ13)+BE13 -> 107 | BH13: =+BF13-BD13 -> -46057 | BJ13: =+BK13-BL13 -> 46164 | BK13: =+BQ13 -> 46164 | BL13: 0 | BM13: =+IF(BG13=0,BF13,BG13)+BL13 -> 107 | BO13: =+BM13-BK13 -> -46057 | BQ13: =+BR13-BS13 -> 46164 | BR13: =+BX13 -> 46164 | BT13: =+IF(BN13=0,BM13,BN13)+BS13 -> 107 | BV13: =+BT13-BR13 -> -46057 | BW13: FDP1040 | BX13: 46164 | BY13: =+BT13-BX13 -> -46057
A14: SERVICIOS | C14: CONTRATACIÓN MANO DE OBRA ESPECIALIZADA | D14: - | E14: =+J14-1 -> 46051 | H14: =+F14-E14 -> -46051 | J14: =+K14-L14 -> 46052 | K14: =+R14-1 -> 46059 | L14: 7 | M14: =+F14+L14 -> 7 | O14: =+M14-K14 -> -46052 | R14: =+S14-T14 -> 46060 | S14: =+AC14-1 -> 46090 | T14: 30 | U14: =+M14+T14 -> 37 | W14: =+U14-S14 -> -46053 | Y14: - | Z14: - | AA14: - | AC14: =+AD14-AE14 -> 46091 | AD14: =+AJ14-1 -> 46121 | AE14: 30 | AF14: =+IF(V14=0,U14,V14)+AE14 -> 67 | AH14: =+AF14-AD14 -> -46054 | AJ14: =+AK14-AL14 -> 46122 | AK14: =+AV14-1 -> 46162 | AL14: 40 | AM14: =+IF(AG14=0,AF14,AG14)+AL14 -> 107 | AO14: =+AM14-AK14 -> -46055 | AV14: =+AW14-AX14 -> 46163 | AW14: =+BC14-1 -> 46163 | AY14: =+IF(AN14=0,AM14,AN14)+AX14 -> 107 | BA14: =+AY14-AW14 -> -46056 | BC14: =+BD14-BE14 -> 46164 | BD14: =+BJ14 -> 46164 | BE14: 0 | BF14: =+IF(AZ14=0,AY14,AZ14)+BE14 -> 107 | BH14: =+BF14-BD14 -> -46057 | BJ14: =+BK14-BL14 -> 46164 | BK14: =+BQ14 -> 46164 | BL14: 0 | BM14: =+IF(BG14=0,BF14,BG14)+BL14 -> 107 | BO14: =+BM14-BK14 -> -46057 | BQ14: =+BR14-BS14 -> 46164 | BR14: =+BX14 -> 46164 | BT14: =+IF(BN14=0,BM14,BN14)+BS14 -> 107 | BV14: =+BT14-BR14 -> -46057 | BW14: FDP1040 | BX14: 46164 | BY14: =+BT14-BX14 -> -46057
A15: ELECTRICIDAD | B15: 5155-00-2000-IG-EL-RI-XXX | C15: RI-REQUISICIÓN DE INGENIERÍA - AMPLIACIÓN ANTENA EXISTENTE | D15: - | E15: =+J15-1 -> 46158 | F15: 46000 | H15: =+F15-E15 -> -158 | J15: =+K15-L15 -> 46159 | K15: =+R15-1 -> 46166 | L15: 7 | M15: =+F15+L15 -> 46007 | O15: =+M15-K15 -> -159 | R15: =+S15-T15 -> 46167 | S15: =+AC15-1 -> 46197 | T15: 30 | U15: =+M15+T15 -> 46037 | W15: =+U15-S15 -> -160 | Y15: - | Z15: - | AA15: - | AC15: =+AD15-AE15 -> 46198 | AD15: =+AJ15-1 -> 46243 | AE15: 45 | AF15: =+IF(V15=0,U15,V15)+AE15 -> 46082 | AH15: =+AF15-AD15 -> -161 | AJ15: =+AK15-AL15 -> 46244 | AK15: =+AV15-1 -> 46264 | AL15: 20 | AM15: =+IF(AG15=0,AF15,AG15)+AL15 -> 46102 | AO15: =+AM15-AK15 -> -162 | AV15: =+AW15-AX15 -> 46265 | AW15: =+BC15-1 -> 46465 | AX15: 200 | AY15: =+IF(AN15=0,AM15,AN15)+AX15 -> 46302 | BA15: =+AY15-AW15 -> -163 | BC15: =+BD15-BE15 -> 46466 | BD15: =+BJ15 -> 46466 | BE15: 0 | BF15: =+IF(AZ15=0,AY15,AZ15)+BE15 -> 46302 | BH15: =+BF15-BD15 -> -164 | BJ15: =+BK15-BL15 -> 46466 | BK15: =+BQ15 -> 46466 | BL15: 0 | BM15: =+IF(BG15=0,BF15,BG15)+BL15 -> 46302 | BO15: =+BM15-BK15 -> -164 | BQ15: =+BR15-BS15 -> 46466 | BR15: =+BX15 -> 46473 | BS15: 7 | BT15: =+IF(BN15=0,BM15,BN15)+BS15 -> 46309 | BV15: =+BT15-BR15 -> -164 | BW15: FDE1140 | BX15: 46473 | BY15: =+BT15-BX15 -> -164 | CA15: FN entrega de trafos
A16: ELECTRICIDAD | B16: 5155-00-2000-IG-EL-RI-XXX | C16: RI-REQUISICIÓN DE INGENIERÍA - TRANSFORMADORES EN ACEITE | E16: =+J16-1 -> 46158 | F16: 46000 | H16: =+F16-E16 -> -158 | J16: =+K16-L16 -> 46159 | K16: =+R16-1 -> 46166 | L16: 7 | M16: =+F16+L16 -> 46007 | O16: =+M16-K16 -> -159 | R16: =+S16-T16 -> 46167 | S16: =+AC16-1 -> 46197 | T16: 30 | U16: =+M16+T16 -> 46037 | W16: =+U16-S16 -> -160 | AC16: =+AD16-AE16 -> 46198 | AD16: =+AJ16-1 -> 46243 | AE16: 45 | AF16: =+IF(V16=0,U16,V16)+AE16 -> 46082 | AH16: =+AF16-AD16 -> -161 | AJ16: =+AK16-AL16 -> 46244 | AK16: =+AV16-1 -> 46264 | AL16: 20 | AM16: =+IF(AG16=0,AF16,AG16)+AL16 -> 46102 | AO16: =+AM16-AK16 -> -162 | AV16: =+AW16-AX16 -> 46265 | AW16: =+BC16-1 -> 46465 | AX16: 200 | AY16: =+IF(AN16=0,AM16,AN16)+AX16 -> 46302 | BA16: =+AY16-AW16 -> -163 | BC16: =+BD16-BE16 -> 46466 | BD16: =+BJ16 -> 46466 | BE16: 0 | BF16: =+IF(AZ16=0,AY16,AZ16)+BE16 -> 46302 | BH16: =+BF16-BD16 -> -164 | BJ16: =+BK16-BL16 -> 46466 | BK16: =+BQ16 -> 46466 | BL16: 0 | BM16: =+IF(BG16=0,BF16,BG16)+BL16 -> 46302 | BO16: =+BM16-BK16 -> -164 | BQ16: =+BR16-BS16 -> 46466 | BR16: =+BX16 -> 46473 | BS16: 7 | BT16: =+IF(BN16=0,BM16,BN16)+BS16 -> 46309 | BV16: =+BT16-BR16 -> -164 | BW16: FDE1140 | BX16: 46473 | BY16: =+BT16-BX16 -> -164 | CA16: FN entrega de trafos
A17: ELECTRICIDAD | B17: 5155-00-2300-IG-EL-RI-XXX | C17: RI-REQUISICIÓN DE INGENIERÍA - TRANSFORMADORES SECOS | E17: =+J17-1 -> 46158 | F17: 46059 | H17: =+F17-E17 -> -99 | J17: =+K17-L17 -> 46159 | K17: =+R17-1 -> 46166 | L17: 7 | M17: =+F17+L17 -> 46066 | O17: =+M17-K17 -> -100 | R17: =+S17-T17 -> 46167 | S17: =+AC17-1 -> 46197 | T17: 30 | U17: =+M17+T17 -> 46096 | W17: =+U17-S17 -> -101 | AC17: =+AD17-AE17 -> 46198 | AD17: =+AJ17-1 -> 46243 | AE17: 45 | AF17: =+IF(V17=0,U17,V17)+AE17 -> 46141 | AH17: =+AF17-AD17 -> -102 | AJ17: =+AK17-AL17 -> 46244 | AK17: =+AV17-1 -> 46264 | AL17: 20 | AM17: =+IF(AG17=0,AF17,AG17)+AL17 -> 46161 | AO17: =+AM17-AK17 -> -103 | AV17: =+AW17-AX17 -> 46265 | AW17: =+BC17-1 -> 46465 | AX17: 200 | AY17: =+IF(AN17=0,AM17,AN17)+AX17 -> 46361 | BA17: =+AY17-AW17 -> -104 | BC17: =+BD17-BE17 -> 46466 | BD17: =+BJ17 -> 46466 | BE17: 0 | BF17: =+IF(AZ17=0,AY17,AZ17)+BE17 -> 46361 | BH17: =+BF17-BD17 -> -105 | BJ17: =+BK17-BL17 -> 46466 | BK17: =+BQ17 -> 46466 | BL17: 0 | BM17: =+IF(BG17=0,BF17,BG17)+BL17 -> 46361 | BO17: =+BM17-BK17 -> -105 | BQ17: =+BR17-BS17 -> 46466 | BR17: =+BX17 -> 46473 | BS17: 7 | BT17: =+IF(BN17=0,BM17,BN17)+BS17 -> 46368 | BV17: =+BT17-BR17 -> -105 | BW17: FDE1140 | BX17: 46473 | BY17: =+BT17-BX17 -> -105 | CA17: FN entrega de trafos
A18: ELECTRICIDAD | B18: 5155-00-0000-IG-EL-RI-XXX | C18: RI-REQUISICIÓN DE INGENIERÍA - CAJAS DE CONEXIONADO | E18: =+J18-1 -> 46113 | F18: 46059 | H18: =+F18-E18 -> -54 | J18: =+K18-L18 -> 46114 | K18: =+R18-1 -> 46121 | L18: 7 | M18: =+F18+L18 -> 46066 | O18: =+M18-K18 -> -55 | R18: =+S18-T18 -> 46122 | S18: =+AC18-1 -> 46152 | T18: 30 | U18: =+M18+T18 -> 46096 | W18: =+U18-S18 -> -56 | AC18: =+AD18-AE18 -> 46153 | AD18: =+AJ18-1 -> 46198 | AE18: 45 | AF18: =+IF(V18=0,U18,V18)+AE18 -> 46141 | AH18: =+AF18-AD18 -> -57 | AJ18: =+AK18-AL18 -> 46199 | AK18: =+AV18-1 -> 46219 | AL18: 20 | AM18: =+IF(AG18=0,AF18,AG18)+AL18 -> 46161 | AO18: =+AM18-AK18 -> -58 | AV18: =+AW18-AX18 -> 46220 | AW18: =+BC18-1 -> 46340 | AX18: 120 | AY18: =+IF(AN18=0,AM18,AN18)+AX18 -> 46281 | BA18: =+AY18-AW18 -> -59 | BC18: =+BD18-BE18 -> 46341 | BD18: =+BJ18 -> 46341 | BE18: 0 | BF18: =+IF(AZ18=0,AY18,AZ18)+BE18 -> 46281 | BH18: =+BF18-BD18 -> -60 | BJ18: =+BK18-BL18 -> 46341 | BK18: =+BQ18 -> 46341 | BL18: 0 | BM18: =+IF(BG18=0,BF18,BG18)+BL18 -> 46281 | BO18: =+BM18-BK18 -> -60 | BQ18: =+BR18-BS18 -> 46341 | BR18: =+BX18 -> 46348 | BS18: 7 | BT18: =+IF(BN18=0,BM18,BN18)+BS18 -> 46288 | BV18: =+BT18-BR18 -> -60 | BW18: FDE1010 | BX18: 46348 | BY18: =+BT18-BX18 -> -60 | CA18: FN entrega de canalizaciones
A19: ELECTRICIDAD | B19: 5155-00-2300-IG-EL-RI-XXX | C19: RI-REQUISICIÓN DE INGENIERÍA - DUCTO DE BARRAS BT | E19: =+J19-1 -> 46114 | F19: 46059 | H19: =+F19-E19 -> -55 | J19: =+K19-L19 -> 46115 | K19: =+R19-1 -> 46122 | L19: 7 | M19: =+F19+L19 -> 46066 | O19: =+M19-K19 -> -56 | R19: =+S19-T19 -> 46123 | S19: =+AC19-1 -> 46153 | T19: 30 | U19: =+M19+T19 -> 46096 | W19: =+U19-S19 -> -57 | AC19: =+AD19-AE19 -> 46154 | AD19: =+AJ19-1 -> 46199 | AE19: 45 | AF19: =+IF(V19=0,U19,V19)+AE19 -> 46141 | AH19: =+AF19-AD19 -> -58 | AJ19: =+AK19-AL19 -> 46200 | AK19: =+AV19-1 -> 46220 | AL19: 20 | AM19: =+IF(AG19=0,AF19,AG19)+AL19 -> 46161 | AO19: =+AM19-AK19 -> -59 | AV19: =+AW19-AX19 -> 46221 | AW19: =+BC19-1 -> 46431 | AX19: 210 | AY19: =+IF(AN19=0,AM19,AN19)+AX19 -> 46371 | BA19: =+AY19-AW19 -> -60 | BC19: =+BD19-BE19 -> 46432 | BD19: =+BJ19 -> 46432 | BE19: 0 | BF19: =+IF(AZ19=0,AY19,AZ19)+BE19 -> 46371 | BH19: =+BF19-BD19 -> -61 | BJ19: =+BK19-BL19 -> 46432 | BK19: =+BQ19 -> 46432 | BL19: 0 | BM19: =+IF(BG19=0,BF19,BG19)+BL19 -> 46371 | BO19: =+BM19-BK19 -> -61 | BQ19: =+BR19-BS19 -> 46432 | BR19: =+BX19 -> 46439 | BS19: 7 | BT19: =+IF(BN19=0,BM19,BN19)+BS19 -> 46378 | BV19: =+BT19-BR19 -> -61 | BW19: FDE1103 | BX19: 46439 | BY19: =+BT19-BX19 -> -61 | CA19: FN entrega de shelter según cronograma
A20: ELECTRICIDAD | B20: 5155-00-2300-IG-EL-RI-XXX | C20: RI-REQUISICIÓN DE INGENIERÍA - GENERADOR DE EMERGENCIA | E20: =+J20-1 -> 45995 | F20: 46104 | H20: =+F20-E20 -> 109 | J20: =+K20-L20 -> 45996 | K20: =+R20-1 -> 46003 | L20: 7 | M20: =+F20+L20 -> 46111 | O20: =+M20-K20 -> 108 | R20: =+S20-T20 -> 46004 | S20: =+AC20-1 -> 46034 | T20: 30 | U20: =+M20+T20 -> 46141 | W20: =+U20-S20 -> 107 | AC20: =+AD20-AE20 -> 46035 | AD20: =+AJ20-1 -> 46080 | AE20: 45 | AF20: =+IF(V20=0,U20,V20)+AE20 -> 46186 | AH20: =+AF20-AD20 -> 106 | AJ20: =+AK20-AL20 -> 46081 | AK20: =+AV20-1 -> 46101 | AL20: 20 | AM20: =+IF(AG20=0,AF20,AG20)+AL20 -> 46206 | AO20: =+AM20-AK20 -> 105 | AV20: =+AW20-AX20 -> 46102 | AW20: =+BC20-1 -> 46282 | AX20: 180 | AY20: =+IF(AN20=0,AM20,AN20)+AX20 -> 46386 | BA20: =+AY20-AW20 -> 104 | BC20: =+BD20-BE20 -> 46283 | BD20: =+BJ20 -> 46283 | BE20: 0 | BF20: =+IF(AZ20=0,AY20,AZ20)+BE20 -> 46386 | BH20: =+BF20-BD20 -> 103 | BJ20: =+BK20-BL20 -> 46283 | BK20: =+BQ20 -> 46283 | BL20: 0 | BM20: =+IF(BG20=0,BF20,BG20)+BL20 -> 46386 | BO20: =+BM20-BK20 -> 103 | BQ20: =+BR20-BS20 -> 46283 | BR20: =+BX20 -> 46290 | BS20: 7 | BT20: =+IF(BN20=0,BM20,BN20)+BS20 -> 46393 | BV20: =+BT20-BR20 -> 103 | BW20: CM015021 | BX20: 46290 | BY20: =+BT20-BX20 -> 103 | CA20: No tiene ítem el crono. Se toma inicio de montaje de generadores de Pluspetrol
A21: ELECTRICIDAD | B21: 5155-00-0000-IG-EL-RI-XXX | C21: RI-REQUISICIÓN DE INGENIERÍA - MATERIALES DE PAT Y SPCDA - Compra inicial | E21: =+J21-1 -> 45914 | F21: 45930 | H21: =+F21-E21 -> 16 | J21: =+K21-L21 -> 45915 | K21: =+R21-1 -> 45922 | L21: 7 | M21: =+F21+L21 -> 45937 | O21: =+M21-K21 -> 15 | R21: =+S21-T21 -> 45923 | S21: =+AC21-1 -> 45953 | T21: 30 | U21: =+M21+T21 -> 45967 | W21: =+U21-S21 -> 14 | AC21: =+AD21-AE21 -> 45954 | AD21: =+AJ21-1 -> 45984 | AE21: 30 | AF21: =+IF(V21=0,U21,V21)+AE21 -> 45997 | AH21: =+AF21-AD21 -> 13 | AJ21: =+AK21-AL21 -> 45985 | AK21: =+AV21-1 -> 46005 | AL21: 20 | AM21: =+IF(AG21=0,AF21,AG21)+AL21 -> 46017 | AO21: =+AM21-AK21 -> 12 | AV21: =+AW21-AX21 -> 46006 | AW21: =+BC21-1 -> 46086 | AX21: 80 | AY21: =+IF(AN21=0,AM21,AN21)+AX21 -> 46097 | BA21: =+AY21-AW21 -> 11 | BC21: =+BD21-BE21 -> 46087 | BD21: =+BJ21 -> 46087 | BE21: 0 | BF21: =+IF(AZ21=0,AY21,AZ21)+BE21 -> 46097 | BH21: =+BF21-BD21 -> 10 | BJ21: =+BK21-BL21 -> 46087 | BK21: =+BQ21 -> 46087 | BL21: 0 | BM21: =+IF(BG21=0,BF21,BG21)+BL21 -> 46097 | BO21: =+BM21-BK21 -> 10 | BQ21: =+BR21-BS21 -> 46087 | BR21: =+BX21 -> 46094 | BS21: 7 | BT21: =+IF(BN21=0,BM21,BN21)+BS21 -> 46104 | BV21: =+BT21-BR21 -> 10 | BW21: CDE1055 | BX21: 46094 | BY21: =+BT21-BX21 -> 10 | CA21: FN inicio de trabajos PAT
A22: ELECTRICIDAD | B22: 5155-00-0000-IG-EL-RI-XXX | C22: RI-REQUISICIÓN DE INGENIERÍA - MATERIALES DE ILUMINACIÓN Y TOMAS | E22: =+J22-1 -> 46191 | F22: 46101 | H22: =+F22-E22 -> -90 | J22: =+K22-L22 -> 46192 | K22: =+R22-1 -> 46199 | L22: 7 | M22: =+F22+L22 -> 46108 | O22: =+M22-K22 -> -91 | R22: =+S22-T22 -> 46200 | S22: =+AC22-1 -> 46230 | T22: 30 | U22: =+M22+T22 -> 46138 | W22: =+U22-S22 -> -92 | AC22: =+AD22-AE22 -> 46231 | AD22: =+AJ22-1 -> 46276 | AE22: 45 | AF22: =+IF(V22=0,U22,V22)+AE22 -> 46183 | AH22: =+AF22-AD22 -> -93 | AJ22: =+AK22-AL22 -> 46277 | AK22: =+AV22-1 -> 46297 | AL22: 20 | AM22: =+IF(AG22=0,AF22,AG22)+AL22 -> 46203 | AO22: =+AM22-AK22 -> -94 | AV22: =+AW22-AX22 -> 46298 | AW22: =+BC22-1 -> 46418 | AX22: 120 | AY22: =+IF(AN22=0,AM22,AN22)+AX22 -> 46323 | BA22: =+AY22-AW22 -> -95 | BC22: =+BD22-BE22 -> 46419 | BD22: =+BJ22 -> 46419 | BE22: 0 | BF22: =+IF(AZ22=0,AY22,AZ22)+BE22 -> 46323 | BH22: =+BF22-BD22 -> -96 | BJ22: =+BK22-BL22 -> 46419 | BK22: =+BQ22 -> 46419 | BL22: 0 | BM22: =+IF(BG22=0,BF22,BG22)+BL22 -> 46323 | BO22: =+BM22-BK22 -> -96 | BQ22: =+BR22-BS22 -> 46419 | BR22: =+BX22 -> 46426 | BS22: 7 | BT22: =+IF(BN22=0,BM22,BN22)+BS22 -> 46330 | BV22: =+BT22-BR22 -> -96 | BW22: FDE1090 | BX22: 46426 | BY22: =+BT22-BX22 -> -96 | CA22: FN entrega de acuerdo a crono
A23: ELECTRICIDAD | B23: 5155-00-0000-IG-EL-RI-XXX | C23: RI-REQUISICIÓN DE INGENIERÍA - TRACING | E23: =+J23-1 -> 46070 | F23: 46335 | H23: =+F23-E23 -> 265 | J23: =+K23-L23 -> 46071 | K23: =+R23-1 -> 46078 | L23: 7 | M23: =+F23+L23 -> 46342 | O23: =+M23-K23 -> 264 | R23: =+S23-T23 -> 46079 | S23: =+AC23-1 -> 46109 | T23: 30 | U23: =+M23+T23 -> 46372 | W23: =+U23-S23 -> 263 | AC23: =+AD23-AE23 -> 46110 | AD23: =+AJ23-1 -> 46155 | AE23: 45 | AF23: =+IF(V23=0,U23,V23)+AE23 -> 46417 | AH23: =+AF23-AD23 -> 262 | AJ23: =+AK23-AL23 -> 46156 | AK23: =+AV23-1 -> 46176 | AL23: 20 | AM23: =+IF(AG23=0,AF23,AG23)+AL23 -> 46437 | AO23: =+AM23-AK23 -> 261 | AV23: =+AW23-AX23 -> 46177 | AW23: =+BC23-1 -> 46297 | AX23: 120 | AY23: =+IF(AN23=0,AM23,AN23)+AX23 -> 46557 | BA23: =+AY23-AW23 -> 260 | BC23: =+BD23-BE23 -> 46298 | BD23: =+BJ23 -> 46298 | BE23: 0 | BF23: =+IF(AZ23=0,AY23,AZ23)+BE23 -> 46557 | BH23: =+BF23-BD23 -> 259 | BJ23: =+BK23-BL23 -> 46298 | BK23: =+BQ23 -> 46298 | BL23: 0 | BM23: =+IF(BG23=0,BF23,BG23)+BL23 -> 46557 | BO23: =+BM23-BK23 -> 259 | BQ23: =+BR23-BS23 -> 46298 | BR23: =+BX23 -> 46305 | BS23: 7 | BT23: =+IF(BN23=0,BM23,BN23)+BS23 -> 46564 | BV23: =+BT23-BR23 -> 259 | BW23: CDE1160 | BX23: 46305 | BY23: =+BT23-BX23 -> 259 | CA23: FN inicio de trabajos de tracing
A24: ELECTRICIDAD | B24: 5155-00-0000-IG-EL-RI-XXX | C24: RI-REQUISICIÓN DE INGENIERÍA - PROTECCIÓN CATÓDICA | E24: =+J24-1 -> 46191 | F24: 46335 | H24: =+F24-E24 -> 144 | J24: =+K24-L24 -> 46192 | K24: =+R24-1 -> 46199 | L24: 7 | M24: =+F24+L24 -> 46342 | O24: =+M24-K24 -> 143 | R24: =+S24-T24 -> 46200 | S24: =+AC24-1 -> 46230 | T24: 30 | U24: =+M24+T24 -> 46372 | W24: =+U24-S24 -> 142 | AC24: =+AD24-AE24 -> 46231 | AD24: =+AJ24-1 -> 46276 | AE24: 45 | AF24: =+IF(V24=0,U24,V24)+AE24 -> 46417 | AH24: =+AF24-AD24 -> 141 | AJ24: =+AK24-AL24 -> 46277 | AK24: =+AV24-1 -> 46297 | AL24: 20 | AM24: =+IF(AG24=0,AF24,AG24)+AL24 -> 46437 | AO24: =+AM24-AK24 -> 140 | AV24: =+AW24-AX24 -> 46298 | AW24: =+BC24-1 -> 46418 | AX24: 120 | AY24: =+IF(AN24=0,AM24,AN24)+AX24 -> 46557 | BA24: =+AY24-AW24 -> 139 | BC24: =+BD24-BE24 -> 46419 | BD24: =+BJ24 -> 46419 | BE24: 0 | BF24: =+IF(AZ24=0,AY24,AZ24)+BE24 -> 46557 | BH24: =+BF24-BD24 -> 138 | BJ24: =+BK24-BL24 -> 46419 | BK24: =+BQ24 -> 46419 | BL24: 0 | BM24: =+IF(BG24=0,BF24,BG24)+BL24 -> 46557 | BO24: =+BM24-BK24 -> 138 | BQ24: =+BR24-BS24 -> 46419 | BR24: =+BX24 -> 46426 | BS24: 7 | BT24: =+IF(BN24=0,BM24,BN24)+BS24 -> 46564 | BV24: =+BT24-BR24 -> 138 | BW24: FDE1090 | BX24: 46426 | BY24: =+BT24-BX24 -> 138 | CA24: FN entrega de columnas de acuerod a cronograma
A25: ELECTRICIDAD | B25: 5155-00-0000-IG-EL-RI-XXX | C25: RI-REQUISICIÓN DE INGENIERÍA - CABLES ELÉCTRICOS- Ing al 30% - Incluye cables MT | E25: =+J25-1 -> 46102 | F25: 46104 | H25: =+F25-E25 -> 2 | J25: =+K25-L25 -> 46103 | K25: =+R25-1 -> 46110 | L25: 7 | M25: =+F25+L25 -> 46111 | O25: =+M25-K25 -> 1 | R25: =+S25-T25 -> 46111 | S25: =+AC25-1 -> 46141 | T25: 30 | U25: =+M25+T25 -> 46141 | W25: =+U25-S25 -> 0 | AC25: =+AD25-AE25 -> 46142 | AD25: =+AJ25-1 -> 46187 | AE25: 45 | AF25: =+IF(V25=0,U25,V25)+AE25 -> 46186 | AH25: =+AF25-AD25 -> -1 | AJ25: =+AK25-AL25 -> 46188 | AK25: =+AV25-1 -> 46208 | AL25: 20 | AM25: =+IF(AG25=0,AF25,AG25)+AL25 -> 46206 | AO25: =+AM25-AK25 -> -2 | AV25: =+AW25-AX25 -> 46209 | AW25: =+BC25-1 -> 46359 | AX25: 150 | AY25: =+IF(AN25=0,AM25,AN25)+AX25 -> 46356 | BA25: =+AY25-AW25 -> -3 | BC25: =+BD25-BE25 -> 46360 | BD25: =+BJ25 -> 46360 | BE25: 0 | BF25: =+IF(AZ25=0,AY25,AZ25)+BE25 -> 46356 | BH25: =+BF25-BD25 -> -4 | BJ25: =+BK25-BL25 -> 46360 | BK25: =+BQ25 -> 46360 | BL25: 0 | BM25: =+IF(BG25=0,BF25,BG25)+BL25 -> 46356 | BO25: =+BM25-BK25 -> -4 | BQ25: =+BR25-BS25 -> 46360 | BR25: =+BX25 -> 46367 | BS25: 7 | BT25: =+IF(BN25=0,BM25,BN25)+BS25 -> 46363 | BV25: =+BT25-BR25 -> -4 | BW25: CDE1127 | BX25: 46367 | BY25: =+BT25-BX25 -> -4 | CA25: FN inicio de trabajos de tendido
A26: ELECTRICIDAD | B26: 5155-00-0000-IG-EL-RI-XXX | C26: RI-REQUISICIÓN DE INGENIERÍA - CABLES ELÉCTRICOS- Ing al 60% - Cables BT | E26: =+J26-1 -> 46206 | H26: =+F26-E26 -> -46206 | J26: =+K26-L26 -> 46207 | K26: =+R26-1 -> 46214 | L26: 7 | M26: =+F26+L26 -> 7 | O26: =+M26-K26 -> -46207 | R26: =+S26-T26 -> 46215 | S26: =+AC26-1 -> 46245 | T26: 30 | U26: =+M26+T26 -> 37 | W26: =+U26-S26 -> -46208 | AC26: =+AD26-AE26 -> 46246 | AD26: =+AJ26-1 -> 46291 | AE26: 45 | AF26: =+IF(V26=0,U26,V26)+AE26 -> 82 | AH26: =+AF26-AD26 -> -46209 | AJ26: =+AK26-AL26 -> 46292 | AK26: =+AV26-1 -> 46312 | AL26: 20 | AM26: =+IF(AG26=0,AF26,AG26)+AL26 -> 102 | AO26: =+AM26-AK26 -> -46210 | AV26: =+AW26-AX26 -> 46313 | AW26: =+BC26-1 -> 46463 | AX26: 150 | AY26: =+IF(AN26=0,AM26,AN26)+AX26 -> 252 | BA26: =+AY26-AW26 -> -46211 | BC26: =+BD26-BE26 -> 46464 | BD26: =+BJ26 -> 46464 | BE26: 0 | BF26: =+IF(AZ26=0,AY26,AZ26)+BE26 -> 252 | BH26: =+BF26-BD26 -> -46212 | BJ26: =+BK26-BL26 -> 46464 | BK26: =+BQ26 -> 46464 | BL26: 0 | BM26: =+IF(BG26=0,BF26,BG26)+BL26 -> 252 | BO26: =+BM26-BK26 -> -46212 | BQ26: =+BR26-BS26 -> 46464 | BR26: =+BX26 -> 46471 | BS26: 7 | BT26: =+IF(BN26=0,BM26,BN26)+BS26 -> 259 | BV26: =+BT26-BR26 -> -46212 | BW26: CDE1127 | BX26: 46471 | BY26: =+BT26-BX26 -> -46212 | CA26: FN 150 días antes de fin de tendido
A27: ELECTRICIDAD | B27: 5155-00-0000-IG-EL-RI-XXX | C27: RI-REQUISICIÓN DE INGENIERÍA - CABLES ELÉCTRICOS- Ing al 90% - Cables BT | E27: =+J27-1 -> 46298 | H27: =+F27-E27 -> -46298 | J27: =+K27-L27 -> 46299 | K27: =+R27-1 -> 46306 | L27: 7 | M27: =+F27+L27 -> 7 | O27: =+M27-K27 -> -46299 | R27: =+S27-T27 -> 46307 | S27: =+AC27-1 -> 46337 | T27: 30 | U27: =+M27+T27 -> 37 | W27: =+U27-S27 -> -46300 | AC27: =+AD27-AE27 -> 46338 | AD27: =+AJ27-1 -> 46383 | AE27: 45 | AF27: =+IF(V27=0,U27,V27)+AE27 -> 82 | AH27: =+AF27-AD27 -> -46301 | AJ27: =+AK27-AL27 -> 46384 | AK27: =+AV27-1 -> 46404 | AL27: 20 | AM27: =+IF(AG27=0,AF27,AG27)+AL27 -> 102 | AO27: =+AM27-AK27 -> -46302 | AV27: =+AW27-AX27 -> 46405 | AW27: =+BC27-1 -> 46555 | AX27: 150 | AY27: =+IF(AN27=0,AM27,AN27)+AX27 -> 252 | BA27: =+AY27-AW27 -> -46303 | BC27: =+BD27-BE27 -> 46556 | BD27: =+BJ27 -> 46556 | BE27: 0 | BF27: =+IF(AZ27=0,AY27,AZ27)+BE27 -> 252 | BH27: =+BF27-BD27 -> -46304 | BJ27: =+BK27-BL27 -> 46556 | BK27: =+BQ27 -> 46556 | BL27: 0 | BM27: =+IF(BG27=0,BF27,BG27)+BL27 -> 252 | BO27: =+BM27-BK27 -> -46304 | BQ27: =+BR27-BS27 -> 46556 | BR27: =+BX27 -> 46563 | BS27: 7 | BT27: =+IF(BN27=0,BM27,BN27)+BS27 -> 259 | BV27: =+BT27-BR27 -> -46304 | BW27: CDE1127 | BX27: 46563 | BY27: =+BT27-BX27 -> -46304 | CA27: FN 60 días antes de fin de tendido
A28: ELECTRICIDAD | B28: 5155-00-0000-IG-EL-RI-XXX | C28: RI-REQUISICIÓN DE INGENIERÍA - CANALIZACIONES ELÉCTRICAS | E28: =+J28-1 -> 46113 | F28: 46059 | H28: =+F28-E28 -> -54 | J28: =+K28-L28 -> 46114 | K28: =+R28-1 -> 46121 | L28: 7 | M28: =+F28+L28 -> 46066 | O28: =+M28-K28 -> -55 | R28: =+S28-T28 -> 46122 | S28: =+AC28-1 -> 46152 | T28: 30 | U28: =+M28+T28 -> 46096 | W28: =+U28-S28 -> -56 | AC28: =+AD28-AE28 -> 46153 | AD28: =+AJ28-1 -> 46198 | AE28: 45 | AF28: =+IF(V28=0,U28,V28)+AE28 -> 46141 | AH28: =+AF28-AD28 -> -57 | AJ28: =+AK28-AL28 -> 46199 | AK28: =+AV28-1 -> 46219 | AL28: 20 | AM28: =+IF(AG28=0,AF28,AG28)+AL28 -> 46161 | AO28: =+AM28-AK28 -> -58 | AV28: =+AW28-AX28 -> 46220 | AW28: =+BC28-1 -> 46340 | AX28: 120 | AY28: =+IF(AN28=0,AM28,AN28)+AX28 -> 46281 | BA28: =+AY28-AW28 -> -59 | BC28: =+BD28-BE28 -> 46341 | BD28: =+BJ28 -> 46341 | BE28: 0 | BF28: =+IF(AZ28=0,AY28,AZ28)+BE28 -> 46281 | BH28: =+BF28-BD28 -> -60 | BJ28: =+BK28-BL28 -> 46341 | BK28: =+BQ28 -> 46341 | BL28: 0 | BM28: =+IF(BG28=0,BF28,BG28)+BL28 -> 46281 | BO28: =+BM28-BK28 -> -60 | BQ28: =+BR28-BS28 -> 46341 | BR28: =+BX28 -> 46348 | BS28: 7 | BT28: =+IF(BN28=0,BM28,BN28)+BS28 -> 46288 | BV28: =+BT28-BR28 -> -60 | BW28: FDE1010 | BX28: 46348 | BY28: =+BT28-BX28 -> -60 | CA28: FN entrega de canalizaciones
A29: ELECTRICIDAD | B29: 5155-00-0000-IG-EL-RI-XXX | C29: RI-REQUISICIÓN DE INGENIERÍA - PRENSACABLES | E29: =+J29-1 -> 46221 | F29: 46059 | H29: =+F29-E29 -> -162 | J29: =+K29-L29 -> 46222 | K29: =+R29-1 -> 46229 | L29: 7 | M29: =+F29+L29 -> 46066 | O29: =+M29-K29 -> -163 | R29: =+S29-T29 -> 46230 | S29: =+AC29-1 -> 46260 | T29: 30 | U29: =+M29+T29 -> 46096 | W29: =+U29-S29 -> -164 | AC29: =+AD29-AE29 -> 46261 | AD29: =+AJ29-1 -> 46306 | AE29: 45 | AF29: =+IF(V29=0,U29,V29)+AE29 -> 46141 | AH29: =+AF29-AD29 -> -165 | AJ29: =+AK29-AL29 -> 46307 | AK29: =+AV29-1 -> 46327 | AL29: 20 | AM29: =+IF(AG29=0,AF29,AG29)+AL29 -> 46161 | AO29: =+AM29-AK29 -> -166 | AV29: =+AW29-AX29 -> 46328 | AW29: =+BC29-1 -> 46418 | AX29: 90 | AY29: =+IF(AN29=0,AM29,AN29)+AX29 -> 46251 | BA29: =+AY29-AW29 -> -167 | BC29: =+BD29-BE29 -> 46419 | BD29: =+BJ29 -> 46419 | BE29: 0 | BF29: =+IF(AZ29=0,AY29,AZ29)+BE29 -> 46251 | BH29: =+BF29-BD29 -> -168 | BJ29: =+BK29-BL29 -> 46419 | BK29: =+BQ29 -> 46419 | BL29: 0 | BM29: =+IF(BG29=0,BF29,BG29)+BL29 -> 46251 | BO29: =+BM29-BK29 -> -168 | BQ29: =+BR29-BS29 -> 46419 | BR29: =+BX29 -> 46426 | BS29: 7 | BT29: =+IF(BN29=0,BM29,BN29)+BS29 -> 46258 | BV29: =+BT29-BR29 -> -168 | BW29: FDE1090 | BX29: 46426 | BY29: =+BT29-BX29 -> -168 | CA29: FN entrega de columnas de acuerod a cronograma
A30: ELECTRICIDAD | B30: 5155-00-0000-IG-EL-RI-XXX | C30: RI-REQUISICIÓN DE INGENIERÍA - MISCELÁNEOS | E30: =+J30-1 -> 46191 | F30: 46059 | H30: =+F30-E30 -> -132 | J30: =+K30-L30 -> 46192 | K30: =+R30-1 -> 46199 | L30: 7 | M30: =+F30+L30 -> 46066 | O30: =+M30-K30 -> -133 | R30: =+S30-T30 -> 46200 | S30: =+AC30-1 -> 46230 | T30: 30 | U30: =+M30+T30 -> 46096 | W30: =+U30-S30 -> -134 | AC30: =+AD30-AE30 -> 46231 | AD30: =+AJ30-1 -> 46276 | AE30: 45 | AF30: =+IF(V30=0,U30,V30)+AE30 -> 46141 | AH30: =+AF30-AD30 -> -135 | AJ30: =+AK30-AL30 -> 46277 | AK30: =+AV30-1 -> 46297 | AL30: 20 | AM30: =+IF(AG30=0,AF30,AG30)+AL30 -> 46161 | AO30: =+AM30-AK30 -> -136 | AV30: =+AW30-AX30 -> 46298 | AW30: =+BC30-1 -> 46418 | AX30: 120 | AY30: =+IF(AN30=0,AM30,AN30)+AX30 -> 46281 | BA30: =+AY30-AW30 -> -137 | BC30: =+BD30-BE30 -> 46419 | BD30: =+BJ30 -> 46419 | BE30: 0 | BF30: =+IF(AZ30=0,AY30,AZ30)+BE30 -> 46281 | BH30: =+BF30-BD30 -> -138 | BJ30: =+BK30-BL30 -> 46419 | BK30: =+BQ30 -> 46419 | BL30: 0 | BM30: =+IF(BG30=0,BF30,BG30)+BL30 -> 46281 | BO30: =+BM30-BK30 -> -138 | BQ30: =+BR30-BS30 -> 46419 | BR30: =+BX30 -> 46426 | BS30: 7 | BT30: =+IF(BN30=0,BM30,BN30)+BS30 -> 46288 | BV30: =+BT30-BR30 -> -138 | BW30: FDE1090 | BX30: 46426 | BY30: =+BT30-BX30 -> -138 | CA30: FN entrega de columnas de acuerod a cronograma
A31: ELECTRICIDAD | B31: 5155-00-2000-IG-EL-RI-XXX | C31: RI-REQUISICIÓN DE INGENIERÍA - EQUIPAMIENTO DE MANIOBRA DE MT INTEMPERIE | E31: =+J31-1 -> 46144 | F31: 46000 | H31: =+F31-E31 -> -144 | J31: =+K31-L31 -> 46145 | K31: =+R31-1 -> 46152 | L31: 7 | M31: =+F31+L31 -> 46007 | O31: =+M31-K31 -> -145 | R31: =+S31-T31 -> 46153 | S31: =+AC31-1 -> 46183 | T31: 30 | U31: =+M31+T31 -> 46037 | W31: =+U31-S31 -> -146 | AC31: =+AD31-AE31 -> 46184 | AD31: =+AJ31-1 -> 46229 | AE31: 45 | AF31: =+IF(V31=0,U31,V31)+AE31 -> 46082 | AH31: =+AF31-AD31 -> -147 | AJ31: =+AK31-AL31 -> 46230 | AK31: =+AV31-1 -> 46250 | AL31: 20 | AM31: =+IF(AG31=0,AF31,AG31)+AL31 -> 46102 | AO31: =+AM31-AK31 -> -148 | AV31: =+AW31-AX31 -> 46251 | AW31: =+BC31-1 -> 46431 | AX31: 180 | AY31: =+IF(AN31=0,AM31,AN31)+AX31 -> 46282 | BA31: =+AY31-AW31 -> -149 | BC31: =+BD31-BE31 -> 46432 | BD31: =+BJ31 -> 46432 | BE31: 0 | BF31: =+IF(AZ31=0,AY31,AZ31)+BE31 -> 46282 | BH31: =+BF31-BD31 -> -150 | BJ31: =+BK31-BL31 -> 46432 | BK31: =+BQ31 -> 46432 | BL31: 0 | BM31: =+IF(BG31=0,BF31,BG31)+BL31 -> 46282 | BO31: =+BM31-BK31 -> -150 | BQ31: =+BR31-BS31 -> 46432 | BR31: =+BX31 -> 46439 | BS31: 7 | BT31: =+IF(BN31=0,BM31,BN31)+BS31 -> 46289 | BV31: =+BT31-BR31 -> -150 | BX31: 46439 | BY31: =+BT31-BX31 -> -150 | CA31: Asumo misma FN que los shelters
A32: ELECTRICIDAD | B32: 5155-00-2300-IG-EL-RI-XXX | C32: RI-REQUISICIÓN DE INGENIERÍA - SHELTER ELECTRICO SE#4 MT CON EQUIPAMIENTO | E32: =+J32-1 -> 45869 | F32: 45894 | H32: =+F32-E32 -> 25 | J32: =+K32-L32 -> 45870 | K32: =+R32-1 -> 45877 | L32: 7 | M32: =+F32+L32 -> 45901 | O32: =+M32-K32 -> 24 | R32: =+S32-T32 -> 45878 | S32: =+AC32-1 -> 45908 | T32: 30 | U32: =+M32+T32 -> 45931 | W32: =+U32-S32 -> 23 | AC32: =+AD32-AE32 -> 45909 | AD32: =+AJ32-1 -> 45969 | AE32: 60 | AF32: =+IF(V32=0,U32,V32)+AE32 -> 45991 | AH32: =+AF32-AD32 -> 22 | AJ32: =+AK32-AL32 -> 45970 | AK32: =+AV32-1 -> 46010 | AL32: 40 | AM32: =+IF(AG32=0,AF32,AG32)+AL32 -> 46031 | AO32: =+AM32-AK32 -> 21 | AV32: =+AW32-AX32 -> 46011 | AW32: =+BC32-1 -> 46431 | AX32: 420 | AY32: =+IF(AN32=0,AM32,AN32)+AX32 -> 46451 | BA32: =+AY32-AW32 -> 20 | BC32: =+BD32-BE32 -> 46432 | BD32: =+BJ32 -> 46432 | BE32: 0 | BF32: =+IF(AZ32=0,AY32,AZ32)+BE32 -> 46451 | BH32: =+BF32-BD32 -> 19 | BJ32: =+BK32-BL32 -> 46432 | BK32: =+BQ32 -> 46432 | BL32: 0 | BM32: =+IF(BG32=0,BF32,BG32)+BL32 -> 46451 | BO32: =+BM32-BK32 -> 19 | BQ32: =+BR32-BS32 -> 46432 | BR32: =+BX32 -> 46439 | BS32: 7 | BT32: =+IF(BN32=0,BM32,BN32)+BS32 -> 46458 | BV32: =+BT32-BR32 -> 19 | BW32: FDE1103 | BX32: 46439 | BY32: =+BT32-BX32 -> 19 | CA32: FN entrega según cronograma
A33: ELECTRICIDAD | B33: 5155-00-2300-IG-EL-RI-XXX | C33: RI-REQUISICIÓN DE INGENIERÍA - SHELTER ELECTRICO SE#3 Y SE#4 BT CON EQUIPAMIENTO | E33: =+J33-1 -> 45929 | F33: 45925 | H33: =+F33-E33 -> -4 | J33: =+K33-L33 -> 45930 | K33: =+R33-1 -> 45937 | L33: 7 | M33: =+F33+L33 -> 45932 | O33: =+M33-K33 -> -5 | R33: =+S33-T33 -> 45938 | S33: =+AC33-1 -> 45968 | T33: 30 | U33: =+M33+T33 -> 45962 | W33: =+U33-S33 -> -6 | AC33: =+AD33-AE33 -> 45969 | AD33: =+AJ33-1 -> 46029 | AE33: 60 | AF33: =+IF(V33=0,U33,V33)+AE33 -> 46022 | AH33: =+AF33-AD33 -> -7 | AJ33: =+AK33-AL33 -> 46030 | AK33: =+AV33-1 -> 46070 | AL33: 40 | AM33: =+IF(AG33=0,AF33,AG33)+AL33 -> 46062 | AO33: =+AM33-AK33 -> -8 | AV33: =+AW33-AX33 -> 46071 | AW33: =+BC33-1 -> 46431 | AX33: 360 | AY33: =+IF(AN33=0,AM33,AN33)+AX33 -> 46422 | BA33: =+AY33-AW33 -> -9 | BC33: =+BD33-BE33 -> 46432 | BD33: =+BJ33 -> 46432 | BE33: 0 | BF33: =+IF(AZ33=0,AY33,AZ33)+BE33 -> 46422 | BH33: =+BF33-BD33 -> -10 | BJ33: =+BK33-BL33 -> 46432 | BK33: =+BQ33 -> 46432 | BL33: 0 | BM33: =+IF(BG33=0,BF33,BG33)+BL33 -> 46422 | BO33: =+BM33-BK33 -> -10 | BQ33: =+BR33-BS33 -> 46432 | BR33: =+BX33 -> 46439 | BS33: 7 | BT33: =+IF(BN33=0,BM33,BN33)+BS33 -> 46429 | BV33: =+BT33-BR33 -> -10 | BW33: FDE1104 | BX33: 46439 | BY33: =+BT33-BX33 -> -10 | CA33: FN entrega según cronograma
A34: INSTRUMENTOS | B34: 5155-00-0000-IG-IN-RI-XXX | C34: REQUISICIÓN DE INGENIERÍA VÁLVULAS DE CONTROL Y AUTORREGULADORAS | E34: =+J34-1 -> 45998 | F34: 46003 | H34: =+F34-E34 -> 5 | J34: =+K34-L34 -> 45999 | K34: =+R34-1 -> 46006 | L34: 7 | M34: =+F34+L34 -> 46010 | O34: =+M34-K34 -> 4 | R34: =+S34-T34 -> 46007 | S34: =+AC34-1 -> 46037 | T34: 30 | U34: =+M34+T34 -> 46040 | W34: =+U34-S34 -> 3 | AC34: =+AD34-AE34 -> 46038 | AD34: =+AJ34-1 -> 46083 | AE34: 45 | AF34: =+IF(V34=0,U34,V34)+AE34 -> 46085 | AH34: =+AF34-AD34 -> 2 | AJ34: =+AK34-AL34 -> 46084 | AK34: =+AV34-1 -> 46104 | AL34: 20 | AM34: =+IF(AG34=0,AF34,AG34)+AL34 -> 46105 | AO34: =+AM34-AK34 -> 1 | AV34: =+AW34-AX34 -> 46105 | AW34: =+BC34-1 -> 46405 | AX34: 300 | AY34: =+IF(AN34=0,AM34,AN34)+AX34 -> 46405 | BA34: =+AY34-AW34 -> 0 | BC34: =+BD34-BE34 -> 46406 | BD34: =+BJ34 -> 46406 | BE34: 0 | BF34: =+IF(AZ34=0,AY34,AZ34)+BE34 -> 46405 | BH34: =+BF34-BD34 -> -1 | BJ34: =+BK34-BL34 -> 46406 | BK34: =+BQ34 -> 46406 | BL34: 0 | BM34: =+IF(BG34=0,BF34,BG34)+BL34 -> 46405 | BO34: =+BM34-BK34 -> -1 | BQ34: =+BR34-BS34 -> 46406 | BR34: =+BX34 -> 46413 | BS34: 7 | BT34: =+IF(BN34=0,BM34,BN34)+BS34 -> 46412 | BV34: =+BT34-BR34 -> -1 | BW34: FDI1060 | BX34: 46413 | BY34: =+BT34-BX34 -> -1
A35: INSTRUMENTOS | B35: 5155-00-0000-IG-IN-RI-XXX | C35: REQUISICIÓN DE INGENIERÍA VÁLVULAS DE SEGURIDAD | E35: =+J35-1 -> 46148 | F35: 46007 | H35: =+F35-E35 -> -141 | J35: =+K35-L35 -> 46149 | K35: =+R35-1 -> 46156 | L35: 7 | M35: =+F35+L35 -> 46014 | O35: =+M35-K35 -> -142 | R35: =+S35-T35 -> 46157 | S35: =+AC35-1 -> 46187 | T35: 30 | U35: =+M35+T35 -> 46044 | W35: =+U35-S35 -> -143 | AC35: =+AD35-AE35 -> 46188 | AD35: =+AJ35-1 -> 46233 | AE35: 45 | AF35: =+IF(V35=0,U35,V35)+AE35 -> 46089 | AH35: =+AF35-AD35 -> -144 | AJ35: =+AK35-AL35 -> 46234 | AK35: =+AV35-1 -> 46254 | AL35: 20 | AM35: =+IF(AG35=0,AF35,AG35)+AL35 -> 46109 | AO35: =+AM35-AK35 -> -145 | AV35: =+AW35-AX35 -> 46255 | AW35: =+BC35-1 -> 46405 | AX35: 150 | AY35: =+IF(AN35=0,AM35,AN35)+AX35 -> 46259 | BA35: =+AY35-AW35 -> -146 | BC35: =+BD35-BE35 -> 46406 | BD35: =+BJ35 -> 46406 | BE35: 0 | BF35: =+IF(AZ35=0,AY35,AZ35)+BE35 -> 46259 | BH35: =+BF35-BD35 -> -147 | BJ35: =+BK35-BL35 -> 46406 | BK35: =+BQ35 -> 46406 | BL35: 0 | BM35: =+IF(BG35=0,BF35,BG35)+BL35 -> 46259 | BO35: =+BM35-BK35 -> -147 | BQ35: =+BR35-BS35 -> 46406 | BR35: =+BX35 -> 46413 | BS35: 7 | BT35: =+IF(BN35=0,BM35,BN35)+BS35 -> 46266 | BV35: =+BT35-BR35 -> -147 | BW35: FDI1060 | BX35: 46413 | BY35: =+BT35-BX35 -> -147
A36: INSTRUMENTOS | B36: 5155-00-2000-IG-IN-RI-XXX | C36: REQUISICIÓN DE INGENIERÍA INSTRUMENTOS F&G (DETECTORES GAS/FUEGO) | E36: =+J36-1 -> 46117 | F36: 46062 | H36: =+F36-E36 -> -55 | J36: =+K36-L36 -> 46118 | K36: =+R36-1 -> 46125 | L36: 7 | M36: =+F36+L36 -> 46069 | O36: =+M36-K36 -> -56 | R36: =+S36-T36 -> 46126 | S36: =+AC36-1 -> 46156 | T36: 30 | U36: =+M36+T36 -> 46099 | W36: =+U36-S36 -> -57 | AC36: =+AD36-AE36 -> 46157 | AD36: =+AJ36-1 -> 46202 | AE36: 45 | AF36: =+IF(V36=0,U36,V36)+AE36 -> 46144 | AH36: =+AF36-AD36 -> -58 | AJ36: =+AK36-AL36 -> 46203 | AK36: =+AV36-1 -> 46223 | AL36: 20 | AM36: =+IF(AG36=0,AF36,AG36)+AL36 -> 46164 | AO36: =+AM36-AK36 -> -59 | AV36: =+AW36-AX36 -> 46224 | AW36: =+BC36-1 -> 46374 | AX36: 150 | AY36: =+IF(AN36=0,AM36,AN36)+AX36 -> 46314 | BA36: =+AY36-AW36 -> -60 | BC36: =+BD36-BE36 -> 46375 | BD36: =+BJ36 -> 46375 | BE36: 0 | BF36: =+IF(AZ36=0,AY36,AZ36)+BE36 -> 46314 | BH36: =+BF36-BD36 -> -61 | BJ36: =+BK36-BL36 -> 46375 | BK36: =+BQ36 -> 46375 | BL36: 0 | BM36: =+IF(BG36=0,BF36,BG36)+BL36 -> 46314 | BO36: =+BM36-BK36 -> -61 | BQ36: =+BR36-BS36 -> 46375 | BR36: =+BX36 -> 46382 | BS36: 7 | BT36: =+IF(BN36=0,BM36,BN36)+BS36 -> 46321 | BV36: =+BT36-BR36 -> -61 | BW36: FDI1040 | BX36: 46382 | BY36: =+BT36-BX36 -> -61
A37: INSTRUMENTOS | B37: 5155-00-0000-IG-IN-RI-XXX | C37: REQUISICIÓN DE INGENIERÍA VÁLVULAS BLOWDOWN Y SHUTDOWN | E37: =+J37-1 -> 46058 | F37: 46006 | H37: =+F37-E37 -> -52 | J37: =+K37-L37 -> 46059 | K37: =+R37-1 -> 46066 | L37: 7 | M37: =+F37+L37 -> 46013 | O37: =+M37-K37 -> -53 | R37: =+S37-T37 -> 46067 | S37: =+AC37-1 -> 46097 | T37: 30 | U37: =+M37+T37 -> 46043 | W37: =+U37-S37 -> -54 | AC37: =+AD37-AE37 -> 46098 | AD37: =+AJ37-1 -> 46143 | AE37: 45 | AF37: =+IF(V37=0,U37,V37)+AE37 -> 46088 | AH37: =+AF37-AD37 -> -55 | AJ37: =+AK37-AL37 -> 46144 | AK37: =+AV37-1 -> 46164 | AL37: 20 | AM37: =+IF(AG37=0,AF37,AG37)+AL37 -> 46108 | AO37: =+AM37-AK37 -> -56 | AV37: =+AW37-AX37 -> 46165 | AW37: =+BC37-1 -> 46405 | AX37: 240 | AY37: =+IF(AN37=0,AM37,AN37)+AX37 -> 46348 | BA37: =+AY37-AW37 -> -57 | BC37: =+BD37-BE37 -> 46406 | BD37: =+BJ37 -> 46406 | BE37: 0 | BF37: =+IF(AZ37=0,AY37,AZ37)+BE37 -> 46348 | BH37: =+BF37-BD37 -> -58 | BJ37: =+BK37-BL37 -> 46406 | BK37: =+BQ37 -> 46406 | BL37: 0 | BM37: =+IF(BG37=0,BF37,BG37)+BL37 -> 46348 | BO37: =+BM37-BK37 -> -58 | BQ37: =+BR37-BS37 -> 46406 | BR37: =+BX37 -> 46413 | BS37: 7 | BT37: =+IF(BN37=0,BM37,BN37)+BS37 -> 46355 | BV37: =+BT37-BR37 -> -58 | BW37: FDI1060 | BX37: 46413 | BY37: =+BT37-BX37 -> -58
A38: INSTRUMENTOS | B38: 5155-00-0000-IG-IN-RI-XXX | C38: REQUISICIÓN DE INGENIERÍA PLACA ORIFICIO Y ORIFICIO DE RESTRICCIÓN | E38: =+J38-1 -> 46177 | F38: 46112 | H38: =+F38-E38 -> -65 | J38: =+K38-L38 -> 46178 | K38: =+R38-1 -> 46185 | L38: 7 | M38: =+F38+L38 -> 46119 | O38: =+M38-K38 -> -66 | R38: =+S38-T38 -> 46186 | S38: =+AC38-1 -> 46216 | T38: 30 | U38: =+M38+T38 -> 46149 | W38: =+U38-S38 -> -67 | AC38: =+AD38-AE38 -> 46217 | AD38: =+AJ38-1 -> 46262 | AE38: 45 | AF38: =+IF(V38=0,U38,V38)+AE38 -> 46194 | AH38: =+AF38-AD38 -> -68 | AJ38: =+AK38-AL38 -> 46263 | AK38: =+AV38-1 -> 46283 | AL38: 20 | AM38: =+IF(AG38=0,AF38,AG38)+AL38 -> 46214 | AO38: =+AM38-AK38 -> -69 | AV38: =+AW38-AX38 -> 46284 | AW38: =+BC38-1 -> 46374 | AX38: 90 | AY38: =+IF(AN38=0,AM38,AN38)+AX38 -> 46304 | BA38: =+AY38-AW38 -> -70 | BC38: =+BD38-BE38 -> 46375 | BD38: =+BJ38 -> 46375 | BE38: 0 | BF38: =+IF(AZ38=0,AY38,AZ38)+BE38 -> 46304 | BH38: =+BF38-BD38 -> -71 | BJ38: =+BK38-BL38 -> 46375 | BK38: =+BQ38 -> 46375 | BL38: 0 | BM38: =+IF(BG38=0,BF38,BG38)+BL38 -> 46304 | BO38: =+BM38-BK38 -> -71 | BQ38: =+BR38-BS38 -> 46375 | BR38: =+BX38 -> 46382 | BS38: 7 | BT38: =+IF(BN38=0,BM38,BN38)+BS38 -> 46311 | BV38: =+BT38-BR38 -> -71 | BW38: FDI1040 | BX38: 46382 | BY38: =+BT38-BX38 -> -71
A39: INSTRUMENTOS | B39: 5155-00-0000-IG-IN-RI-XXX | C39: REQUISICIÓN DE INGENIERÍA TRANSMISOR DE PRESIÓN | E39: =+J39-1 -> 46117 | F39: 46073 | H39: =+F39-E39 -> -44 | J39: =+K39-L39 -> 46118 | K39: =+R39-1 -> 46125 | L39: 7 | M39: =+F39+L39 -> 46080 | O39: =+M39-K39 -> -45 | R39: =+S39-T39 -> 46126 | S39: =+AC39-1 -> 46156 | T39: 30 | U39: =+M39+T39 -> 46110 | W39: =+U39-S39 -> -46 | AC39: =+AD39-AE39 -> 46157 | AD39: =+AJ39-1 -> 46202 | AE39: 45 | AF39: =+IF(V39=0,U39,V39)+AE39 -> 46155 | AH39: =+AF39-AD39 -> -47 | AJ39: =+AK39-AL39 -> 46203 | AK39: =+AV39-1 -> 46223 | AL39: 20 | AM39: =+IF(AG39=0,AF39,AG39)+AL39 -> 46175 | AO39: =+AM39-AK39 -> -48 | AV39: =+AW39-AX39 -> 46224 | AW39: =+BC39-1 -> 46374 | AX39: 150 | AY39: =+IF(AN39=0,AM39,AN39)+AX39 -> 46325 | BA39: =+AY39-AW39 -> -49 | BC39: =+BD39-BE39 -> 46375 | BD39: =+BJ39 -> 46375 | BE39: 0 | BF39: =+IF(AZ39=0,AY39,AZ39)+BE39 -> 46325 | BH39: =+BF39-BD39 -> -50 | BJ39: =+BK39-BL39 -> 46375 | BK39: =+BQ39 -> 46375 | BL39: 0 | BM39: =+IF(BG39=0,BF39,BG39)+BL39 -> 46325 | BO39: =+BM39-BK39 -> -50 | BQ39: =+BR39-BS39 -> 46375 | BR39: =+BX39 -> 46382 | BS39: 7 | BT39: =+IF(BN39=0,BM39,BN39)+BS39 -> 46332 | BV39: =+BT39-BR39 -> -50 | BW39: FDI1040 | BX39: 46382 | BY39: =+BT39-BX39 -> -50
A40: INSTRUMENTOS | B40: 5155-00-0000-IG-IN-RI-XXX | C40: REQUISICIÓN DE INGENIERÍA TRANSMISOR DE PRESIÓN DIFERENCIAL | E40: =+J40-1 -> 46117 | F40: 46076 | H40: =+F40-E40 -> -41 | J40: =+K40-L40 -> 46118 | K40: =+R40-1 -> 46125 | L40: 7 | M40: =+F40+L40 -> 46083 | O40: =+M40-K40 -> -42 | R40: =+S40-T40 -> 46126 | S40: =+AC40-1 -> 46156 | T40: 30 | U40: =+M40+T40 -> 46113 | W40: =+U40-S40 -> -43 | AC40: =+AD40-AE40 -> 46157 | AD40: =+AJ40-1 -> 46202 | AE40: 45 | AF40: =+IF(V40=0,U40,V40)+AE40 -> 46158 | AH40: =+AF40-AD40 -> -44 | AJ40: =+AK40-AL40 -> 46203 | AK40: =+AV40-1 -> 46223 | AL40: 20 | AM40: =+IF(AG40=0,AF40,AG40)+AL40 -> 46178 | AO40: =+AM40-AK40 -> -45 | AV40: =+AW40-AX40 -> 46224 | AW40: =+BC40-1 -> 46374 | AX40: 150 | AY40: =+IF(AN40=0,AM40,AN40)+AX40 -> 46328 | BA40: =+AY40-AW40 -> -46 | BC40: =+BD40-BE40 -> 46375 | BD40: =+BJ40 -> 46375 | BE40: 0 | BF40: =+IF(AZ40=0,AY40,AZ40)+BE40 -> 46328 | BH40: =+BF40-BD40 -> -47 | BJ40: =+BK40-BL40 -> 46375 | BK40: =+BQ40 -> 46375 | BL40: 0 | BM40: =+IF(BG40=0,BF40,BG40)+BL40 -> 46328 | BO40: =+BM40-BK40 -> -47 | BQ40: =+BR40-BS40 -> 46375 | BR40: =+BX40 -> 46382 | BS40: 7 | BT40: =+IF(BN40=0,BM40,BN40)+BS40 -> 46335 | BV40: =+BT40-BR40 -> -47 | BW40: FDI1040 | BX40: 46382 | BY40: =+BT40-BX40 -> -47
A41: INSTRUMENTOS | B41: 5155-00-0000-IG-IN-RI-XXX | C41: REQUISICIÓN DE INGENIERÍA CAUDALÍMETROS ROTÁMETROS | E41: =+J41-1 -> 46147 | F41: 46113 | H41: =+F41-E41 -> -34 | J41: =+K41-L41 -> 46148 | K41: =+R41-1 -> 46155 | L41: 7 | M41: =+F41+L41 -> 46120 | O41: =+M41-K41 -> -35 | R41: =+S41-T41 -> 46156 | S41: =+AC41-1 -> 46186 | T41: 30 | U41: =+M41+T41 -> 46150 | W41: =+U41-S41 -> -36 | AC41: =+AD41-AE41 -> 46187 | AD41: =+AJ41-1 -> 46232 | AE41: 45 | AF41: =+IF(V41=0,U41,V41)+AE41 -> 46195 | AH41: =+AF41-AD41 -> -37 | AJ41: =+AK41-AL41 -> 46233 | AK41: =+AV41-1 -> 46253 | AL41: 20 | AM41: =+IF(AG41=0,AF41,AG41)+AL41 -> 46215 | AO41: =+AM41-AK41 -> -38 | AV41: =+AW41-AX41 -> 46254 | AW41: =+BC41-1 -> 46374 | AX41: 120 | AY41: =+IF(AN41=0,AM41,AN41)+AX41 -> 46335 | BA41: =+AY41-AW41 -> -39 | BC41: =+BD41-BE41 -> 46375 | BD41: =+BJ41 -> 46375 | BE41: 0 | BF41: =+IF(AZ41=0,AY41,AZ41)+BE41 -> 46335 | BH41: =+BF41-BD41 -> -40 | BJ41: =+BK41-BL41 -> 46375 | BK41: =+BQ41 -> 46375 | BL41: 0 | BM41: =+IF(BG41=0,BF41,BG41)+BL41 -> 46335 | BO41: =+BM41-BK41 -> -40 | BQ41: =+BR41-BS41 -> 46375 | BR41: =+BX41 -> 46382 | BS41: 7 | BT41: =+IF(BN41=0,BM41,BN41)+BS41 -> 46342 | BV41: =+BT41-BR41 -> -40 | BW41: FDI1040 | BX41: 46382 | BY41: =+BT41-BX41 -> -40
A42: INSTRUMENTOS | B42: 5155-00-0000-IG-IN-RI-XXX | C42: REQUISICIÓN DE INGENIERÍA TRANSMISOR DE NIVEL DP CELL | E42: =+J42-1 -> 46117 | F42: 46078 | H42: =+F42-E42 -> -39 | J42: =+K42-L42 -> 46118 | K42: =+R42-1 -> 46125 | L42: 7 | M42: =+F42+L42 -> 46085 | O42: =+M42-K42 -> -40 | R42: =+S42-T42 -> 46126 | S42: =+AC42-1 -> 46156 | T42: 30 | U42: =+M42+T42 -> 46115 | W42: =+U42-S42 -> -41 | AC42: =+AD42-AE42 -> 46157 | AD42: =+AJ42-1 -> 46202 | AE42: 45 | AF42: =+IF(V42=0,U42,V42)+AE42 -> 46160 | AH42: =+AF42-AD42 -> -42 | AJ42: =+AK42-AL42 -> 46203 | AK42: =+AV42-1 -> 46223 | AL42: 20 | AM42: =+IF(AG42=0,AF42,AG42)+AL42 -> 46180 | AO42: =+AM42-AK42 -> -43 | AV42: =+AW42-AX42 -> 46224 | AW42: =+BC42-1 -> 46374 | AX42: 150 | AY42: =+IF(AN42=0,AM42,AN42)+AX42 -> 46330 | BA42: =+AY42-AW42 -> -44 | BC42: =+BD42-BE42 -> 46375 | BD42: =+BJ42 -> 46375 | BE42: 0 | BF42: =+IF(AZ42=0,AY42,AZ42)+BE42 -> 46330 | BH42: =+BF42-BD42 -> -45 | BJ42: =+BK42-BL42 -> 46375 | BK42: =+BQ42 -> 46375 | BL42: 0 | BM42: =+IF(BG42=0,BF42,BG42)+BL42 -> 46330 | BO42: =+BM42-BK42 -> -45 | BQ42: =+BR42-BS42 -> 46375 | BR42: =+BX42 -> 46382 | BS42: 7 | BT42: =+IF(BN42=0,BM42,BN42)+BS42 -> 46337 | BV42: =+BT42-BR42 -> -45 | BW42: FDI1040 | BX42: 46382 | BY42: =+BT42-BX42 -> -45
A43: INSTRUMENTOS | B43: 5155-00-0000-IG-IN-RI-XXX | C43: REQUISICIÓN DE INGENIERÍA TRANSMISOR DE NIVEL RADAR | E43: =+J43-1 -> 46087 | F43: 46080 | H43: =+F43-E43 -> -7 | J43: =+K43-L43 -> 46088 | K43: =+R43-1 -> 46095 | L43: 7 | M43: =+F43+L43 -> 46087 | O43: =+M43-K43 -> -8 | R43: =+S43-T43 -> 46096 | S43: =+AC43-1 -> 46126 | T43: 30 | U43: =+M43+T43 -> 46117 | W43: =+U43-S43 -> -9 | AC43: =+AD43-AE43 -> 46127 | AD43: =+AJ43-1 -> 46172 | AE43: 45 | AF43: =+IF(V43=0,U43,V43)+AE43 -> 46162 | AH43: =+AF43-AD43 -> -10 | AJ43: =+AK43-AL43 -> 46173 | AK43: =+AV43-1 -> 46193 | AL43: 20 | AM43: =+IF(AG43=0,AF43,AG43)+AL43 -> 46182 | AO43: =+AM43-AK43 -> -11 | AV43: =+AW43-AX43 -> 46194 | AW43: =+BC43-1 -> 46374 | AX43: 180 | AY43: =+IF(AN43=0,AM43,AN43)+AX43 -> 46362 | BA43: =+AY43-AW43 -> -12 | BC43: =+BD43-BE43 -> 46375 | BD43: =+BJ43 -> 46375 | BE43: 0 | BF43: =+IF(AZ43=0,AY43,AZ43)+BE43 -> 46362 | BH43: =+BF43-BD43 -> -13 | BJ43: =+BK43-BL43 -> 46375 | BK43: =+BQ43 -> 46375 | BL43: 0 | BM43: =+IF(BG43=0,BF43,BG43)+BL43 -> 46362 | BO43: =+BM43-BK43 -> -13 | BQ43: =+BR43-BS43 -> 46375 | BR43: =+BX43 -> 46382 | BS43: 7 | BT43: =+IF(BN43=0,BM43,BN43)+BS43 -> 46369 | BV43: =+BT43-BR43 -> -13 | BW43: FDI1040 | BX43: 46382 | BY43: =+BT43-BX43 -> -13
A44: INSTRUMENTOS | B44: 5155-00-0000-IG-IN-RI-XXX | C44: REQUISICIÓN DE INGENIERÍA INDICADOR DE NIVEL MAGNÉTICO | E44: =+J44-1 -> 46117 | F44: 46113 | H44: =+F44-E44 -> -4 | J44: =+K44-L44 -> 46118 | K44: =+R44-1 -> 46125 | L44: 7 | M44: =+F44+L44 -> 46120 | O44: =+M44-K44 -> -5 | R44: =+S44-T44 -> 46126 | S44: =+AC44-1 -> 46156 | T44: 30 | U44: =+M44+T44 -> 46150 | W44: =+U44-S44 -> -6 | AC44: =+AD44-AE44 -> 46157 | AD44: =+AJ44-1 -> 46202 | AE44: 45 | AF44: =+IF(V44=0,U44,V44)+AE44 -> 46195 | AH44: =+AF44-AD44 -> -7 | AJ44: =+AK44-AL44 -> 46203 | AK44: =+AV44-1 -> 46223 | AL44: 20 | AM44: =+IF(AG44=0,AF44,AG44)+AL44 -> 46215 | AO44: =+AM44-AK44 -> -8 | AV44: =+AW44-AX44 -> 46224 | AW44: =+BC44-1 -> 46374 | AX44: 150 | AY44: =+IF(AN44=0,AM44,AN44)+AX44 -> 46365 | BA44: =+AY44-AW44 -> -9 | BC44: =+BD44-BE44 -> 46375 | BD44: =+BJ44 -> 46375 | BE44: 0 | BF44: =+IF(AZ44=0,AY44,AZ44)+BE44 -> 46365 | BH44: =+BF44-BD44 -> -10 | BJ44: =+BK44-BL44 -> 46375 | BK44: =+BQ44 -> 46375 | BL44: 0 | BM44: =+IF(BG44=0,BF44,BG44)+BL44 -> 46365 | BO44: =+BM44-BK44 -> -10 | BQ44: =+BR44-BS44 -> 46375 | BR44: =+BX44 -> 46382 | BS44: 7 | BT44: =+IF(BN44=0,BM44,BN44)+BS44 -> 46372 | BV44: =+BT44-BR44 -> -10 | BW44: FDI1040 | BX44: 46382 | BY44: =+BT44-BX44 -> -10
A45: INSTRUMENTOS | B45: 5155-00-0000-IG-IN-RI-XXX | C45: REQUISICIÓN DE INGENIERÍA TRANSMISOR DE TEMPERATURA | E45: =+J45-1 -> 46117 | F45: 46084 | H45: =+F45-E45 -> -33 | J45: =+K45-L45 -> 46118 | K45: =+R45-1 -> 46125 | L45: 7 | M45: =+F45+L45 -> 46091 | O45: =+M45-K45 -> -34 | R45: =+S45-T45 -> 46126 | S45: =+AC45-1 -> 46156 | T45: 30 | U45: =+M45+T45 -> 46121 | W45: =+U45-S45 -> -35 | AC45: =+AD45-AE45 -> 46157 | AD45: =+AJ45-1 -> 46202 | AE45: 45 | AF45: =+IF(V45=0,U45,V45)+AE45 -> 46166 | AH45: =+AF45-AD45 -> -36 | AJ45: =+AK45-AL45 -> 46203 | AK45: =+AV45-1 -> 46223 | AL45: 20 | AM45: =+IF(AG45=0,AF45,AG45)+AL45 -> 46186 | AO45: =+AM45-AK45 -> -37 | AV45: =+AW45-AX45 -> 46224 | AW45: =+BC45-1 -> 46374 | AX45: 150 | AY45: =+IF(AN45=0,AM45,AN45)+AX45 -> 46336 | BA45: =+AY45-AW45 -> -38 | BC45: =+BD45-BE45 -> 46375 | BD45: =+BJ45 -> 46375 | BE45: 0 | BF45: =+IF(AZ45=0,AY45,AZ45)+BE45 -> 46336 | BH45: =+BF45-BD45 -> -39 | BJ45: =+BK45-BL45 -> 46375 | BK45: =+BQ45 -> 46375 | BL45: 0 | BM45: =+IF(BG45=0,BF45,BG45)+BL45 -> 46336 | BO45: =+BM45-BK45 -> -39 | BQ45: =+BR45-BS45 -> 46375 | BR45: =+BX45 -> 46382 | BS45: 7 | BT45: =+IF(BN45=0,BM45,BN45)+BS45 -> 46343 | BV45: =+BT45-BR45 -> -39 | BW45: FDI1040 | BX45: 46382 | BY45: =+BT45-BX45 -> -39
... A57: INSTRUMENTOS | B57: 5155-00-0000-IG-IN-RI-XXX | C57: REQUISICIÓN DE INGENIERÍA MATERIALES PARA MONTAJE ELÉCTRICO | E57: =+J57-1 -> 46147 | F57: 46295 | H57: =+F57-E57 -> 148 | J57: =+K57-L57 -> 46148 | K57: =+R57-1 -> 46155 | L57: 7 | M57: =+F57+L57 -> 46302 | O57: =+M57-K57 -> 147 | R57: =+S57-T57 -> 46156 | S57: =+AC57-1 -> 46186 | T57: 30 | U57: =+M57+T57 -> 46332 | W57: =+U57-S57 -> 146 | AC57: =+AD57-AE57 -> 46187 | AD57: =+AJ57-1 -> 46232 | AE57: 45 | AF57: =+IF(V57=0,U57,V57)+AE57 -> 46377 | AH57: =+AF57-AD57 -> 145 | AJ57: =+AK57-AL57 -> 46233 | AK57: =+AV57-1 -> 46253 | AL57: 20 | AM57: =+IF(AG57=0,AF57,AG57)+AL57 -> 46397 | AO57: =+AM57-AK57 -> 144 | AV57: =+AW57-AX57 -> 46254 | AW57: =+BC57-1 -> 46374 | AX57: 120 | AY57: =+IF(AN57=0,AM57,AN57)+AX57 -> 46517 | BA57: =+AY57-AW57 -> 143 | BC57: =+BD57-BE57 -> 46375 | BD57: =+BJ57 -> 46375 | BE57: 0 | BF57: =+IF(AZ57=0,AY57,AZ57)+BE57 -> 46517 | BH57: =+BF57-BD57 -> 142 | BJ57: =+BK57-BL57 -> 46375 | BK57: =+BQ57 -> 46375 | BL57: 0 | BM57: =+IF(BG57=0,BF57,BG57)+BL57 -> 46517 | BO57: =+BM57-BK57 -> 142 | BQ57: =+BR57-BS57 -> 46375 | BR57: =+BX57 -> 46382 | BS57: 7 | BT57: =+IF(BN57=0,BM57,BN57)+BS57 -> 46524 | BV57: =+BT57-BR57 -> 142 | BW57: FDI1040 | BX57: 46382 | BY57: =+BT57-BX57 -> 142
A58: INSTRUMENTOS | B58: 5155-00-0000-IG-IN-RI-XXX | C58: REQUISICIÓN DE INGENIERÍA CABLES - Ing al 30% | E58: =+J58-1 -> 46168 | F58: 46073 | H58: =+F58-E58 -> -95 | J58: =+K58-L58 -> 46169 | K58: =+R58-1 -> 46176 | L58: 7 | M58: =+F58+L58 -> 46080 | O58: =+M58-K58 -> -96 | R58: =+S58-T58 -> 46177 | S58: =+AC58-1 -> 46207 | T58: 30 | U58: =+M58+T58 -> 46110 | W58: =+U58-S58 -> -97 | AC58: =+AD58-AE58 -> 46208 | AD58: =+AJ58-1 -> 46253 | AE58: 45 | AF58: =+IF(V58=0,U58,V58)+AE58 -> 46155 | AH58: =+AF58-AD58 -> -98 | AJ58: =+AK58-AL58 -> 46254 | AK58: =+AV58-1 -> 46274 | AL58: 20 | AM58: =+IF(AG58=0,AF58,AG58)+AL58 -> 46175 | AO58: =+AM58-AK58 -> -99 | AV58: =+AW58-AX58 -> 46275 | AW58: =+BC58-1 -> 46395 | AX58: 120 | AY58: =+IF(AN58=0,AM58,AN58)+AX58 -> 46295 | BA58: =+AY58-AW58 -> -100 | BC58: =+BD58-BE58 -> 46396 | BD58: =+BJ58 -> 46396 | BE58: 0 | BF58: =+IF(AZ58=0,AY58,AZ58)+BE58 -> 46295 | BH58: =+BF58-BD58 -> -101 | BJ58: =+BK58-BL58 -> 46396 | BK58: =+BQ58 -> 46396 | BL58: 0 | BM58: =+IF(BG58=0,BF58,BG58)+BL58 -> 46295 | BO58: =+BM58-BK58 -> -101 | BQ58: =+BR58-BS58 -> 46396 | BR58: =+BX58 -> 46403 | BS58: 7 | BT58: =+IF(BN58=0,BM58,BN58)+BS58 -> 46302 | BV58: =+BT58-BR58 -> -101 | BW58: CDI1160 | BX58: 46403 | BY58: =+BT58-BX58 -> -101 | CA58: FN inicio de tendido de cable
A59: INSTRUMENTOS | B59: 5155-00-0000-IG-IN-RI-XXX | C59: REQUISICIÓN DE INGENIERÍA CABLES - Ing al 60% | E59: =+J59-1 -> 46304 | H59: =+F59-E59 -> -46304 | J59: =+K59-L59 -> 46305 | K59: =+R59-1 -> 46312 | L59: 7 | M59: =+F59+L59 -> 7 | O59: =+M59-K59 -> -46305 | R59: =+S59-T59 -> 46313 | S59: =+AC59-1 -> 46343 | T59: 30 | U59: =+M59+T59 -> 37 | W59: =+U59-S59 -> -46306 | AC59: =+AD59-AE59 -> 46344 | AD59: =+AJ59-1 -> 46374 | AE59: 30 | AF59: =+IF(V59=0,U59,V59)+AE59 -> 67 | AH59: =+AF59-AD59 -> -46307 | AJ59: =+AK59-AL59 -> 46375 | AK59: =+AV59-1 -> 46395 | AL59: 20 | AM59: =+IF(AG59=0,AF59,AG59)+AL59 -> 87 | AO59: =+AM59-AK59 -> -46308 | AV59: =+AW59-AX59 -> 46396 | AW59: =+BC59-1 -> 46496 | AX59: 100 | AY59: =+IF(AN59=0,AM59,AN59)+AX59 -> 187 | BA59: =+AY59-AW59 -> -46309 | BC59: =+BD59-BE59 -> 46497 | BD59: =+BJ59 -> 46497 | BE59: 0 | BF59: =+IF(AZ59=0,AY59,AZ59)+BE59 -> 187 | BH59: =+BF59-BD59 -> -46310 | BJ59: =+BK59-BL59 -> 46497 | BK59: =+BQ59 -> 46497 | BL59: 0 | BM59: =+IF(BG59=0,BF59,BG59)+BL59 -> 187 | BO59: =+BM59-BK59 -> -46310 | BQ59: =+BR59-BS59 -> 46497 | BR59: =+BX59 -> 46504 | BS59: 7 | BT59: =+IF(BN59=0,BM59,BN59)+BS59 -> 194 | BV59: =+BT59-BR59 -> -46310 | BW59: CDI1160 | BX59: 46504 | BY59: =+BT59-BX59 -> -46310 | CA59: FN 120 días antes de fin de tendido
A60: INSTRUMENTOS | B60: 5155-00-0000-IG-IN-RI-XXX | C60: REQUISICIÓN DE INGENIERÍA CABLES - Ing al 90% | E60: =+J60-1 -> 46365 | H60: =+F60-E60 -> -46365 | J60: =+K60-L60 -> 46366 | K60: =+R60-1 -> 46373 | L60: 7 | M60: =+F60+L60 -> 7 | O60: =+M60-K60 -> -46366 | R60: =+S60-T60 -> 46374 | S60: =+AC60-1 -> 46404 | T60: 30 | U60: =+M60+T60 -> 37 | W60: =+U60-S60 -> -46367 | AC60: =+AD60-AE60 -> 46405 | AD60: =+AJ60-1 -> 46435 | AE60: 30 | AF60: =+IF(V60=0,U60,V60)+AE60 -> 67 | AH60: =+AF60-AD60 -> -46368 | AJ60: =+AK60-AL60 -> 46436 | AK60: =+AV60-1 -> 46456 | AL60: 20 | AM60: =+IF(AG60=0,AF60,AG60)+AL60 -> 87 | AO60: =+AM60-AK60 -> -46369 | AV60: =+AW60-AX60 -> 46457 | AW60: =+BC60-1 -> 46557 | AX60: 100 | AY60: =+IF(AN60=0,AM60,AN60)+AX60 -> 187 | BA60: =+AY60-AW60 -> -46370 | BC60: =+BD60-BE60 -> 46558 | BD60: =+BJ60 -> 46558 | BE60: 0 | BF60: =+IF(AZ60=0,AY60,AZ60)+BE60 -> 187 | BH60: =+BF60-BD60 -> -46371 | BJ60: =+BK60-BL60 -> 46558 | BK60: =+BQ60 -> 46558 | BL60: 0 | BM60: =+IF(BG60=0,BF60,BG60)+BL60 -> 187 | BO60: =+BM60-BK60 -> -46371 | BQ60: =+BR60-BS60 -> 46558 | BR60: =+BX60 -> 46565 | BS60: 7 | BT60: =+IF(BN60=0,BM60,BN60)+BS60 -> 194 | BV60: =+BT60-BR60 -> -46371 | BW60: CDI1160 | BX60: 46565 | BY60: =+BT60-BX60 -> -46371 | CA60: FN 60 días antes de fin de tendido
A61: INSTRUMENTOS | B61: 5155-00-0000-IG-IN-RI-XXX | C61: REQUISICIÓN DE INGENIERÍA CAJAS | E61: =+J61-1 -> 46167 | F61: 46138 | H61: =+F61-E61 -> -29 | J61: =+K61-L61 -> 46168 | K61: =+R61-1 -> 46175 | L61: 7 | M61: =+F61+L61 -> 46145 | O61: =+M61-K61 -> -30 | R61: =+S61-T61 -> 46176 | S61: =+AC61-1 -> 46206 | T61: 30 | U61: =+M61+T61 -> 46175 | W61: =+U61-S61 -> -31 | AC61: =+AD61-AE61 -> 46207 | AD61: =+AJ61-1 -> 46252 | AE61: 45 | AF61: =+IF(V61=0,U61,V61)+AE61 -> 46220 | AH61: =+AF61-AD61 -> -32 | AJ61: =+AK61-AL61 -> 46253 | AK61: =+AV61-1 -> 46273 | AL61: 20 | AM61: =+IF(AG61=0,AF61,AG61)+AL61 -> 46240 | AO61: =+AM61-AK61 -> -33 | AV61: =+AW61-AX61 -> 46274 | AW61: =+BC61-1 -> 46374 | AX61: 100 | AY61: =+IF(AN61=0,AM61,AN61)+AX61 -> 46340 | BA61: =+AY61-AW61 -> -34 | BC61: =+BD61-BE61 -> 46375 | BD61: =+BJ61 -> 46375 | BE61: 0 | BF61: =+IF(AZ61=0,AY61,AZ61)+BE61 -> 46340 | BH61: =+BF61-BD61 -> -35 | BJ61: =+BK61-BL61 -> 46375 | BK61: =+BQ61 -> 46375 | BL61: 0 | BM61: =+IF(BG61=0,BF61,BG61)+BL61 -> 46340 | BO61: =+BM61-BK61 -> -35 | BQ61: =+BR61-BS61 -> 46375 | BR61: =+BX61 -> 46382 | BS61: 7 | BT61: =+IF(BN61=0,BM61,BN61)+BS61 -> 46347 | BV61: =+BT61-BR61 -> -35 | BW61: FDI1040 | BX61: 46382 | BY61: =+BT61-BX61 -> -35
A62: INSTRUMENTOS | B62: 5155-00-2000-IG-IN-RI-XXX | C62: REQUISICIÓN DE INGENIERÍA VÁLVULAS DE PRESIÓN Y VACÍO | E62: =+J62-1 -> 46117 | F62: 46100 | H62: =+F62-E62 -> -17 | J62: =+K62-L62 -> 46118 | K62: =+R62-1 -> 46125 | L62: 7 | M62: =+F62+L62 -> 46107 | O62: =+M62-K62 -> -18 | R62: =+S62-T62 -> 46126 | S62: =+AC62-1 -> 46156 | T62: 30 | U62: =+M62+T62 -> 46137 | W62: =+U62-S62 -> -19 | AC62: =+AD62-AE62 -> 46157 | AD62: =+AJ62-1 -> 46202 | AE62: 45 | AF62: =+IF(V62=0,U62,V62)+AE62 -> 46182 | AH62: =+AF62-AD62 -> -20 | AJ62: =+AK62-AL62 -> 46203 | AK62: =+AV62-1 -> 46223 | AL62: 20 | AM62: =+IF(AG62=0,AF62,AG62)+AL62 -> 46202 | AO62: =+AM62-AK62 -> -21 | AV62: =+AW62-AX62 -> 46224 | AW62: =+BC62-1 -> 46374 | AX62: 150 | AY62: =+IF(AN62=0,AM62,AN62)+AX62 -> 46352 | BA62: =+AY62-AW62 -> -22 | BC62: =+BD62-BE62 -> 46375 | BD62: =+BJ62 -> 46375 | BE62: 0 | BF62: =+IF(AZ62=0,AY62,AZ62)+BE62 -> 46352 | BH62: =+BF62-BD62 -> -23 | BJ62: =+BK62-BL62 -> 46375 | BK62: =+BQ62 -> 46375 | BL62: 0 | BM62: =+IF(BG62=0,BF62,BG62)+BL62 -> 46352 | BO62: =+BM62-BK62 -> -23 | BQ62: =+BR62-BS62 -> 46375 | BR62: =+BX62 -> 46382 | BS62: 7 | BT62: =+IF(BN62=0,BM62,BN62)+BS62 -> 46359 | BV62: =+BT62-BR62 -> -23 | BW62: FDI1040 | BX62: 46382 | BY62: =+BT62-BX62 -> -23
A63: INSTRUMENTOS | B63: 5155-00-2000-IG-IN-RI-XXX | C63: REQUISICIÓN DE INGENIERÍA DE TAPAS DE EMERGENCIA | E63: =+J63-1 -> 46087 | F63: 46101 | H63: =+F63-E63 -> 14 | J63: =+K63-L63 -> 46088 | K63: =+R63-1 -> 46095 | L63: 7 | M63: =+F63+L63 -> 46108 | O63: =+M63-K63 -> 13 | R63: =+S63-T63 -> 46096 | S63: =+AC63-1 -> 46126 | T63: 30 | U63: =+M63+T63 -> 46138 | W63: =+U63-S63 -> 12 | AC63: =+AD63-AE63 -> 46127 | AD63: =+AJ63-1 -> 46172 | AE63: 45 | AF63: =+IF(V63=0,U63,V63)+AE63 -> 46183 | AH63: =+AF63-AD63 -> 11 | AJ63: =+AK63-AL63 -> 46173 | AK63: =+AV63-1 -> 46193 | AL63: 20 | AM63: =+IF(AG63=0,AF63,AG63)+AL63 -> 46203 | AO63: =+AM63-AK63 -> 10 | AV63: =+AW63-AX63 -> 46194 | AW63: =+BC63-1 -> 46374 | AX63: 180 | AY63: =+IF(AN63=0,AM63,AN63)+AX63 -> 46383 | BA63: =+AY63-AW63 -> 9 | BC63: =+BD63-BE63 -> 46375 | BD63: =+BJ63 -> 46375 | BE63: 0 | BF63: =+IF(AZ63=0,AY63,AZ63)+BE63 -> 46383 | BH63: =+BF63-BD63 -> 8 | BJ63: =+BK63-BL63 -> 46375 | BK63: =+BQ63 -> 46375 | BL63: 0 | BM63: =+IF(BG63=0,BF63,BG63)+BL63 -> 46383 | BO63: =+BM63-BK63 -> 8 | BQ63: =+BR63-BS63 -> 46375 | BR63: =+BX63 -> 46382 | BS63: 7 | BT63: =+IF(BN63=0,BM63,BN63)+BS63 -> 46390 | BV63: =+BT63-BR63 -> 8 | BW63: FDI1040 | BX63: 46382 | BY63: =+BT63-BX63 -> 8
A64: INSTRUMENTOS | B64: 5155-00-2000-IG-IN-RI-XXX | C64: REQUISICIÓN DE INGENIERÍA SKID DE GAS DE BLANKETING | E64: =+J64-1 -> 46117 | F64: 46106 | H64: =+F64-E64 -> -11 | J64: =+K64-L64 -> 46118 | K64: =+R64-1 -> 46125 | L64: 7 | M64: =+F64+L64 -> 46113 | O64: =+M64-K64 -> -12 | R64: =+S64-T64 -> 46126 | S64: =+AC64-1 -> 46156 | T64: 30 | U64: =+M64+T64 -> 46143 | W64: =+U64-S64 -> -13 | AC64: =+AD64-AE64 -> 46157 | AD64: =+AJ64-1 -> 46202 | AE64: 45 | AF64: =+IF(V64=0,U64,V64)+AE64 -> 46188 | AH64: =+AF64-AD64 -> -14 | AJ64: =+AK64-AL64 -> 46203 | AK64: =+AV64-1 -> 46223 | AL64: 20 | AM64: =+IF(AG64=0,AF64,AG64)+AL64 -> 46208 | AO64: =+AM64-AK64 -> -15 | AV64: =+AW64-AX64 -> 46224 | AW64: =+BC64-1 -> 46374 | AX64: 150 | AY64: =+IF(AN64=0,AM64,AN64)+AX64 -> 46358 | BA64: =+AY64-AW64 -> -16 | BC64: =+BD64-BE64 -> 46375 | BD64: =+BJ64 -> 46375 | BE64: 0 | BF64: =+IF(AZ64=0,AY64,AZ64)+BE64 -> 46358 | BH64: =+BF64-BD64 -> -17 | BJ64: =+BK64-BL64 -> 46375 | BK64: =+BQ64 -> 46375 | BL64: 0 | BM64: =+IF(BG64=0,BF64,BG64)+BL64 -> 46358 | BO64: =+BM64-BK64 -> -17 | BQ64: =+BR64-BS64 -> 46375 | BR64: =+BX64 -> 46382 | BS64: 7 | BT64: =+IF(BN64=0,BM64,BN64)+BS64 -> 46365 | BV64: =+BT64-BR64 -> -17 | BW64: FDI1040 | BX64: 46382 | BY64: =+BT64-BX64 -> -17
A65: INSTRUMENTOS | B65: 5155-00-2000-IG-IN-RI-XXX | C65: REQUISICIÓN DE INGENIERÍA TRANSMISOR DE CAUDAL MAGNÉTICO | E65: =+J65-1 -> 46147 | F65: 46062 | H65: =+F65-E65 -> -85 | J65: =+K65-L65 -> 46148 | K65: =+R65-1 -> 46155 | L65: 7 | M65: =+F65+L65 -> 46069 | O65: =+M65-K65 -> -86 | R65: =+S65-T65 -> 46156 | S65: =+AC65-1 -> 46186 | T65: 30 | U65: =+M65+T65 -> 46099 | W65: =+U65-S65 -> -87 | AC65: =+AD65-AE65 -> 46187 | AD65: =+AJ65-1 -> 46232 | AE65: 45 | AF65: =+IF(V65=0,U65,V65)+AE65 -> 46144 | AH65: =+AF65-AD65 -> -88 | AJ65: =+AK65-AL65 -> 46233 | AK65: =+AV65-1 -> 46253 | AL65: 20 | AM65: =+IF(AG65=0,AF65,AG65)+AL65 -> 46164 | AO65: =+AM65-AK65 -> -89 | AV65: =+AW65-AX65 -> 46254 | AW65: =+BC65-1 -> 46374 | AX65: 120 | AY65: =+IF(AN65=0,AM65,AN65)+AX65 -> 46284 | BA65: =+AY65-AW65 -> -90 | BC65: =+BD65-BE65 -> 46375 | BD65: =+BJ65 -> 46375 | BE65: 0 | BF65: =+IF(AZ65=0,AY65,AZ65)+BE65 -> 46284 | BH65: =+BF65-BD65 -> -91 | BJ65: =+BK65-BL65 -> 46375 | BK65: =+BQ65 -> 46375 | BL65: 0 | BM65: =+IF(BG65=0,BF65,BG65)+BL65 -> 46284 | BO65: =+BM65-BK65 -> -91 | BQ65: =+BR65-BS65 -> 46375 | BR65: =+BX65 -> 46382 | BS65: 7 | BT65: =+IF(BN65=0,BM65,BN65)+BS65 -> 46291 | BV65: =+BT65-BR65 -> -91 | BW65: FDI1040 | BX65: 46382 | BY65: =+BT65-BX65 -> -91
A66: INSTRUMENTOS | B66: 5155-00-2000-IG-IN-RI-XXX | C66: REQUISICIÓN DE INGENIERÍA TRANSMISOR DE CAUDAL CORIOLIS | E66: =+J66-1 -> 46147 | F66: 46064 | H66: =+F66-E66 -> -83 | J66: =+K66-L66 -> 46148 | K66: =+R66-1 -> 46155 | L66: 7 | M66: =+F66+L66 -> 46071 | O66: =+M66-K66 -> -84 | R66: =+S66-T66 -> 46156 | S66: =+AC66-1 -> 46186 | T66: 30 | U66: =+M66+T66 -> 46101 | W66: =+U66-S66 -> -85 | AC66: =+AD66-AE66 -> 46187 | AD66: =+AJ66-1 -> 46232 | AE66: 45 | AF66: =+IF(V66=0,U66,V66)+AE66 -> 46146 | AH66: =+AF66-AD66 -> -86 | AJ66: =+AK66-AL66 -> 46233 | AK66: =+AV66-1 -> 46253 | AL66: 20 | AM66: =+IF(AG66=0,AF66,AG66)+AL66 -> 46166 | AO66: =+AM66-AK66 -> -87 | AV66: =+AW66-AX66 -> 46254 | AW66: =+BC66-1 -> 46374 | AX66: 120 | AY66: =+IF(AN66=0,AM66,AN66)+AX66 -> 46286 | BA66: =+AY66-AW66 -> -88 | BC66: =+BD66-BE66 -> 46375 | BD66: =+BJ66 -> 46375 | BE66: 0 | BF66: =+IF(AZ66=0,AY66,AZ66)+BE66 -> 46286 | BH66: =+BF66-BD66 -> -89 | BJ66: =+BK66-BL66 -> 46375 | BK66: =+BQ66 -> 46375 | BL66: 0 | BM66: =+IF(BG66=0,BF66,BG66)+BL66 -> 46286 | BO66: =+BM66-BK66 -> -89 | BQ66: =+BR66-BS66 -> 46375 | BR66: =+BX66 -> 46382 | BS66: 7 | BT66: =+IF(BN66=0,BM66,BN66)+BS66 -> 46293 | BV66: =+BT66-BR66 -> -89 | BW66: FDI1040 | BX66: 46382 | BY66: =+BT66-BX66 -> -89
A67: INSTRUMENTOS | B67: 5155-00-2000-IG-IN-RI-XXX | C67: REQUISICIÓN DE INGENIERÍA TRANSMISOR DE CAUDAL ULTRASÓNICO | E67: =+J67-1 -> 46107 | F67: 46066 | H67: =+F67-E67 -> -41 | J67: =+K67-L67 -> 46108 | K67: =+R67-1 -> 46115 | L67: 7 | M67: =+F67+L67 -> 46073 | O67: =+M67-K67 -> -42 | R67: =+S67-T67 -> 46116 | S67: =+AC67-1 -> 46146 | T67: 30 | U67: =+M67+T67 -> 46103 | W67: =+U67-S67 -> -43 | AC67: =+AD67-AE67 -> 46147 | AD67: =+AJ67-1 -> 46192 | AE67: 45 | AF67: =+IF(V67=0,U67,V67)+AE67 -> 46148 | AH67: =+AF67-AD67 -> -44 | AJ67: =+AK67-AL67 -> 46193 | AK67: =+AV67-1 -> 46213 | AL67: 20 | AM67: =+IF(AG67=0,AF67,AG67)+AL67 -> 46168 | AO67: =+AM67-AK67 -> -45 | AV67: =+AW67-AX67 -> 46214 | AW67: =+BC67-1 -> 46374 | AX67: 160 | AY67: =+IF(AN67=0,AM67,AN67)+AX67 -> 46328 | BA67: =+AY67-AW67 -> -46 | BC67: =+BD67-BE67 -> 46375 | BD67: =+BJ67 -> 46375 | BE67: 0 | BF67: =+IF(AZ67=0,AY67,AZ67)+BE67 -> 46328 | BH67: =+BF67-BD67 -> -47 | BJ67: =+BK67-BL67 -> 46375 | BK67: =+BQ67 -> 46375 | BL67: 0 | BM67: =+IF(BG67=0,BF67,BG67)+BL67 -> 46328 | BO67: =+BM67-BK67 -> -47 | BQ67: =+BR67-BS67 -> 46375 | BR67: =+BX67 -> 46382 | BS67: 7 | BT67: =+IF(BN67=0,BM67,BN67)+BS67 -> 46335 | BV67: =+BT67-BR67 -> -47 | BW67: FDI1040 | BX67: 46382 | BY67: =+BT67-BX67 -> -47
A68: INSTRUMENTOS | B68: 5155-00-2000-IG-IN-RI-XXX | C68: REQUISICIÓN DE INGENIERÍA TRANSMISOR DE CAUDAL MULTIVARIABLE | E68: =+J68-1 -> 46107 | F68: 46108 | H68: =+F68-E68 -> 1 | J68: =+K68-L68 -> 46108 | K68: =+R68-1 -> 46115 | L68: 7 | M68: =+F68+L68 -> 46115 | O68: =+M68-K68 -> 0 | R68: =+S68-T68 -> 46116 | S68: =+AC68-1 -> 46146 | T68: 30 | U68: =+M68+T68 -> 46145 | W68: =+U68-S68 -> -1 | AC68: =+AD68-AE68 -> 46147 | AD68: =+AJ68-1 -> 46192 | AE68: 45 | AF68: =+IF(V68=0,U68,V68)+AE68 -> 46190 | AH68: =+AF68-AD68 -> -2 | AJ68: =+AK68-AL68 -> 46193 | AK68: =+AV68-1 -> 46213 | AL68: 20 | AM68: =+IF(AG68=0,AF68,AG68)+AL68 -> 46210 | AO68: =+AM68-AK68 -> -3 | AV68: =+AW68-AX68 -> 46214 | AW68: =+BC68-1 -> 46374 | AX68: 160 | AY68: =+IF(AN68=0,AM68,AN68)+AX68 -> 46370 | BA68: =+AY68-AW68 -> -4 | BC68: =+BD68-BE68 -> 46375 | BD68: =+BJ68 -> 46375 | BE68: 0 | BF68: =+IF(AZ68=0,AY68,AZ68)+BE68 -> 46370 | BH68: =+BF68-BD68 -> -5 | BJ68: =+BK68-BL68 -> 46375 | BK68: =+BQ68 -> 46375 | BL68: 0 | BM68: =+IF(BG68=0,BF68,BG68)+BL68 -> 46370 | BO68: =+BM68-BK68 -> -5 | BQ68: =+BR68-BS68 -> 46375 | BR68: =+BX68 -> 46382 | BS68: 7 | BT68: =+IF(BN68=0,BM68,BN68)+BS68 -> 46377 | BV68: =+BT68-BR68 -> -5 | BW68: FDI1040 | BX68: 46382 | BY68: =+BT68-BX68 -> -5
A69: INSTRUMENTOS | B69: 5155-00-2000-IG-IN-RI-XXX | C69: REQUISICIÓN DE INGENIERÍA SISTEMA DE CCTV Y WIFI | E69: =+J69-1 -> 46087 | F69: 45930 | H69: =+F69-E69 -> -157 | J69: =+K69-L69 -> 46088 | K69: =+R69-1 -> 46095 | L69: 7 | M69: =+F69+L69 -> 45937 | O69: =+M69-K69 -> -158 | R69: =+S69-T69 -> 46096 | S69: =+AC69-1 -> 46126 | T69: 30 | U69: =+M69+T69 -> 45967 | W69: =+U69-S69 -> -159 | AC69: =+AD69-AE69 -> 46127 | AD69: =+AJ69-1 -> 46172 | AE69: 45 | AF69: =+IF(V69=0,U69,V69)+AE69 -> 46012 | AH69: =+AF69-AD69 -> -160 | AJ69: =+AK69-AL69 -> 46173 | AK69: =+AV69-1 -> 46193 | AL69: 20 | AM69: =+IF(AG69=0,AF69,AG69)+AL69 -> 46032 | AO69: =+AM69-AK69 -> -161 | AV69: =+AW69-AX69 -> 46194 | AW69: =+BC69-1 -> 46374 | AX69: 180 | AY69: =+IF(AN69=0,AM69,AN69)+AX69 -> 46212 | BA69: =+AY69-AW69 -> -162 | BC69: =+BD69-BE69 -> 46375 | BD69: =+BJ69 -> 46375 | BE69: 0 | BF69: =+IF(AZ69=0,AY69,AZ69)+BE69 -> 46212 | BH69: =+BF69-BD69 -> -163 | BJ69: =+BK69-BL69 -> 46375 | BK69: =+BQ69 -> 46375 | BL69: 0 | BM69: =+IF(BG69=0,BF69,BG69)+BL69 -> 46212 | BO69: =+BM69-BK69 -> -163 | BQ69: =+BR69-BS69 -> 46375 | BR69: =+BX69 -> 46382 | BS69: 7 | BT69: =+IF(BN69=0,BM69,BN69)+BS69 -> 46219 | BV69: =+BT69-BR69 -> -163 | BW69: FDI1040 | BX69: 46382 | BY69: =+BT69-BX69 -> -163
A70: INSTRUMENTOS | B70: 5155-00-2000-IG-IN-RI-XXX | C70: REQUISICIÓN DE INGENIERÍA SISTEMA DE CONTROL PCS | E70: =+J70-1 -> 46087 | F70: 45930 | H70: =+F70-E70 -> -157 | J70: =+K70-L70 -> 46088 | K70: =+R70-1 -> 46095 | L70: 7 | M70: =+F70+L70 -> 45937 | O70: =+M70-K70 -> -158 | R70: =+S70-T70 -> 46096 | S70: =+AC70-1 -> 46126 | T70: 30 | U70: =+M70+T70 -> 45967 | W70: =+U70-S70 -> -159 | AC70: =+AD70-AE70 -> 46127 | AD70: =+AJ70-1 -> 46172 | AE70: 45 | AF70: =+IF(V70=0,U70,V70)+AE70 -> 46012 | AH70: =+AF70-AD70 -> -160 | AJ70: =+AK70-AL70 -> 46173 | AK70: =+AV70-1 -> 46193 | AL70: 20 | AM70: =+IF(AG70=0,AF70,AG70)+AL70 -> 46032 | AO70: =+AM70-AK70 -> -161 | AV70: =+AW70-AX70 -> 46194 | AW70: =+BC70-1 -> 46374 | AX70: 180 | AY70: =+IF(AN70=0,AM70,AN70)+AX70 -> 46212 | BA70: =+AY70-AW70 -> -162 | BC70: =+BD70-BE70 -> 46375 | BD70: =+BJ70 -> 46375 | BE70: 0 | BF70: =+IF(AZ70=0,AY70,AZ70)+BE70 -> 46212 | BH70: =+BF70-BD70 -> -163 | BJ70: =+BK70-BL70 -> 46375 | BK70: =+BQ70 -> 46375 | BL70: 0 | BM70: =+IF(BG70=0,BF70,BG70)+BL70 -> 46212 | BO70: =+BM70-BK70 -> -163 | BQ70: =+BR70-BS70 -> 46375 | BR70: =+BX70 -> 46382 | BS70: 7 | BT70: =+IF(BN70=0,BM70,BN70)+BS70 -> 46219 | BV70: =+BT70-BR70 -> -163 | BW70: FDI1040 | BX70: 46382 | BY70: =+BT70-BX70 -> -163
A71: INSTRUMENTOS | B71: 5155-00-2000-IG-IN-RI-XXX | C71: REQUISICIÓN DE INGENIERÍA SISTEMA DE SEGURIDAD SIS | E71: =+J71-1 -> 46087 | F71: 45930 | H71: =+F71-E71 -> -157 | J71: =+K71-L71 -> 46088 | K71: =+R71-1 -> 46095 | L71: 7 | M71: =+F71+L71 -> 45937 | O71: =+M71-K71 -> -158 | R71: =+S71-T71 -> 46096 | S71: =+AC71-1 -> 46126 | T71: 30 | U71: =+M71+T71 -> 45967 | W71: =+U71-S71 -> -159 | AC71: =+AD71-AE71 -> 46127 | AD71: =+AJ71-1 -> 46172 | AE71: 45 | AF71: =+IF(V71=0,U71,V71)+AE71 -> 46012 | AH71: =+AF71-AD71 -> -160 | AJ71: =+AK71-AL71 -> 46173 | AK71: =+AV71-1 -> 46193 | AL71: 20 | AM71: =+IF(AG71=0,AF71,AG71)+AL71 -> 46032 | AO71: =+AM71-AK71 -> -161 | AV71: =+AW71-AX71 -> 46194 | AW71: =+BC71-1 -> 46374 | AX71: 180 | AY71: =+IF(AN71=0,AM71,AN71)+AX71 -> 46212 | BA71: =+AY71-AW71 -> -162 | BC71: =+BD71-BE71 -> 46375 | BD71: =+BJ71 -> 46375 | BE71: 0 | BF71: =+IF(AZ71=0,AY71,AZ71)+BE71 -> 46212 | BH71: =+BF71-BD71 -> -163 | BJ71: =+BK71-BL71 -> 46375 | BK71: =+BQ71 -> 46375 | BL71: 0 | BM71: =+IF(BG71=0,BF71,BG71)+BL71 -> 46212 | BO71: =+BM71-BK71 -> -163 | BQ71: =+BR71-BS71 -> 46375 | BR71: =+BX71 -> 46382 | BS71: 7 | BT71: =+IF(BN71=0,BM71,BN71)+BS71 -> 46219 | BV71: =+BT71-BR71 -> -163 | BW71: FDI1040 | BX71: 46382 | BY71: =+BT71-BX71 -> -163
A72: INSTRUMENTOS | B72: 5155-00-2000-IG-IN-RI-XXX | C72: REQUISICIÓN DE INGENIERÍA INFORME DE VERIFICACIÓN SIL | E72: =+J72-1 -> -295 | F72: 46210 | H72: =+F72-E72 -> 46505 | J72: =+K72-L72 -> -294 | K72: =+R72-1 -> -287 | L72: 7 | M72: =+F72+L72 -> 46217 | O72: =+M72-K72 -> 46504 | R72: =+S72-T72 -> -286 | S72: =+AC72-1 -> -256 | T72: 30 | U72: =+M72+T72 -> 46247 | W72: =+U72-S72 -> 46503 | AC72: =+AD72-AE72 -> -255 | AD72: =+AJ72-1 -> -210 | AE72: 45 | AF72: =+IF(V72=0,U72,V72)+AE72 -> 46292 | AH72: =+AF72-AD72 -> 46502 | AJ72: =+AK72-AL72 -> -209 | AK72: =+AV72-1 -> -189 | AL72: 20 | AM72: =+IF(AG72=0,AF72,AG72)+AL72 -> 46312 | AO72: =+AM72-AK72 -> 46501 | AV72: =+AW72-AX72 -> -188 | AW72: =+BC72-1 -> -8 | AX72: 180 | AY72: =+IF(AN72=0,AM72,AN72)+AX72 -> 46492 | BA72: =+AY72-AW72 -> 46500 | BC72: =+BD72-BE72 -> -7 | BD72: =+BJ72 -> -7 | BE72: 0 | BF72: =+IF(AZ72=0,AY72,AZ72)+BE72 -> 46492 | BH72: =+BF72-BD72 -> 46499 | BJ72: =+BK72-BL72 -> -7 | BK72: =+BQ72 -> -7 | BL72: 0 | BM72: =+IF(BG72=0,BF72,BG72)+BL72 -> 46492 | BO72: =+BM72-BK72 -> 46499 | BQ72: =+BR72-BS72 -> -7 | BR72: =+BX72 -> 0 | BS72: 7 | BT72: =+IF(BN72=0,BM72,BN72)+BS72 -> 46499 | BV72: =+BT72-BR72 -> 46499 | BY72: =+BT72-BX72 -> 46499
A73: INSTRUMENTOS | B73: 5155-00-2000-IG-IN-RI-XXX | C73: REQUISICIÓN DE INGENIERÍA INFORME DE REQUERIMIENTO DE SEGURIDAD SRS | E73: =+J73-1 -> -295 | F73: 46210 | H73: =+F73-E73 -> 46505 | J73: =+K73-L73 -> -294 | K73: =+R73-1 -> -287 | L73: 7 | M73: =+F73+L73 -> 46217 | O73: =+M73-K73 -> 46504 | R73: =+S73-T73 -> -286 | S73: =+AC73-1 -> -256 | T73: 30 | U73: =+M73+T73 -> 46247 | W73: =+U73-S73 -> 46503 | AC73: =+AD73-AE73 -> -255 | AD73: =+AJ73-1 -> -210 | AE73: 45 | AF73: =+IF(V73=0,U73,V73)+AE73 -> 46292 | AH73: =+AF73-AD73 -> 46502 | AJ73: =+AK73-AL73 -> -209 | AK73: =+AV73-1 -> -189 | AL73: 20 | AM73: =+IF(AG73=0,AF73,AG73)+AL73 -> 46312 | AO73: =+AM73-AK73 -> 46501 | AV73: =+AW73-AX73 -> -188 | AW73: =+BC73-1 -> -8 | AX73: 180 | AY73: =+IF(AN73=0,AM73,AN73)+AX73 -> 46492 | BA73: =+AY73-AW73 -> 46500 | BC73: =+BD73-BE73 -> -7 | BD73: =+BJ73 -> -7 | BE73: 0 | BF73: =+IF(AZ73=0,AY73,AZ73)+BE73 -> 46492 | BH73: =+BF73-BD73 -> 46499 | BJ73: =+BK73-BL73 -> -7 | BK73: =+BQ73 -> -7 | BL73: 0 | BM73: =+IF(BG73=0,BF73,BG73)+BL73 -> 46492 | BO73: =+BM73-BK73 -> 46499 | BQ73: =+BR73-BS73 -> -7 | BR73: =+BX73 -> 0 | BS73: 7 | BT73: =+IF(BN73=0,BM73,BN73)+BS73 -> 46499 | BV73: =+BT73-BR73 -> 46499 | BY73: =+BT73-BX73 -> 46499
A74: INSTRUMENTOS | B74: 5155-00-2000-IG-IN-RI-XXX | C74: REQUISICIÓN DE INGENIERÍA TRANSMISOR DE TEMPERATURA | E74: =+J74-1 -> 46117 | F74: 46084 | H74: =+F74-E74 -> -33 | J74: =+K74-L74 -> 46118 | K74: =+R74-1 -> 46125 | L74: 7 | M74: =+F74+L74 -> 46091 | O74: =+M74-K74 -> -34 | R74: =+S74-T74 -> 46126 | S74: =+AC74-1 -> 46156 | T74: 30 | U74: =+M74+T74 -> 46121 | W74: =+U74-S74 -> -35 | AC74: =+AD74-AE74 -> 46157 | AD74: =+AJ74-1 -> 46202 | AE74: 45 | AF74: =+IF(V74=0,U74,V74)+AE74 -> 46166 | AH74: =+AF74-AD74 -> -36 | AJ74: =+AK74-AL74 -> 46203 | AK74: =+AV74-1 -> 46223 | AL74: 20 | AM74: =+IF(AG74=0,AF74,AG74)+AL74 -> 46186 | AO74: =+AM74-AK74 -> -37 | AV74: =+AW74-AX74 -> 46224 | AW74: =+BC74-1 -> 46374 | AX74: 150 | AY74: =+IF(AN74=0,AM74,AN74)+AX74 -> 46336 | BA74: =+AY74-AW74 -> -38 | BC74: =+BD74-BE74 -> 46375 | BD74: =+BJ74 -> 46375 | BE74: 0 | BF74: =+IF(AZ74=0,AY74,AZ74)+BE74 -> 46336 | BH74: =+BF74-BD74 -> -39 | BJ74: =+BK74-BL74 -> 46375 | BK74: =+BQ74 -> 46375 | BL74: 0 | BM74: =+IF(BG74=0,BF74,BG74)+BL74 -> 46336 | BO74: =+BM74-BK74 -> -39 | BQ74: =+BR74-BS74 -> 46375 | BR74: =+BX74 -> 46382 | BS74: 7 | BT74: =+IF(BN74=0,BM74,BN74)+BS74 -> 46343 | BV74: =+BT74-BR74 -> -39 | BW74: FDI1040 | BX74: 46382 | BY74: =+BT74-BX74 -> -39
A75: INSTRUMENTOS | B75: 5155-00-2000-IG-IN-RI-XXX | C75: REQUISICIÓN DE INGENIERÍA MANÓMETROS | E75: =+J75-1 -> 46147 | F75: 46118 | H75: =+F75-E75 -> -29 | J75: =+K75-L75 -> 46148 | K75: =+R75-1 -> 46155 | L75: 7 | M75: =+F75+L75 -> 46125 | O75: =+M75-K75 -> -30 | R75: =+S75-T75 -> 46156 | S75: =+AC75-1 -> 46186 | T75: 30 | U75: =+M75+T75 -> 46155 | W75: =+U75-S75 -> -31 | AC75: =+AD75-AE75 -> 46187 | AD75: =+AJ75-1 -> 46232 | AE75: 45 | AF75: =+IF(V75=0,U75,V75)+AE75 -> 46200 | AH75: =+AF75-AD75 -> -32 | AJ75: =+AK75-AL75 -> 46233 | AK75: =+AV75-1 -> 46253 | AL75: 20 | AM75: =+IF(AG75=0,AF75,AG75)+AL75 -> 46220 | AO75: =+AM75-AK75 -> -33 | AV75: =+AW75-AX75 -> 46254 | AW75: =+BC75-1 -> 46374 | AX75: 120 | AY75: =+IF(AN75=0,AM75,AN75)+AX75 -> 46340 | BA75: =+AY75-AW75 -> -34 | BC75: =+BD75-BE75 -> 46375 | BD75: =+BJ75 -> 46375 | BE75: 0 | BF75: =+IF(AZ75=0,AY75,AZ75)+BE75 -> 46340 | BH75: =+BF75-BD75 -> -35 | BJ75: =+BK75-BL75 -> 46375 | BK75: =+BQ75 -> 46375 | BL75: 0 | BM75: =+IF(BG75=0,BF75,BG75)+BL75 -> 46340 | BO75: =+BM75-BK75 -> -35 | BQ75: =+BR75-BS75 -> 46375 | BR75: =+BX75 -> 46382 | BS75: 7 | BT75: =+IF(BN75=0,BM75,BN75)+BS75 -> 46347 | BV75: =+BT75-BR75 -> -35 | BW75: FDI1040 | BX75: 46382 | BY75: =+BT75-BX75 -> -35
A76: INSTRUMENTOS | B76: 5155-00-2000-IG-IN-RI-XXX | C76: REQUISICIÓN DE INGENIERÍA ROTÁMETROS | E76: =+J76-1 -> 46147 | F76: 46118 | H76: =+F76-E76 -> -29 | J76: =+K76-L76 -> 46148 | K76: =+R76-1 -> 46155 | L76: 7 | M76: =+F76+L76 -> 46125 | O76: =+M76-K76 -> -30 | R76: =+S76-T76 -> 46156 | S76: =+AC76-1 -> 46186 | T76: 30 | U76: =+M76+T76 -> 46155 | W76: =+U76-S76 -> -31 | AC76: =+AD76-AE76 -> 46187 | AD76: =+AJ76-1 -> 46232 | AE76: 45 | AF76: =+IF(V76=0,U76,V76)+AE76 -> 46200 | AH76: =+AF76-AD76 -> -32 | AJ76: =+AK76-AL76 -> 46233 | AK76: =+AV76-1 -> 46253 | AL76: 20 | AM76: =+IF(AG76=0,AF76,AG76)+AL76 -> 46220 | AO76: =+AM76-AK76 -> -33 | AV76: =+AW76-AX76 -> 46254 | AW76: =+BC76-1 -> 46374 | AX76: 120 | AY76: =+IF(AN76=0,AM76,AN76)+AX76 -> 46340 | BA76: =+AY76-AW76 -> -34 | BC76: =+BD76-BE76 -> 46375 | BD76: =+BJ76 -> 46375 | BE76: 0 | BF76: =+IF(AZ76=0,AY76,AZ76)+BE76 -> 46340 | BH76: =+BF76-BD76 -> -35 | BJ76: =+BK76-BL76 -> 46375 | BK76: =+BQ76 -> 46375 | BL76: 0 | BM76: =+IF(BG76=0,BF76,BG76)+BL76 -> 46340 | BO76: =+BM76-BK76 -> -35 | BQ76: =+BR76-BS76 -> 46375 | BR76: =+BX76 -> 46382 | BS76: 7 | BT76: =+IF(BN76=0,BM76,BN76)+BS76 -> 46347 | BV76: =+BT76-BR76 -> -35 | BW76: FDI1040 | BX76: 46382 | BY76: =+BT76-BX76 -> -35
A77: INSTRUMENTOS | B77: 5155-00-2000-IG-IN-RI-XXX | C77: REQUISICIÓN DE INGENIERÍA TOMAMUESTRAS MANUAL | E77: =+J77-1 -> 46147 | F77: 46091 | H77: =+F77-E77 -> -56 | J77: =+K77-L77 -> 46148 | K77: =+R77-1 -> 46155 | L77: 7 | M77: =+F77+L77 -> 46098 | O77: =+M77-K77 -> -57 | R77: =+S77-T77 -> 46156 | S77: =+AC77-1 -> 46186 | T77: 30 | U77: =+M77+T77 -> 46128 | W77: =+U77-S77 -> -58 | AC77: =+AD77-AE77 -> 46187 | AD77: =+AJ77-1 -> 46232 | AE77: 45 | AF77: =+IF(V77=0,U77,V77)+AE77 -> 46173 | AH77: =+AF77-AD77 -> -59 | AJ77: =+AK77-AL77 -> 46233 | AK77: =+AV77-1 -> 46253 | AL77: 20 | AM77: =+IF(AG77=0,AF77,AG77)+AL77 -> 46193 | AO77: =+AM77-AK77 -> -60 | AV77: =+AW77-AX77 -> 46254 | AW77: =+BC77-1 -> 46374 | AX77: 120 | AY77: =+IF(AN77=0,AM77,AN77)+AX77 -> 46313 | BA77: =+AY77-AW77 -> -61 | BC77: =+BD77-BE77 -> 46375 | BD77: =+BJ77 -> 46375 | BE77: 0 | BF77: =+IF(AZ77=0,AY77,AZ77)+BE77 -> 46313 | BH77: =+BF77-BD77 -> -62 | BJ77: =+BK77-BL77 -> 46375 | BK77: =+BQ77 -> 46375 | BL77: 0 | BM77: =+IF(BG77=0,BF77,BG77)+BL77 -> 46313 | BO77: =+BM77-BK77 -> -62 | BQ77: =+BR77-BS77 -> 46375 | BR77: =+BX77 -> 46382 | BS77: 7 | BT77: =+IF(BN77=0,BM77,BN77)+BS77 -> 46320 | BV77: =+BT77-BR77 -> -62 | BW77: FDI1040 | BX77: 46382 | BY77: =+BT77-BX77 -> -62
A78: INSTRUMENTOS | B78: 5155-00-2000-IG-IN-RI-XXX | C78: REQUISICIÓN DE INGENIERÍA TRANSMISOR DE PRESIÓN DIFERENCIAL | E78: =+J78-1 -> 46117 | F78: 46076 | H78: =+F78-E78 -> -41 | J78: =+K78-L78 -> 46118 | K78: =+R78-1 -> 46125 | L78: 7 | M78: =+F78+L78 -> 46083 | O78: =+M78-K78 -> -42 | R78: =+S78-T78 -> 46126 | S78: =+AC78-1 -> 46156 | T78: 30 | U78: =+M78+T78 -> 46113 | W78: =+U78-S78 -> -43 | AC78: =+AD78-AE78 -> 46157 | AD78: =+AJ78-1 -> 46202 | AE78: 45 | AF78: =+IF(V78=0,U78,V78)+AE78 -> 46158 | AH78: =+AF78-AD78 -> -44 | AJ78: =+AK78-AL78 -> 46203 | AK78: =+AV78-1 -> 46223 | AL78: 20 | AM78: =+IF(AG78=0,AF78,AG78)+AL78 -> 46178 | AO78: =+AM78-AK78 -> -45 | AV78: =+AW78-AX78 -> 46224 | AW78: =+BC78-1 -> 46374 | AX78: 150 | AY78: =+IF(AN78=0,AM78,AN78)+AX78 -> 46328 | BA78: =+AY78-AW78 -> -46 | BC78: =+BD78-BE78 -> 46375 | BD78: =+BJ78 -> 46375 | BE78: 0 | BF78: =+IF(AZ78=0,AY78,AZ78)+BE78 -> 46328 | BH78: =+BF78-BD78 -> -47 | BJ78: =+BK78-BL78 -> 46375 | BK78: =+BQ78 -> 46375 | BL78: 0 | BM78: =+IF(BG78=0,BF78,BG78)+BL78 -> 46328 | BO78: =+BM78-BK78 -> -47 | BQ78: =+BR78-BS78 -> 46375 | BR78: =+BX78 -> 46382 | BS78: 7 | BT78: =+IF(BN78=0,BM78,BN78)+BS78 -> 46335 | BV78: =+BT78-BR78 -> -47 | BW78: FDI1040 | BX78: 46382 | BY78: =+BT78-BX78 -> -47
A79: INSTRUMENTOS | B79: 5155-00-2000-IG-IN-RI-XXX | C79: REQUISICIÓN DE INGENIERÍA VÁLVULAS BLOWDOWN Y SHUTDOWN | E79: =+J79-1 -> 46210 | F79: 46007 | H79: =+F79-E79 -> -203 | J79: =+K79-L79 -> 46211 | K79: =+R79-1 -> 46218 | L79: 7 | M79: =+F79+L79 -> 46014 | O79: =+M79-K79 -> -204 | R79: =+S79-T79 -> 46219 | S79: =+AC79-1 -> 46249 | T79: 30 | U79: =+M79+T79 -> 46044 | W79: =+U79-S79 -> -205 | AC79: =+AD79-AE79 -> 46250 | AD79: =+AJ79-1 -> 46295 | AE79: 45 | AF79: =+IF(V79=0,U79,V79)+AE79 -> 46089 | AH79: =+AF79-AD79 -> -206 | AJ79: =+AK79-AL79 -> 46296 | AK79: =+AV79-1 -> 46316 | AL79: 20 | AM79: =+IF(AG79=0,AF79,AG79)+AL79 -> 46109 | AO79: =+AM79-AK79 -> -207 | AV79: =+AW79-AX79 -> 46317 | AW79: =+BC79-1 -> 46557 | AX79: 240 | AY79: =+IF(AN79=0,AM79,AN79)+AX79 -> 46349 | BA79: =+AY79-AW79 -> -208 | BC79: =+BD79-BE79 -> 46558 | BD79: =+BJ79 -> 46558 | BE79: 0 | BF79: =+IF(AZ79=0,AY79,AZ79)+BE79 -> 46349 | BH79: =+BF79-BD79 -> -209 | BJ79: =+BK79-BL79 -> 46558 | BK79: =+BQ79 -> 46558 | BL79: 0 | BM79: =+IF(BG79=0,BF79,BG79)+BL79 -> 46349 | BO79: =+BM79-BK79 -> -209 | BQ79: =+BR79-BS79 -> 46558 | BR79: =+BX79 -> 46565 | BS79: 7 | BT79: =+IF(BN79=0,BM79,BN79)+BS79 -> 46356 | BV79: =+BT79-BR79 -> -209 | BW79: CDI1160 | BX79: 46565 | BY79: =+BT79-BX79 -> -209
A80: INSTRUMENTOS | B80: 5155-00-2000-IG-IN-RI-XXX | C80: REQUISICIÓN DE INGENIERÍA PLACA ORIFICIO Y ORIFICIO DE RESTRICCIÓN | E80: =+J80-1 -> 46177 | F80: 46112 | H80: =+F80-E80 -> -65 | J80: =+K80-L80 -> 46178 | K80: =+R80-1 -> 46185 | L80: 7 | M80: =+F80+L80 -> 46119 | O80: =+M80-K80 -> -66 | R80: =+S80-T80 -> 46186 | S80: =+AC80-1 -> 46216 | T80: 30 | U80: =+M80+T80 -> 46149 | W80: =+U80-S80 -> -67 | AC80: =+AD80-AE80 -> 46217 | AD80: =+AJ80-1 -> 46262 | AE80: 45 | AF80: =+IF(V80=0,U80,V80)+AE80 -> 46194 | AH80: =+AF80-AD80 -> -68 | AJ80: =+AK80-AL80 -> 46263 | AK80: =+AV80-1 -> 46283 | AL80: 20 | AM80: =+IF(AG80=0,AF80,AG80)+AL80 -> 46214 | AO80: =+AM80-AK80 -> -69 | AV80: =+AW80-AX80 -> 46284 | AW80: =+BC80-1 -> 46374 | AX80: 90 | AY80: =+IF(AN80=0,AM80,AN80)+AX80 -> 46304 | BA80: =+AY80-AW80 -> -70 | BC80: =+BD80-BE80 -> 46375 | BD80: =+BJ80 -> 46375 | BE80: 0 | BF80: =+IF(AZ80=0,AY80,AZ80)+BE80 -> 46304 | BH80: =+BF80-BD80 -> -71 | BJ80: =+BK80-BL80 -> 46375 | BK80: =+BQ80 -> 46375 | BL80: 0 | BM80: =+IF(BG80=0,BF80,BG80)+BL80 -> 46304 | BO80: =+BM80-BK80 -> -71 | BQ80: =+BR80-BS80 -> 46375 | BR80: =+BX80 -> 46382 | BS80: 7 | BT80: =+IF(BN80=0,BM80,BN80)+BS80 -> 46311 | BV80: =+BT80-BR80 -> -71 | BW80: FDI1040 | BX80: 46382 | BY80: =+BT80-BX80 -> -71
A81: SERVICIOS | B81: 5155-00-0000-IG-CI-RI-xxx | C81: Estudio de suelos - Requisición de Ingeniería | E81: =+J81-1 -> 46547 | F81: 45905 | H81: =+F81-E81 -> -642 | J81: =+K81-L81 -> 46548 | K81: =+R81-1 -> 46555 | L81: 7 | M81: =+F81+L81 -> 45912 | O81: =+M81-K81 -> -643 | R81: =+S81-T81 -> 46556 | S81: =+AC81-1 -> 46586 | T81: 30 | U81: =+M81+T81 -> 45942 | W81: =+U81-S81 -> -644 | AC81: =+AD81-AE81 -> 46587 | AD81: =+AJ81-1 -> 46632 | AE81: 45 | AF81: =+IF(V81=0,U81,V81)+AE81 -> 45987 | AH81: =+AF81-AD81 -> -645 | AJ81: =+AK81-AL81 -> 46633 | AK81: =+AV81-1 -> 46653 | AL81: 20 | AM81: =+IF(AG81=0,AF81,AG81)+AL81 -> 46007 | AO81: =+AM81-AK81 -> -646 | AV81: =+AW81-AX81 -> 46654 | AW81: =+BC81-1 -> 46714 | AX81: 60 | AY81: =+IF(AN81=0,AM81,AN81)+AX81 -> 46067 | BA81: =+AY81-AW81 -> -647 | BC81: =+BD81-BE81 -> 46715 | BD81: =+BJ81 -> 46715 | BE81: 0 | BF81: =+IF(AZ81=0,AY81,AZ81)+BE81 -> 46067 | BH81: =+BF81-BD81 -> -648 | BJ81: =+BK81-BL81 -> 46715 | BK81: =+BQ81 -> 46715 | BL81: 0 | BM81: =+IF(BG81=0,BF81,BG81)+BL81 -> 46067 | BO81: =+BM81-BK81 -> -648 | BQ81: =+BR81-BS81 -> 46715 | BR81: =+BX81 -> 46722 | BS81: 7 | BT81: =+IF(BN81=0,BM81,BN81)+BS81 -> 46074 | BV81: =+BT81-BR81 -> -648 | BX81: 46722 | BY81: =+BT81-BX81 -> -648
A82: SERVICIOS | B82: 5155-00-0000-IG-CI-RI-xxx | C82: Estudio Georadar - Requisición de Ingeniería | E82: =+J82-1 -> 46547 | F82: 45891 | H82: =+F82-E82 -> -656 | J82: =+K82-L82 -> 46548 | K82: =+R82-1 -> 46555 | L82: 7 | M82: =+F82+L82 -> 45898 | O82: =+M82-K82 -> -657 | R82: =+S82-T82 -> 46556 | S82: =+AC82-1 -> 46586 | T82: 30 | U82: =+M82+T82 -> 45928 | W82: =+U82-S82 -> -658 | AC82: =+AD82-AE82 -> 46587 | AD82: =+AJ82-1 -> 46632 | AE82: 45 | AF82: =+IF(V82=0,U82,V82)+AE82 -> 45973 | AH82: =+AF82-AD82 -> -659 | AJ82: =+AK82-AL82 -> 46633 | AK82: =+AV82-1 -> 46653 | AL82: 20 | AM82: =+IF(AG82=0,AF82,AG82)+AL82 -> 45993 | AO82: =+AM82-AK82 -> -660 | AV82: =+AW82-AX82 -> 46654 | AW82: =+BC82-1 -> 46714 | AX82: 60 | AY82: =+IF(AN82=0,AM82,AN82)+AX82 -> 46053 | BA82: =+AY82-AW82 -> -661 | BC82: =+BD82-BE82 -> 46715 | BD82: =+BJ82 -> 46715 | BE82: 0 | BF82: =+IF(AZ82=0,AY82,AZ82)+BE82 -> 46053 | BH82: =+BF82-BD82 -> -662 | BJ82: =+BK82-BL82 -> 46715 | BK82: =+BQ82 -> 46715 | BL82: 0 | BM82: =+IF(BG82=0,BF82,BG82)+BL82 -> 46053 | BO82: =+BM82-BK82 -> -662 | BQ82: =+BR82-BS82 -> 46715 | BR82: =+BX82 -> 46722 | BS82: 7 | BT82: =+IF(BN82=0,BM82,BN82)+BS82 -> 46060 | BV82: =+BT82-BR82 -> -662 | BX82: 46722 | BY82: =+BT82-BX82 -> -662
A83: SERVICIOS | B83: 5155-00-0000-IG-CI-RI-xxx | C83: Estudio topografico - Requisición de Ingeniería | E83: =+J83-1 -> 46547 | H83: =+F83-E83 -> -46547 | J83: =+K83-L83 -> 46548 | K83: =+R83-1 -> 46555 | L83: 7 | M83: =+F83+L83 -> 7 | O83: =+M83-K83 -> -46548 | R83: =+S83-T83 -> 46556 | S83: =+AC83-1 -> 46586 | T83: 30 | U83: =+M83+T83 -> 37 | W83: =+U83-S83 -> -46549 | AC83: =+AD83-AE83 -> 46587 | AD83: =+AJ83-1 -> 46632 | AE83: 45 | AF83: =+IF(V83=0,U83,V83)+AE83 -> 82 | AH83: =+AF83-AD83 -> -46550 | AJ83: =+AK83-AL83 -> 46633 | AK83: =+AV83-1 -> 46653 | AL83: 20 | AM83: =+IF(AG83=0,AF83,AG83)+AL83 -> 102 | AO83: =+AM83-AK83 -> -46551 | AV83: =+AW83-AX83 -> 46654 | AW83: =+BC83-1 -> 46714 | AX83: 60 | AY83: =+IF(AN83=0,AM83,AN83)+AX83 -> 162 | BA83: =+AY83-AW83 -> -46552 | BC83: =+BD83-BE83 -> 46715 | BD83: =+BJ83 -> 46715 | BE83: 0 | BF83: =+IF(AZ83=0,AY83,AZ83)+BE83 -> 162 | BH83: =+BF83-BD83 -> -46553 | BJ83: =+BK83-BL83 -> 46715 | BK83: =+BQ83 -> 46715 | BL83: 0 | BM83: =+IF(BG83=0,BF83,BG83)+BL83 -> 162 | BO83: =+BM83-BK83 -> -46553 | BQ83: =+BR83-BS83 -> 46715 | BR83: =+BX83 -> 46722 | BS83: 7 | BT83: =+IF(BN83=0,BM83,BN83)+BS83 -> 169 | BV83: =+BT83-BR83 -> -46553 | BX83: 46722 | BY83: =+BT83-BX83 -> -46553
A84: SERVICIOS | B84: 5155-00-0000-IG-ES-RI-xxx | C84: Estructuras metálicas - Requisición de Ingeniería | E84: =+J84-1 -> 45946 | F84: 45938 | H84: =+F84-E84 -> -8 | J84: =+K84-L84 -> 45947 | K84: =+R84-1 -> 45954 | L84: 7 | M84: =+F84+L84 -> 45945 | O84: =+M84-K84 -> -9 | R84: =+S84-T84 -> 45955 | S84: =+AC84-1 -> 45985 | T84: 30 | U84: =+M84+T84 -> 45975 | W84: =+U84-S84 -> -10 | AC84: =+AD84-AE84 -> 45986 | AD84: =+AJ84-1 -> 46016 | AE84: 30 | AF84: =+IF(V84=0,U84,V84)+AE84 -> 46005 | AH84: =+AF84-AD84 -> -11 | AJ84: =+AK84-AL84 -> 46017 | AK84: =+AV84-1 -> 46057 | AL84: 40 | AM84: =+IF(AG84=0,AF84,AG84)+AL84 -> 46045 | AO84: =+AM84-AK84 -> -12 | AV84: =+AW84-AX84 -> 46058 | AW84: =+BC84-1 -> 46058 | AY84: =+IF(AN84=0,AM84,AN84)+AX84 -> 46045 | BA84: =+AY84-AW84 -> -13 | BC84: =+BD84-BE84 -> 46059 | BD84: =+BJ84 -> 46059 | BE84: 0 | BF84: =+IF(AZ84=0,AY84,AZ84)+BE84 -> 46045 | BH84: =+BF84-BD84 -> -14 | BJ84: =+BK84-BL84 -> 46059 | BK84: =+BQ84 -> 46059 | BL84: 0 | BM84: =+IF(BG84=0,BF84,BG84)+BL84 -> 46045 | BO84: =+BM84-BK84 -> -14 | BQ84: =+BR84-BS84 -> 46059 | BR84: =+BX84 -> 46059 | BT84: =+IF(BN84=0,BM84,BN84)+BS84 -> 46045 | BV84: =+BT84-BR84 -> -14 | BW84: GCS1000 | BX84: 46059 | BY84: =+BT84-BX84 -> -14 | CA84: Contratación de EEMM de acuerdo a Crono
A85: SERVICIOS | B85: 5155-00-0000-IG-CI-RI-xxx | C85: PREMOLDEADOS - Requisición de Ingeniería | E85: =+J85-1 -> 45931 | F85: 45952 | H85: =+F85-E85 -> 21 | J85: =+K85-L85 -> 45932 | K85: =+R85-1 -> 45939 | L85: 7 | M85: =+F85+L85 -> 45959 | O85: =+M85-K85 -> 20 | R85: =+S85-T85 -> 45940 | S85: =+AC85-1 -> 45970 | T85: 30 | U85: =+M85+T85 -> 45989 | W85: =+U85-S85 -> 19 | AC85: =+AD85-AE85 -> 45971 | AD85: =+AJ85-1 -> 46016 | AE85: 45 | AF85: =+IF(V85=0,U85,V85)+AE85 -> 46034 | AH85: =+AF85-AD85 -> 18 | AJ85: =+AK85-AL85 -> 46017 | AK85: =+AV85-1 -> 46057 | AL85: 40 | AM85: =+IF(AG85=0,AF85,AG85)+AL85 -> 46074 | AO85: =+AM85-AK85 -> 17 | AV85: =+AW85-AX85 -> 46058 | AW85: =+BC85-1 -> 46058 | AY85: =+IF(AN85=0,AM85,AN85)+AX85 -> 46074 | BA85: =+AY85-AW85 -> 16 | BC85: =+BD85-BE85 -> 46059 | BD85: =+BJ85 -> 46059 | BE85: 0 | BF85: =+IF(AZ85=0,AY85,AZ85)+BE85 -> 46074 | BH85: =+BF85-BD85 -> 15 | BJ85: =+BK85-BL85 -> 46059 | BK85: =+BQ85 -> 46059 | BL85: 0 | BM85: =+IF(BG85=0,BF85,BG85)+BL85 -> 46074 | BO85: =+BM85-BK85 -> 15 | BQ85: =+BR85-BS85 -> 46059 | BR85: =+BX85 -> 46059 | BT85: =+IF(BN85=0,BM85,BN85)+BS85 -> 46074 | BV85: =+BT85-BR85 -> 15 | BW85: GCC1020 | BX85: 46059 | BY85: =+BT85-BX85 -> 15 | CA85: Contratación de premoldeados de acuerdo a Crono
A86: SERVICIOS | B86: 5155-00-0000-IG-SD-RI-001 | C86: RI - ESTUDIO HAZOP/LOPA | E86: =+J86-1 -> 45882 | F86: 45915 | H86: =+F86-E86 -> 33 | J86: =+K86-L86 -> 45883 | K86: =+R86-1 -> 45890 | L86: 7 | M86: =+F86+L86 -> 45922 | O86: =+M86-K86 -> 32 | R86: =+S86-T86 -> 45891 | S86: =+AC86-1 -> 45911 | T86: 20 | U86: =+M86+T86 -> 45942 | W86: =+U86-S86 -> 31 | AC86: =+AD86-AE86 -> 45912 | AD86: =+AJ86-1 -> 45942 | AE86: 30 | AF86: =+IF(V86=0,U86,V86)+AE86 -> 45972 | AH86: =+AF86-AD86 -> 30 | AJ86: =+AK86-AL86 -> 45943 | AK86: =+AV86-1 -> 45953 | AL86: 10 | AM86: =+IF(AG86=0,AF86,AG86)+AL86 -> 45982 | AO86: =+AM86-AK86 -> 29 | AV86: =+AW86-AX86 -> 45954 | AW86: =+BC86-1 -> 45984 | AX86: 30 | AY86: =+IF(AN86=0,AM86,AN86)+AX86 -> 46012 | BA86: =+AY86-AW86 -> 28 | BC86: =+BD86-BE86 -> 45985 | BD86: =+BJ86 -> 45985 | BE86: 0 | BF86: =+IF(AZ86=0,AY86,AZ86)+BE86 -> 46012 | BH86: =+BF86-BD86 -> 27 | BJ86: =+BK86-BL86 -> 45985 | BK86: =+BQ86 -> 45985 | BL86: 0 | BM86: =+IF(BG86=0,BF86,BG86)+BL86 -> 46012 | BO86: =+BM86-BK86 -> 27 | BQ86: =+BR86-BS86 -> 45985 | BR86: =+BX86 -> 45992 | BS86: 7 | BT86: =+IF(BN86=0,BM86,BN86)+BS86 -> 46019 | BV86: =+BT86-BR86 -> 27 | BX86: 45992 | BY86: =+BT86-BX86 -> 27 | CA86: Se toma Fecha de Nececidad de acuerdo a datos del KOM
A87: SERVICIOS | B87: 5155-00-0000-IG-SD-RI-002 | C87: RI - ESTUDIO RADIACIÓN/DISPERSIÓN | E87: =+J87-1 -> 46612 | F87: 45961 | H87: =+F87-E87 -> -651 | J87: =+K87-L87 -> 46613 | K87: =+R87-1 -> 46620 | L87: 7 | M87: =+F87+L87 -> 45968 | O87: =+M87-K87 -> -652 | R87: =+S87-T87 -> 46621 | S87: =+AC87-1 -> 46641 | T87: 20 | U87: =+M87+T87 -> 45988 | W87: =+U87-S87 -> -653 | AC87: =+AD87-AE87 -> 46642 | AD87: =+AJ87-1 -> 46672 | AE87: 30 | AF87: =+IF(V87=0,U87,V87)+AE87 -> 46018 | AH87: =+AF87-AD87 -> -654 | AJ87: =+AK87-AL87 -> 46673 | AK87: =+AV87-1 -> 46683 | AL87: 10 | AM87: =+IF(AG87=0,AF87,AG87)+AL87 -> 46028 | AO87: =+AM87-AK87 -> -655 | AV87: =+AW87-AX87 -> 46684 | AW87: =+BC87-1 -> 46714 | AX87: 30 | AY87: =+IF(AN87=0,AM87,AN87)+AX87 -> 46058 | BA87: =+AY87-AW87 -> -656 | BC87: =+BD87-BE87 -> 46715 | BD87: =+BJ87 -> 46715 | BE87: 0 | BF87: =+IF(AZ87=0,AY87,AZ87)+BE87 -> 46058 | BH87: =+BF87-BD87 -> -657 | BJ87: =+BK87-BL87 -> 46715 | BK87: =+BQ87 -> 46715 | BL87: 0 | BM87: =+IF(BG87=0,BF87,BG87)+BL87 -> 46058 | BO87: =+BM87-BK87 -> -657 | BQ87: =+BR87-BS87 -> 46715 | BR87: =+BX87 -> 46722 | BS87: 7 | BT87: =+IF(BN87=0,BM87,BN87)+BS87 -> 46065 | BV87: =+BT87-BR87 -> -657 | BX87: 46722 | BY87: =+BT87-BX87 -> -657
A88: SED | B88: 5155-00-0000-IG-SD-RI-003 | C88: RI - ELEMENTOS SISTEMA CONTRA INCENDIO | E88: =+J88-1 -> 46117 | F88: 46198 | H88: =+F88-E88 -> 81 | J88: =+K88-L88 -> 46118 | K88: =+R88-1 -> 46125 | L88: 7 | M88: =+F88+L88 -> 46205 | O88: =+M88-K88 -> 80 | R88: =+S88-T88 -> 46126 | S88: =+AC88-1 -> 46156 | T88: 30 | U88: =+M88+T88 -> 46235 | W88: =+U88-S88 -> 79 | AC88: =+AD88-AE88 -> 46157 | AD88: =+AJ88-1 -> 46202 | AE88: 45 | AF88: =+IF(V88=0,U88,V88)+AE88 -> 46280 | AH88: =+AF88-AD88 -> 78 | AJ88: =+AK88-AL88 -> 46203 | AK88: =+AV88-1 -> 46223 | AL88: 20 | AM88: =+IF(AG88=0,AF88,AG88)+AL88 -> 46300 | AO88: =+AM88-AK88 -> 77 | AV88: =+AW88-AX88 -> 46224 | AW88: =+BC88-1 -> 46494 | AX88: 270 | AY88: =+IF(AN88=0,AM88,AN88)+AX88 -> 46570 | BA88: =+AY88-AW88 -> 76 | BC88: =+BD88-BE88 -> 46495 | BD88: =+BJ88 -> 46495 | BE88: 0 | BF88: =+IF(AZ88=0,AY88,AZ88)+BE88 -> 46570 | BH88: =+BF88-BD88 -> 75 | BJ88: =+BK88-BL88 -> 46495 | BK88: =+BQ88 -> 46495 | BL88: 0 | BM88: =+IF(BG88=0,BF88,BG88)+BL88 -> 46570 | BO88: =+BM88-BK88 -> 75 | BQ88: =+BR88-BS88 -> 46495 | BR88: =+BX88 -> 46502 | BS88: 7 | BT88: =+IF(BN88=0,BM88,BN88)+BS88 -> 46577 | BV88: =+BT88-BR88 -> 75 | BX88: 46502 | BY88: =+BT88-BX88 -> 75 | CA88: Asumo 4 meses antes de la primera PEM
A89: MECANICA | B89: 5155-00-1500-IG-EM-RI-001 | C89: RI - RECIPIENTE SEPARADOR EPF | E89: =+J89-1 -> 46016 | F89: 46142 | H89: =+F89-E89 -> 126 | J89: =+K89-L89 -> 46017 | K89: =+R89-1 -> 46024 | L89: 7 | M89: =+F89+L89 -> 46149 | O89: =+M89-K89 -> 125 | R89: =+S89-T89 -> 46025 | S89: =+AC89-1 -> 46055 | T89: 30 | U89: =+M89+T89 -> 46179 | W89: =+U89-S89 -> 124 | AC89: =+AD89-AE89 -> 46056 | AD89: =+AJ89-1 -> 46116 | AE89: 60 | AF89: =+IF(V89=0,U89,V89)+AE89 -> 46239 | AH89: =+AF89-AD89 -> 123 | AJ89: =+AK89-AL89 -> 46117 | AK89: =+AV89-1 -> 46137 | AL89: 20 | AM89: =+IF(AG89=0,AF89,AG89)+AL89 -> 46259 | AO89: =+AM89-AK89 -> 122 | AV89: =+AW89-AX89 -> 46138 | AW89: =+BC89-1 -> 46378 | AX89: 240 | AY89: =+IF(AN89=0,AM89,AN89)+AX89 -> 46499 | BA89: =+AY89-AW89 -> 121 | BC89: =+BD89-BE89 -> 46379 | BD89: =+BJ89 -> 46379 | BE89: 0 | BF89: =+IF(AZ89=0,AY89,AZ89)+BE89 -> 46499 | BH89: =+BF89-BD89 -> 120 | BJ89: =+BK89-BL89 -> 46379 | BK89: =+BQ89 -> 46379 | BL89: 0 | BM89: =+IF(BG89=0,BF89,BG89)+BL89 -> 46499 | BO89: =+BM89-BK89 -> 120 | BQ89: =+BR89-BS89 -> 46379 | BR89: =+BX89 -> 46386 | BS89: 7 | BT89: =+IF(BN89=0,BM89,BN89)+BS89 -> 46506 | BV89: =+BT89-BR89 -> 120 | BW89: FDM1410 | BX89: 46386 | BY89: =+BT89-BX89 -> 120
A90: MECANICA | B90: 5155-00-1800-IG-EM-RI-001 | C90: RI - RECIPIENTES DESGASIFICADORES | E90: =+J90-1 -> 46066 | F90: 46192 | H90: =+F90-E90 -> 126 | J90: =+K90-L90 -> 46067 | K90: =+R90-1 -> 46074 | L90: 7 | M90: =+F90+L90 -> 46199 | O90: =+M90-K90 -> 125 | R90: =+S90-T90 -> 46075 | S90: =+AC90-1 -> 46105 | T90: 30 | U90: =+M90+T90 -> 46229 | W90: =+U90-S90 -> 124 | AC90: =+AD90-AE90 -> 46106 | AD90: =+AJ90-1 -> 46166 | AE90: 60 | AF90: =+IF(V90=0,U90,V90)+AE90 -> 46289 | AH90: =+AF90-AD90 -> 123 | AJ90: =+AK90-AL90 -> 46167 | AK90: =+AV90-1 -> 46187 | AL90: 20 | AM90: =+IF(AG90=0,AF90,AG90)+AL90 -> 46309 | AO90: =+AM90-AK90 -> 122 | AV90: =+AW90-AX90 -> 46188 | AW90: =+BC90-1 -> 46428 | AX90: 240 | AY90: =+IF(AN90=0,AM90,AN90)+AX90 -> 46549 | BA90: =+AY90-AW90 -> 121 | BC90: =+BD90-BE90 -> 46429 | BD90: =+BJ90 -> 46429 | BE90: 0 | BF90: =+IF(AZ90=0,AY90,AZ90)+BE90 -> 46549 | BH90: =+BF90-BD90 -> 120 | BJ90: =+BK90-BL90 -> 46429 | BK90: =+BQ90 -> 46429 | BL90: 0 | BM90: =+IF(BG90=0,BF90,BG90)+BL90 -> 46549 | BO90: =+BM90-BK90 -> 120 | BQ90: =+BR90-BS90 -> 46429 | BR90: =+BX90 -> 46436 | BS90: 7 | BT90: =+IF(BN90=0,BM90,BN90)+BS90 -> 46556 | BV90: =+BT90-BR90 -> 120 | BW90: FDM1420 | BX90: 46436 | BY90: =+BT90-BX90 -> 120
A91: MECANICA | B91: 5155-00-0000-IG-EM-RI-001 | C91: RI - RECIPIENTES | E91: =+J91-1 -> 45961 | F91: 46104 | H91: =+F91-E91 -> 143 | J91: =+K91-L91 -> 45962 | K91: =+R91-1 -> 45969 | L91: 7 | M91: =+F91+L91 -> 46111 | O91: =+M91-K91 -> 142 | R91: =+S91-T91 -> 45970 | S91: =+AC91-1 -> 46000 | T91: 30 | U91: =+M91+T91 -> 46141 | W91: =+U91-S91 -> 141 | AC91: =+AD91-AE91 -> 46001 | AD91: =+AJ91-1 -> 46061 | AE91: 60 | AF91: =+IF(V91=0,U91,V91)+AE91 -> 46201 | AH91: =+AF91-AD91 -> 140 | AJ91: =+AK91-AL91 -> 46062 | AK91: =+AV91-1 -> 46082 | AL91: 20 | AM91: =+IF(AG91=0,AF91,AG91)+AL91 -> 46221 | AO91: =+AM91-AK91 -> 139 | AV91: =+AW91-AX91 -> 46083 | AW91: =+BC91-1 -> 46323 | AX91: 240 | AY91: =+IF(AN91=0,AM91,AN91)+AX91 -> 46461 | BA91: =+AY91-AW91 -> 138 | BC91: =+BD91-BE91 -> 46324 | BD91: =+BJ91 -> 46324 | BE91: 0 | BF91: =+IF(AZ91=0,AY91,AZ91)+BE91 -> 46461 | BH91: =+BF91-BD91 -> 137 | BJ91: =+BK91-BL91 -> 46324 | BK91: =+BQ91 -> 46324 | BL91: 0 | BM91: =+IF(BG91=0,BF91,BG91)+BL91 -> 46461 | BO91: =+BM91-BK91 -> 137 | BQ91: =+BR91-BS91 -> 46324 | BR91: =+BX91 -> 46331 | BS91: 7 | BT91: =+IF(BN91=0,BM91,BN91)+BS91 -> 46468 | BV91: =+BT91-BR91 -> 137 | BW91: FDM1450 | BX91: 46331 | BY91: =+BT91-BX91 -> 137
A92: MECANICA | B92: 5155-00-0000-IG-EM-RI-002 | C92: RI - RECIPIENTES ENTERRADOS | E92: =+J92-1 -> 45976 | F92: 46104 | H92: =+F92-E92 -> 128 | J92: =+K92-L92 -> 45977 | K92: =+R92-1 -> 45984 | L92: 7 | M92: =+F92+L92 -> 46111 | O92: =+M92-K92 -> 127 | R92: =+S92-T92 -> 45985 | S92: =+AC92-1 -> 46015 | T92: 30 | U92: =+M92+T92 -> 46141 | W92: =+U92-S92 -> 126 | AC92: =+AD92-AE92 -> 46016 | AD92: =+AJ92-1 -> 46076 | AE92: 60 | AF92: =+IF(V92=0,U92,V92)+AE92 -> 46201 | AH92: =+AF92-AD92 -> 125 | AJ92: =+AK92-AL92 -> 46077 | AK92: =+AV92-1 -> 46097 | AL92: 20 | AM92: =+IF(AG92=0,AF92,AG92)+AL92 -> 46221 | AO92: =+AM92-AK92 -> 124 | AV92: =+AW92-AX92 -> 46098 | AW92: =+BC92-1 -> 46338 | AX92: 240 | AY92: =+IF(AN92=0,AM92,AN92)+AX92 -> 46461 | BA92: =+AY92-AW92 -> 123 | BC92: =+BD92-BE92 -> 46339 | BD92: =+BJ92 -> 46339 | BE92: 0 | BF92: =+IF(AZ92=0,AY92,AZ92)+BE92 -> 46461 | BH92: =+BF92-BD92 -> 122 | BJ92: =+BK92-BL92 -> 46339 | BK92: =+BQ92 -> 46339 | BL92: 0 | BM92: =+IF(BG92=0,BF92,BG92)+BL92 -> 46461 | BO92: =+BM92-BK92 -> 122 | BQ92: =+BR92-BS92 -> 46339 | BR92: =+BX92 -> 46346 | BS92: 7 | BT92: =+IF(BN92=0,BM92,BN92)+BS92 -> 46468 | BV92: =+BT92-BR92 -> 122 | BW92: FDM1490 | BX92: 46346 | BY92: =+BT92-BX92 -> 122
A93: MECANICA | B93: 5155-00-0000-IG-EM-RI-003 | C93: RI - SUMIDEROS PRFV | E93: =+J93-1 -> 46066 | F93: 46104 | H93: =+F93-E93 -> 38 | J93: =+K93-L93 -> 46067 | K93: =+R93-1 -> 46074 | L93: 7 | M93: =+F93+L93 -> 46111 | O93: =+M93-K93 -> 37 | R93: =+S93-T93 -> 46075 | S93: =+AC93-1 -> 46105 | T93: 30 | U93: =+M93+T93 -> 46141 | W93: =+U93-S93 -> 36 | AC93: =+AD93-AE93 -> 46106 | AD93: =+AJ93-1 -> 46166 | AE93: 60 | AF93: =+IF(V93=0,U93,V93)+AE93 -> 46201 | AH93: =+AF93-AD93 -> 35 | AJ93: =+AK93-AL93 -> 46167 | AK93: =+AV93-1 -> 46187 | AL93: 20 | AM93: =+IF(AG93=0,AF93,AG93)+AL93 -> 46221 | AO93: =+AM93-AK93 -> 34 | AV93: =+AW93-AX93 -> 46188 | AW93: =+BC93-1 -> 46338 | AX93: 150 | AY93: =+IF(AN93=0,AM93,AN93)+AX93 -> 46371 | BA93: =+AY93-AW93 -> 33 | BC93: =+BD93-BE93 -> 46339 | BD93: =+BJ93 -> 46339 | BE93: 0 | BF93: =+IF(AZ93=0,AY93,AZ93)+BE93 -> 46371 | BH93: =+BF93-BD93 -> 32 | BJ93: =+BK93-BL93 -> 46339 | BK93: =+BQ93 -> 46339 | BL93: 0 | BM93: =+IF(BG93=0,BF93,BG93)+BL93 -> 46371 | BO93: =+BM93-BK93 -> 32 | BQ93: =+BR93-BS93 -> 46339 | BR93: =+BX93 -> 46346 | BS93: 7 | BT93: =+IF(BN93=0,BM93,BN93)+BS93 -> 46378 | BV93: =+BT93-BR93 -> 32 | BW93: FDM1490 | BX93: 46346 | BY93: =+BT93-BX93 -> 32
A94: MECANICA | B94: 5155-00-2100-IG-EM-RI-001 | C94: RI - AEROENFRIADORES | E94: =+J94-1 -> 45966 | F94: 46104 | H94: =+F94-E94 -> 138 | J94: =+K94-L94 -> 45967 | K94: =+R94-1 -> 45974 | L94: 7 | M94: =+F94+L94 -> 46111 | O94: =+M94-K94 -> 137 | R94: =+S94-T94 -> 45975 | S94: =+AC94-1 -> 46005 | T94: 30 | U94: =+M94+T94 -> 46141 | W94: =+U94-S94 -> 136 | AC94: =+AD94-AE94 -> 46006 | AD94: =+AJ94-1 -> 46066 | AE94: 60 | AF94: =+IF(V94=0,U94,V94)+AE94 -> 46201 | AH94: =+AF94-AD94 -> 135 | AJ94: =+AK94-AL94 -> 46067 | AK94: =+AV94-1 -> 46087 | AL94: 20 | AM94: =+IF(AG94=0,AF94,AG94)+AL94 -> 46221 | AO94: =+AM94-AK94 -> 134 | AV94: =+AW94-AX94 -> 46088 | AW94: =+BC94-1 -> 46338 | AX94: 250 | AY94: =+IF(AN94=0,AM94,AN94)+AX94 -> 46471 | BA94: =+AY94-AW94 -> 133 | BC94: =+BD94-BE94 -> 46339 | BD94: =+BJ94 -> 46339 | BE94: 0 | BF94: =+IF(AZ94=0,AY94,AZ94)+BE94 -> 46471 | BH94: =+BF94-BD94 -> 132 | BJ94: =+BK94-BL94 -> 46339 | BK94: =+BQ94 -> 46339 | BL94: 0 | BM94: =+IF(BG94=0,BF94,BG94)+BL94 -> 46471 | BO94: =+BM94-BK94 -> 132 | BQ94: =+BR94-BS94 -> 46339 | BR94: =+BX94 -> 46346 | BS94: 7 | BT94: =+IF(BN94=0,BM94,BN94)+BS94 -> 46478 | BV94: =+BT94-BR94 -> 132 | BW94: FDM1460 | BX94: 46346 | BY94: =+BT94-BX94 -> 132 | CA94: FN del Trim Cooler
A95: MECANICA | B95: 5155-00-1500-IG-EM-RI-002 | C95: RI - CALENTADORES STD. | E95: =+J95-1 -> 46066 | F95: 46192 | H95: =+F95-E95 -> 126 | J95: =+K95-L95 -> 46067 | K95: =+R95-1 -> 46074 | L95: 7 | M95: =+F95+L95 -> 46199 | O95: =+M95-K95 -> 125 | R95: =+S95-T95 -> 46075 | S95: =+AC95-1 -> 46105 | T95: 30 | U95: =+M95+T95 -> 46229 | W95: =+U95-S95 -> 124 | AC95: =+AD95-AE95 -> 46106 | AD95: =+AJ95-1 -> 46166 | AE95: 60 | AF95: =+IF(V95=0,U95,V95)+AE95 -> 46289 | AH95: =+AF95-AD95 -> 123 | AJ95: =+AK95-AL95 -> 46167 | AK95: =+AV95-1 -> 46187 | AL95: 20 | AM95: =+IF(AG95=0,AF95,AG95)+AL95 -> 46309 | AO95: =+AM95-AK95 -> 122 | AV95: =+AW95-AX95 -> 46188 | AW95: =+BC95-1 -> 46438 | AX95: 250 | AY95: =+IF(AN95=0,AM95,AN95)+AX95 -> 46559 | BA95: =+AY95-AW95 -> 121 | BC95: =+BD95-BE95 -> 46439 | BD95: =+BJ95 -> 46439 | BE95: 0 | BF95: =+IF(AZ95=0,AY95,AZ95)+BE95 -> 46559 | BH95: =+BF95-BD95 -> 120 | BJ95: =+BK95-BL95 -> 46439 | BK95: =+BQ95 -> 46439 | BL95: 0 | BM95: =+IF(BG95=0,BF95,BG95)+BL95 -> 46559 | BO95: =+BM95-BK95 -> 120 | BQ95: =+BR95-BS95 -> 46439 | BR95: =+BX95 -> 46446 | BS95: 7 | BT95: =+IF(BN95=0,BM95,BN95)+BS95 -> 46566 | BV95: =+BT95-BR95 -> 120 | BW95: FDM1430 | BX95: 46446 | BY95: =+BT95-BX95 -> 120
A96: MECANICA | B96: 5155-00-0600-IG-EM-RI-001 | C96: RI - CALENTADORES KOD | E96: =+J96-1 -> 46066 | F96: 46192 | H96: =+F96-E96 -> 126 | J96: =+K96-L96 -> 46067 | K96: =+R96-1 -> 46074 | L96: 7 | M96: =+F96+L96 -> 46199 | O96: =+M96-K96 -> 125 | R96: =+S96-T96 -> 46075 | S96: =+AC96-1 -> 46105 | T96: 30 | U96: =+M96+T96 -> 46229 | W96: =+U96-S96 -> 124 | AC96: =+AD96-AE96 -> 46106 | AD96: =+AJ96-1 -> 46166 | AE96: 60 | AF96: =+IF(V96=0,U96,V96)+AE96 -> 46289 | AH96: =+AF96-AD96 -> 123 | AJ96: =+AK96-AL96 -> 46167 | AK96: =+AV96-1 -> 46187 | AL96: 20 | AM96: =+IF(AG96=0,AF96,AG96)+AL96 -> 46309 | AO96: =+AM96-AK96 -> 122 | AV96: =+AW96-AX96 -> 46188 | AW96: =+BC96-1 -> 46438 | AX96: 250 | AY96: =+IF(AN96=0,AM96,AN96)+AX96 -> 46559 | BA96: =+AY96-AW96 -> 121 | BC96: =+BD96-BE96 -> 46439 | BD96: =+BJ96 -> 46439 | BE96: 0 | BF96: =+IF(AZ96=0,AY96,AZ96)+BE96 -> 46559 | BH96: =+BF96-BD96 -> 120 | BJ96: =+BK96-BL96 -> 46439 | BK96: =+BQ96 -> 46439 | BL96: 0 | BM96: =+IF(BG96=0,BF96,BG96)+BL96 -> 46559 | BO96: =+BM96-BK96 -> 120 | BQ96: =+BR96-BS96 -> 46439 | BR96: =+BX96 -> 46446 | BS96: 7 | BT96: =+IF(BN96=0,BM96,BN96)+BS96 -> 46566 | BV96: =+BT96-BR96 -> 120 | BW96: FDM1430 | BX96: 46446 | BY96: =+BT96-BX96 -> 120
A97: MECANICA | B97: 5155-00-0000-IG-EM-RI-004 | C97: RI - FILTROS | E97: =+J97-1 -> 46048 | F97: 46216 | H97: =+F97-E97 -> 168 | J97: =+K97-L97 -> 46049 | K97: =+R97-1 -> 46056 | L97: 7 | M97: =+F97+L97 -> 46223 | O97: =+M97-K97 -> 167 | R97: =+S97-T97 -> 46057 | S97: =+AC97-1 -> 46087 | T97: 30 | U97: =+M97+T97 -> 46253 | W97: =+U97-S97 -> 166 | AC97: =+AD97-AE97 -> 46088 | AD97: =+AJ97-1 -> 46148 | AE97: 60 | AF97: =+IF(V97=0,U97,V97)+AE97 -> 46313 | AH97: =+AF97-AD97 -> 165 | AJ97: =+AK97-AL97 -> 46149 | AK97: =+AV97-1 -> 46169 | AL97: 20 | AM97: =+IF(AG97=0,AF97,AG97)+AL97 -> 46333 | AO97: =+AM97-AK97 -> 164 | AV97: =+AW97-AX97 -> 46170 | AW97: =+BC97-1 -> 46420 | AX97: 250 | AY97: =+IF(AN97=0,AM97,AN97)+AX97 -> 46583 | BA97: =+AY97-AW97 -> 163 | BC97: =+BD97-BE97 -> 46421 | BD97: =+BJ97 -> 46421 | BE97: 0 | BF97: =+IF(AZ97=0,AY97,AZ97)+BE97 -> 46583 | BH97: =+BF97-BD97 -> 162 | BJ97: =+BK97-BL97 -> 46421 | BK97: =+BQ97 -> 46421 | BL97: 0 | BM97: =+IF(BG97=0,BF97,BG97)+BL97 -> 46583 | BO97: =+BM97-BK97 -> 162 | BQ97: =+BR97-BS97 -> 46421 | BR97: =+BX97 -> 46428 | BS97: 7 | BT97: =+IF(BN97=0,BM97,BN97)+BS97 -> 46590 | BV97: =+BT97-BR97 -> 162 | BW97: FDM1310 | BX97: 46428 | BY97: =+BT97-BX97 -> 162
A98: SERVICIOS | B98: 5155-00-0000-IG-EM-RI-005 | C98: RI - TANQUES MAYORES API 650 | E98: =+J98-1 -> 45900 | F98: 46010 | H98: =+F98-E98 -> 110 | J98: =+K98-L98 -> 45901 | K98: =+R98-1 -> 45908 | L98: 7 | M98: =+F98+L98 -> 46017 | O98: =+M98-K98 -> 109 | R98: =+S98-T98 -> 45909 | S98: =+AC98-1 -> 45939 | T98: 30 | U98: =+M98+T98 -> 46047 | W98: =+U98-S98 -> 108 | AC98: =+AD98-AE98 -> 45940 | AD98: =+AJ98-1 -> 46000 | AE98: 60 | AF98: =+IF(V98=0,U98,V98)+AE98 -> 46107 | AH98: =+AF98-AD98 -> 107 | AJ98: =+AK98-AL98 -> 46001 | AK98: =+AV98-1 -> 46041 | AL98: 40 | AM98: =+IF(AG98=0,AF98,AG98)+AL98 -> 46147 | AO98: =+AM98-AK98 -> 106 | AV98: =+AW98-AX98 -> 46042 | AW98: =+BC98-1 -> 46552 | AX98: 510 | AY98: =+IF(AN98=0,AM98,AN98)+AX98 -> 46657 | BA98: =+AY98-AW98 -> 105 | BC98: =+BD98-BE98 -> 46553 | BD98: =+BJ98 -> 46553 | BE98: 0 | BF98: =+IF(AZ98=0,AY98,AZ98)+BE98 -> 46657 | BH98: =+BF98-BD98 -> 104 | BJ98: =+BK98-BL98 -> 46553 | BK98: =+BQ98 -> 46553 | BL98: 0 | BM98: =+IF(BG98=0,BF98,BG98)+BL98 -> 46657 | BO98: =+BM98-BK98 -> 104 | BQ98: =+BR98-BS98 -> 46553 | BR98: =+BX98 -> 46553 | BT98: =+IF(BN98=0,BM98,BN98)+BS98 -> 46657 | BV98: =+BT98-BR98 -> 104 | BW98: CDM01000 | BX98: 46553 | BY98: =+BT98-BX98 -> 104 | CA98: Fecha de fin de montaje de tanques
A99: MECANICA | B99: 5155-00-0000-IG-EM-RI-006 | C99: RI - TANQUES API 620 - Se asumen 250 días de fabricación + 30 de transporte. | E99: =+J99-1 -> 46009 | F99: 46120 | H99: =+F99-E99 -> 111 | J99: =+K99-L99 -> 46010 | K99: =+R99-1 -> 46017 | L99: 7 | M99: =+F99+L99 -> 46127 | O99: =+M99-K99 -> 110 | R99: =+S99-T99 -> 46018 | S99: =+AC99-1 -> 46048 | T99: 30 | U99: =+M99+T99 -> 46157 | W99: =+U99-S99 -> 109 | AC99: =+AD99-AE99 -> 46049 | AD99: =+AJ99-1 -> 46109 | AE99: 60 | AF99: =+IF(V99=0,U99,V99)+AE99 -> 46217 | AH99: =+AF99-AD99 -> 108 | AJ99: =+AK99-AL99 -> 46110 | AK99: =+AV99-1 -> 46130 | AL99: 20 | AM99: =+IF(AG99=0,AF99,AG99)+AL99 -> 46237 | AO99: =+AM99-AK99 -> 107 | AV99: =+AW99-AX99 -> 46131 | AW99: =+BC99-1 -> 46381 | AX99: 250 | AY99: =+IF(AN99=0,AM99,AN99)+AX99 -> 46487 | BA99: =+AY99-AW99 -> 106 | BC99: =+BD99-BE99 -> 46382 | BD99: =+BJ99 -> 46382 | BE99: 0 | BF99: =+IF(AZ99=0,AY99,AZ99)+BE99 -> 46487 | BH99: =+BF99-BD99 -> 105 | BJ99: =+BK99-BL99 -> 46382 | BK99: =+BQ99 -> 46382 | BL99: 0 | BM99: =+IF(BG99=0,BF99,BG99)+BL99 -> 46487 | BO99: =+BM99-BK99 -> 105 | BQ99: =+BR99-BS99 -> 46382 | BR99: =+BX99 -> 46412 | BS99: 30 | BT99: =+IF(BN99=0,BM99,BN99)+BS99 -> 46517 | BV99: =+BT99-BR99 -> 105 | BW99: FDM1060 | BX99: 46412 | BY99: =+BT99-BX99 -> 105
A100: MECANICA | B100: 5155-00-0000-IG-EM-RI-007 | C100: RI - TANQUES MENORES API 12F - Idem API menores 620 | E100: =+J100-1 -> 46009 | F100: 46120 | H100: =+F100-E100 -> 111 | J100: =+K100-L100 -> 46010 | K100: =+R100-1 -> 46017 | L100: 7 | M100: =+F100+L100 -> 46127 | O100: =+M100-K100 -> 110 | R100: =+S100-T100 -> 46018 | S100: =+AC100-1 -> 46048 | T100: 30 | U100: =+M100+T100 -> 46157 | W100: =+U100-S100 -> 109 | AC100: =+AD100-AE100 -> 46049 | AD100: =+AJ100-1 -> 46109 | AE100: 60 | AF100: =+IF(V100=0,U100,V100)+AE100 -> 46217 | AH100: =+AF100-AD100 -> 108 | AJ100: =+AK100-AL100 -> 46110 | AK100: =+AV100-1 -> 46130 | AL100: 20 | AM100: =+IF(AG100=0,AF100,AG100)+AL100 -> 46237 | AO100: =+AM100-AK100 -> 107 | AV100: =+AW100-AX100 -> 46131 | AW100: =+BC100-1 -> 46381 | AX100: 250 | AY100: =+IF(AN100=0,AM100,AN100)+AX100 -> 46487 | BA100: =+AY100-AW100 -> 106 | BC100: =+BD100-BE100 -> 46382 | BD100: =+BJ100 -> 46382 | BE100: 0 | BF100: =+IF(AZ100=0,AY100,AZ100)+BE100 -> 46487 | BH100: =+BF100-BD100 -> 105 | BJ100: =+BK100-BL100 -> 46382 | BK100: =+BQ100 -> 46382 | BL100: 0 | BM100: =+IF(BG100=0,BF100,BG100)+BL100 -> 46487 | BO100: =+BM100-BK100 -> 105 | BQ100: =+BR100-BS100 -> 46382 | BR100: =+BX100 -> 46412 | BS100: 30 | BT100: =+IF(BN100=0,BM100,BN100)+BS100 -> 46517 | BV100: =+BT100-BR100 -> 105 | BW100: FDM1060 | BX100: 46412 | BY100: =+BT100-BX100 -> 105
A101: MECANICA | B101: 5155-00-1500-IG-EM-RI-003 | C101: RI - TANQUES DE ACEITE | E101: =+J101-1 -> 46072 | F101: 46230 | H101: =+F101-E101 -> 158 | J101: =+K101-L101 -> 46073 | K101: =+R101-1 -> 46080 | L101: 7 | M101: =+F101+L101 -> 46237 | O101: =+M101-K101 -> 157 | R101: =+S101-T101 -> 46081 | S101: =+AC101-1 -> 46111 | T101: 30 | U101: =+M101+T101 -> 46267 | W101: =+U101-S101 -> 156 | AC101: =+AD101-AE101 -> 46112 | AD101: =+AJ101-1 -> 46172 | AE101: 60 | AF101: =+IF(V101=0,U101,V101)+AE101 -> 46327 | AH101: =+AF101-AD101 -> 155 | AJ101: =+AK101-AL101 -> 46173 | AK101: =+AV101-1 -> 46193 | AL101: 20 | AM101: =+IF(AG101=0,AF101,AG101)+AL101 -> 46347 | AO101: =+AM101-AK101 -> 154 | AV101: =+AW101-AX101 -> 46194 | AW101: =+BC101-1 -> 46404 | AX101: 210 | AY101: =+IF(AN101=0,AM101,AN101)+AX101 -> 46557 | BA101: =+AY101-AW101 -> 153 | BC101: =+BD101-BE101 -> 46405 | BD101: =+BJ101 -> 46405 | BE101: 0 | BF101: =+IF(AZ101=0,AY101,AZ101)+BE101 -> 46557 | BH101: =+BF101-BD101 -> 152 | BJ101: =+BK101-BL101 -> 46405 | BK101: =+BQ101 -> 46405 | BL101: 0 | BM101: =+IF(BG101=0,BF101,BG101)+BL101 -> 46557 | BO101: =+BM101-BK101 -> 152 | BQ101: =+BR101-BS101 -> 46405 | BR101: =+BX101 -> 46412 | BS101: 7 | BT101: =+IF(BN101=0,BM101,BN101)+BS101 -> 46564 | BV101: =+BT101-BR101 -> 152 | BW101: FDM1060 | BX101: 46412 | BY101: =+BT101-BX101 -> 152
A102: MECANICA | B102: 5155-00-1600-IG-EM-RI-001 | C102: RI - TANQUES DE TRANSFERENCIA DE GLICOL | E102: =+J102-1 -> 46142 | F102: 46230 | H102: =+F102-E102 -> 88 | J102: =+K102-L102 -> 46143 | K102: =+R102-1 -> 46150 | L102: 7 | M102: =+F102+L102 -> 46237 | O102: =+M102-K102 -> 87 | R102: =+S102-T102 -> 46151 | S102: =+AC102-1 -> 46181 | T102: 30 | U102: =+M102+T102 -> 46267 | W102: =+U102-S102 -> 86 | AC102: =+AD102-AE102 -> 46182 | AD102: =+AJ102-1 -> 46242 | AE102: 60 | AF102: =+IF(V102=0,U102,V102)+AE102 -> 46327 | AH102: =+AF102-AD102 -> 85 | AJ102: =+AK102-AL102 -> 46243 | AK102: =+AV102-1 -> 46263 | AL102: 20 | AM102: =+IF(AG102=0,AF102,AG102)+AL102 -> 46347 | AO102: =+AM102-AK102 -> 84 | AV102: =+AW102-AX102 -> 46264 | AW102: =+BC102-1 -> 46414 | AX102: 150 | AY102: =+IF(AN102=0,AM102,AN102)+AX102 -> 46497 | BA102: =+AY102-AW102 -> 83 | BC102: =+BD102-BE102 -> 46415 | BD102: =+BJ102 -> 46415 | BE102: 0 | BF102: =+IF(AZ102=0,AY102,AZ102)+BE102 -> 46497 | BH102: =+BF102-BD102 -> 82 | BJ102: =+BK102-BL102 -> 46415 | BK102: =+BQ102 -> 46415 | BL102: 0 | BM102: =+IF(BG102=0,BF102,BG102)+BL102 -> 46497 | BO102: =+BM102-BK102 -> 82 | BQ102: =+BR102-BS102 -> 46415 | BR102: =+BX102 -> 46422 | BS102: 7 | BT102: =+IF(BN102=0,BM102,BN102)+BS102 -> 46504 | BV102: =+BT102-BR102 -> 82 | BW102: FDM1090 | BX102: 46422 | BY102: =+BT102-BX102 -> 82
A103: MECANICA | B103: 5155-00-1500-IG-EM-RI-004 | C103: RI - TANQUES DE ESPUMA SCI | E103: =+J103-1 -> 46192 | F103: 46230 | H103: =+F103-E103 -> 38 | J103: =+K103-L103 -> 46193 | K103: =+R103-1 -> 46200 | L103: 7 | M103: =+F103+L103 -> 46237 | O103: =+M103-K103 -> 37 | R103: =+S103-T103 -> 46201 | S103: =+AC103-1 -> 46231 | T103: 30 | U103: =+M103+T103 -> 46267 | W103: =+U103-S103 -> 36 | AC103: =+AD103-AE103 -> 46232 | AD103: =+AJ103-1 -> 46292 | AE103: 60 | AF103: =+IF(V103=0,U103,V103)+AE103 -> 46327 | AH103: =+AF103-AD103 -> 35 | AJ103: =+AK103-AL103 -> 46293 | AK103: =+AV103-1 -> 46313 | AL103: 20 | AM103: =+IF(AG103=0,AF103,AG103)+AL103 -> 46347 | AO103: =+AM103-AK103 -> 34 | AV103: =+AW103-AX103 -> 46314 | AW103: =+BC103-1 -> 46404 | AX103: 90 | AY103: =+IF(AN103=0,AM103,AN103)+AX103 -> 46437 | BA103: =+AY103-AW103 -> 33 | BC103: =+BD103-BE103 -> 46405 | BD103: =+BJ103 -> 46405 | BE103: 0 | BF103: =+IF(AZ103=0,AY103,AZ103)+BE103 -> 46437 | BH103: =+BF103-BD103 -> 32 | BJ103: =+BK103-BL103 -> 46405 | BK103: =+BQ103 -> 46405 | BL103: 0 | BM103: =+IF(BG103=0,BF103,BG103)+BL103 -> 46437 | BO103: =+BM103-BK103 -> 32 | BQ103: =+BR103-BS103 -> 46405 | BR103: =+BX103 -> 46412 | BS103: 7 | BT103: =+IF(BN103=0,BM103,BN103)+BS103 -> 46444 | BV103: =+BT103-BR103 -> 32 | BW103: FDM1060 | BX103: 46412 | BY103: =+BT103-BX103 -> 32
A104: MECANICA | B104: 5155-00-1700-IG-EM-RI-001 | C104: RI - BOMBAS CENTRIFUGAS API | E104: =+J104-1 -> 45892 | F104: 46073 | H104: =+F104-E104 -> 181 | J104: =+K104-L104 -> 45893 | K104: =+R104-1 -> 45900 | L104: 7 | M104: =+F104+L104 -> 46080 | O104: =+M104-K104 -> 180 | R104: =+S104-T104 -> 45901 | S104: =+AC104-1 -> 45931 | T104: 30 | U104: =+M104+T104 -> 46110 | W104: =+U104-S104 -> 179 | AC104: =+AD104-AE104 -> 45932 | AD104: =+AJ104-1 -> 45992 | AE104: 60 | AF104: =+IF(V104=0,U104,V104)+AE104 -> 46170 | AH104: =+AF104-AD104 -> 178 | AJ104: =+AK104-AL104 -> 45993 | AK104: =+AV104-1 -> 46013 | AL104: 20 | AM104: =+IF(AG104=0,AF104,AG104)+AL104 -> 46190 | AO104: =+AM104-AK104 -> 177 | AV104: =+AW104-AX104 -> 46014 | AW104: =+BC104-1 -> 46374 | AX104: 360 | AY104: =+IF(AN104=0,AM104,AN104)+AX104 -> 46550 | BA104: =+AY104-AW104 -> 176 | BC104: =+BD104-BE104 -> 46375 | BD104: =+BJ104 -> 46375 | BE104: 0 | BF104: =+IF(AZ104=0,AY104,AZ104)+BE104 -> 46550 | BH104: =+BF104-BD104 -> 175 | BJ104: =+BK104-BL104 -> 46375 | BK104: =+BQ104 -> 46375 | BL104: 0 | BM104: =+IF(BG104=0,BF104,BG104)+BL104 -> 46550 | BO104: =+BM104-BK104 -> 175 | BQ104: =+BR104-BS104 -> 46375 | BR104: =+BX104 -> 46382 | BS104: 7 | BT104: =+IF(BN104=0,BM104,BN104)+BS104 -> 46557 | BV104: =+BT104-BR104 -> 175 | BW104: FDM1150 | BX104: 46382 | BY104: =+BT104-BX104 -> 175
